Workbook
Name Category_List: Lists!$B$2:$B$4
Name Department_List: Lists!$E$2:$E$7
Name Equipment_List: Lists!$A$2:$A$53
Name Shift_List: Lists!$C$2:$C$3
Name Shift_List: Lists!$C$2:$C$3
Name UOM_List: Lists!$D$2:$D$17

Sheet Master Dashboard
B1: INVENTORY & NON INVENTORY DASHBOARD
B2: LOTTE KOLSON PVT LTD
B4: Inventory Stock Value (PKR) | D4: Non Inventory Stock Value (PKR) | F4: Total Stock Value (PKR) | H4: QUICK DECISION BOARD | I4: Current | J4: Signal | K4: Next Action | L4: Owner
B5: =SUM(Inventory!J4:J1002) -> 14080023 | D5: =SUM('Non Inventory'!J4:J997) -> 8997266.4 | F5: =SUM(B5:E5) -> 23077289 | H5: Issuance Gap | I5: =$L$22-$G$22 -> 1672430.4 | J5: =IF(I5>0,"Immediate",IF(I5=0,"Balanced","OK")) -> Immediate | K5: =IF(J5="Immediate","Control outward issuance","Maintain normal flow") -> Control outward issuance | L5: Store / Finance
H6: Top Pressure Category | I6: {=INDEX($B$77:$B$80,MATCH(MAX(ABS($J$77:$J$80)),ABS($J$77:$J$80),0))} -> Inventory | J6: =INDEX($K$77:$K$80,MATCH(I6,$B$77:$B$80,0)) -> High Pressure | K6: =INDEX($L$77:$L$80,MATCH(I6,$B$77:$B$80,0)) -> Review issuance control | L6: Procurement
B7: Total Inward Value (PKR) | D7: Total Issuance Value (PKR) | H7: Machine Focus | I7: =COUNTIF($J$31:$J$38,"Focus") -> 2 | J7: =IF(I7>=2,"Priority",IF(I7=1,"Watch","OK")) -> Priority | K7: =IF(J7="Priority","Review focus machines","Monitor machine trend") -> Review focus machines | L7: Maintenance
B8: =SUM('Daily Inward'!J4:J994) -> 4028137 | D8: =SUM('Daily Issuance'!O4:O998) -> 5700567.4 | H8: Data Readiness | I8: =COUNTIF($L$33:$L$38,"No Data") -> 6 | J8: =IF(I8>=3,"Update Required",IF(I8=0,"Complete","Watch")) -> Update Required | K8: =IF(J8="Update Required","Update future month data","Keep monthly refresh") -> Update future month data | L8: Reporting
B10: MONTH WISE PRICE SUMMARY (MAY 2026 - DEC 2026)
B11: Inward & Issuance Price Value by Inventory / Non Inventory
B12: INWARD PRICE VALUE (PKR) | H12: ISSUANCE PRICE VALUE (PKR)
B13: Month | C13: Inventory Inward | D13: Non Inventory Inward | E13: Services | F13: PattyCash | G13: Total Inward | H13: Inventory Issuance | I13: Non Inventory Issuance | J13: Services | K13: Patty Cash | L13: Total Issuance
B14: May 2026 | C14: =SUMIFS('Daily Inward'!$J$4:$J$991,'Daily Inward'!$E$4:$E$991,"Inventory",'Daily Inward'!$B$4:$B$991,">="&DATE(2026,5,1),'Daily Inward'!$B$4:$B$991,"<"&EDATE(DATE(2026,5,1),1)) -> 1086500 | D14: =SUMIFS('Daily Inward'!$J$4:$J$1048576,'Daily Inward'!$E$4:$E$1048576,"Non Inventory",'Daily Inward'!$B$4:$B$1048576,">="&DATE(2026,5,1),'Daily Inward'!$B$4:$B$1048576,"<"&EDATE(DATE(2026,5,1),1)) -> 1018303 | E14: =SUMIFS('Daily Inward'!$J:$J,'Daily Inward'!$E:$E,"Services",'Daily Inward'!$B:$B,">="&DATE(2026,5,1),'Daily Inward'!$B:$B,"<"&EDATE(DATE(2026,5,1),1)) -> 785200 | F14: =SUMIFS('Daily Inward'!$J:$J,'Daily Inward'!$E:$E,"Patty Cash",'Daily Inward'!$B:$B,">="&DATE(2026,5,1),'Daily Inward'!$B:$B,"<"&EDATE(DATE(2026,5,1),1)) -> 14496.56 | G14: =SUM(C14:F14) -> 2904499.6 | H14: =SUMIFS('Daily Issuance'!$O:$O,'Daily Issuance'!$E:$E,"Inventory",'Daily Issuance'!$B:$B,">="&DATE(2026,5,1),'Daily Issuance'!$B:$B,"<"&EDATE(DATE(2026,5,1),1)) -> 1717496 | I14: =SUMIFS('Daily Issuance'!$O:$O,'Daily Issuance'!$E:$E,"Non Inventory",'Daily Issuance'!$B:$B,">="&DATE(2026,5,1),'Daily Issuance'!$B:$B,"<"&EDATE(DATE(2026,5,1),1)) -> 352080 | J14: =SUMIFS('Daily Issuance'!$O:$O,'Daily Issuance'!$E:$E,"Services",'Daily Issuance'!$B:$B,">="&DATE(2026,5,1),'Daily Issuance'!$B:$B,"<"&EDATE(DATE(2026,5,1),1)) -> 785200 | K14: =SUMIFS('Daily Issuance'!$O:$O,'Daily Issuance'!$E:$E,"Patty Cash",'Daily Issuance'!$B:$B,">="&DATE(2026,5,1),'Daily Issuance'!$B:$B,"<"&EDATE(DATE(2026,5,1),1)) -> 16108.96 | L14: =SUM(H14:K14) -> 2870885
B15: Jun 2026 | C15: =SUMIFS('Daily Inward'!$J:$J,'Daily Inward'!$E:$E,"Inventory",'Daily Inward'!$B:$B,">="&DATE(2026,6,1),'Daily Inward'!$B:$B,"<"&EDATE(DATE(2026,6,1),1)) -> 0 | D15: =SUMIFS('Daily Inward'!$J:$J,'Daily Inward'!$E:$E,"Non Inventory",'Daily Inward'!$B:$B,">="&DATE(2026,6,1),'Daily Inward'!$B:$B,"<"&EDATE(DATE(2026,6,1),1)) -> 716382.81 | E15: =SUMIFS('Daily Inward'!$J:$J,'Daily Inward'!$E:$E,"Services",'Daily Inward'!$B:$B,">="&DATE(2026,6,1),'Daily Inward'!$B:$B,"<"&EDATE(DATE(2026,6,1),1)) -> 398000 | F15: =SUMIFS('Daily Inward'!$J:$J,'Daily Inward'!$E:$E,"Patty Cash",'Daily Inward'!$B:$B,">="&DATE(2026,6,1),'Daily Inward'!$B:$B,"<"&EDATE(DATE(2026,6,1),1)) -> 9254.6489 | G15: =SUM(C15:F15) -> 1123637.5 | H15: =SUMIFS('Daily Issuance'!$O:$O,'Daily Issuance'!$E:$E,"Inventory",'Daily Issuance'!$B:$B,">="&DATE(2026,6,1),'Daily Issuance'!$B:$B,"<"&EDATE(DATE(2026,6,1),1)) -> 1621118 | I15: =SUMIFS('Daily Issuance'!$O:$O,'Daily Issuance'!$E:$E,"Non Inventory",'Daily Issuance'!$B:$B,">="&DATE(2026,6,1),'Daily Issuance'!$B:$B,"<"&EDATE(DATE(2026,6,1),1)) -> 801531.81 | J15: =SUMIFS('Daily Issuance'!$O:$O,'Daily Issuance'!$E:$E,"Services",'Daily Issuance'!$B:$B,">="&DATE(2026,6,1),'Daily Issuance'!$B:$B,"<"&EDATE(DATE(2026,6,1),1)) -> 398000 | K15: =SUMIFS('Daily Issuance'!$O:$O,'Daily Issuance'!$E:$E,"Patty Cash",'Daily Issuance'!$B:$B,">="&DATE(2026,6,1),'Daily Issuance'!$B:$B,"<"&EDATE(DATE(2026,6,1),1)) -> 9032.6489 | L15: =SUM(H15:K15) -> 2829682.5
B16: Jul 2026 | C16: =SUMIFS('Daily Inward'!$J:$J,'Daily Inward'!$E:$E,"Inventory",'Daily Inward'!$B:$B,">="&DATE(2026,7,1),'Daily Inward'!$B:$B,"<"&EDATE(DATE(2026,7,1),1)) -> 0 | D16: =SUMIFS('Daily Inward'!$J:$J,'Daily Inward'!$E:$E,"Non Inventory",'Daily Inward'!$B:$B,">="&DATE(2026,7,1),'Daily Inward'!$B:$B,"<"&EDATE(DATE(2026,7,1),1)) -> 0 | E16: =SUMIFS('Daily Inward'!$J:$J,'Daily Inward'!$E:$E,"Services",'Daily Inward'!$B:$B,">="&DATE(2026,7,1),'Daily Inward'!$B:$B,"<"&EDATE(DATE(2026,7,1),1)) -> 0 | F16: =SUMIFS('Daily Inward'!$J:$J,'Daily Inward'!$E:$E,"Patty Cash",'Daily Inward'!$B:$B,">="&DATE(2026,7,1),'Daily Inward'!$B:$B,"<"&EDATE(DATE(2026,7,1),1)) -> 0 | G16: =SUM(C16:F16) -> 0 | H16: =SUMIFS('Daily Issuance'!$O:$O,'Daily Issuance'!$E:$E,"Inventory",'Daily Issuance'!$B:$B,">="&DATE(2026,7,1),'Daily Issuance'!$B:$B,"<"&EDATE(DATE(2026,7,1),1)) -> 0 | I16: =SUMIFS('Daily Issuance'!$O:$O,'Daily Issuance'!$E:$E,"Non Inventory",'Daily Issuance'!$B:$B,">="&DATE(2026,7,1),'Daily Issuance'!$B:$B,"<"&EDATE(DATE(2026,7,1),1)) -> 0 | J16: =SUMIFS('Daily Issuance'!$O:$O,'Daily Issuance'!$E:$E,"Services",'Daily Issuance'!$B:$B,">="&DATE(2026,7,1),'Daily Issuance'!$B:$B,"<"&EDATE(DATE(2026,7,1),1)) -> 0 | K16: =SUMIFS('Daily Issuance'!$O:$O,'Daily Issuance'!$E:$E,"Patty Cash",'Daily Issuance'!$B:$B,">="&DATE(2026,7,1),'Daily Issuance'!$B:$B,"<"&EDATE(DATE(2026,7,1),1)) -> 0 | L16: =SUM(H16:K16) -> 0
B17: Aug 2026 | C17: =SUMIFS('Daily Inward'!$J:$J,'Daily Inward'!$E:$E,"Inventory",'Daily Inward'!$B:$B,">="&DATE(2026,8,1),'Daily Inward'!$B:$B,"<"&EDATE(DATE(2026,8,1),1)) -> 0 | D17: =SUMIFS('Daily Inward'!$J:$J,'Daily Inward'!$E:$E,"Non Inventory",'Daily Inward'!$B:$B,">="&DATE(2026,8,1),'Daily Inward'!$B:$B,"<"&EDATE(DATE(2026,8,1),1)) -> 0 | E17: =SUMIFS('Daily Inward'!$J:$J,'Daily Inward'!$E:$E,"Services",'Daily Inward'!$B:$B,">="&DATE(2026,8,1),'Daily Inward'!$B:$B,"<"&EDATE(DATE(2026,8,1),1)) -> 0 | F17: =SUMIFS('Daily Inward'!$J:$J,'Daily Inward'!$E:$E,"Patty Cash",'Daily Inward'!$B:$B,">="&DATE(2026,8,1),'Daily Inward'!$B:$B,"<"&EDATE(DATE(2026,8,1),1)) -> 0 | G17: =SUM(C17:F17) -> 0 | H17: =SUMIFS('Daily Issuance'!$O:$O,'Daily Issuance'!$E:$E,"Inventory",'Daily Issuance'!$B:$B,">="&DATE(2026,8,1),'Daily Issuance'!$B:$B,"<"&EDATE(DATE(2026,8,1),1)) -> 0 | I17: =SUMIFS('Daily Issuance'!$O:$O,'Daily Issuance'!$E:$E,"Non Inventory",'Daily Issuance'!$B:$B,">="&DATE(2026,8,1),'Daily Issuance'!$B:$B,"<"&EDATE(DATE(2026,8,1),1)) -> 0 | J17: =SUMIFS('Daily Issuance'!$O:$O,'Daily Issuance'!$E:$E,"Services",'Daily Issuance'!$B:$B,">="&DATE(2026,8,1),'Daily Issuance'!$B:$B,"<"&EDATE(DATE(2026,8,1),1)) -> 0 | K17: =SUMIFS('Daily Issuance'!$O:$O,'Daily Issuance'!$E:$E,"Patty Cash",'Daily Issuance'!$B:$B,">="&DATE(2026,8,1),'Daily Issuance'!$B:$B,"<"&EDATE(DATE(2026,8,1),1)) -> 0 | L17: =SUM(H17:K17) -> 0
B18: Sep 2026 | C18: =SUMIFS('Daily Inward'!$J:$J,'Daily Inward'!$E:$E,"Inventory",'Daily Inward'!$B:$B,">="&DATE(2026,9,1),'Daily Inward'!$B:$B,"<"&EDATE(DATE(2026,9,1),1)) -> 0 | D18: =SUMIFS('Daily Inward'!$J:$J,'Daily Inward'!$E:$E,"Non Inventory",'Daily Inward'!$B:$B,">="&DATE(2026,9,1),'Daily Inward'!$B:$B,"<"&EDATE(DATE(2026,9,1),1)) -> 0 | E18: =SUMIFS('Daily Inward'!$J:$J,'Daily Inward'!$E:$E,"Services",'Daily Inward'!$B:$B,">="&DATE(2026,9,1),'Daily Inward'!$B:$B,"<"&EDATE(DATE(2026,9,1),1)) -> 0 | F18: =SUMIFS('Daily Inward'!$J:$J,'Daily Inward'!$E:$E,"Patty Cash",'Daily Inward'!$B:$B,">="&DATE(2026,9,1),'Daily Inward'!$B:$B,"<"&EDATE(DATE(2026,9,1),1)) -> 0 | G18: =SUM(C18:F18) -> 0 | H18: =SUMIFS('Daily Issuance'!$O:$O,'Daily Issuance'!$E:$E,"Inventory",'Daily Issuance'!$B:$B,">="&DATE(2026,9,1),'Daily Issuance'!$B:$B,"<"&EDATE(DATE(2026,9,1),1)) -> 0 | I18: =SUMIFS('Daily Issuance'!$O:$O,'Daily Issuance'!$E:$E,"Non Inventory",'Daily Issuance'!$B:$B,">="&DATE(2026,9,1),'Daily Issuance'!$B:$B,"<"&EDATE(DATE(2026,9,1),1)) -> 0 | J18: =SUMIFS('Daily Issuance'!$O:$O,'Daily Issuance'!$E:$E,"Services",'Daily Issuance'!$B:$B,">="&DATE(2026,9,1),'Daily Issuance'!$B:$B,"<"&EDATE(DATE(2026,9,1),1)) -> 0 | K18: =SUMIFS('Daily Issuance'!$O:$O,'Daily Issuance'!$E:$E,"Patty Cash",'Daily Issuance'!$B:$B,">="&DATE(2026,9,1),'Daily Issuance'!$B:$B,"<"&EDATE(DATE(2026,9,1),1)) -> 0 | L18: =SUM(H18:K18) -> 0
B19: Oct 2026 | C19: =SUMIFS('Daily Inward'!$J:$J,'Daily Inward'!$E:$E,"Inventory",'Daily Inward'!$B:$B,">="&DATE(2026,10,1),'Daily Inward'!$B:$B,"<"&EDATE(DATE(2026,10,1),1)) -> 0 | D19: =SUMIFS('Daily Inward'!$J:$J,'Daily Inward'!$E:$E,"Non Inventory",'Daily Inward'!$B:$B,">="&DATE(2026,10,1),'Daily Inward'!$B:$B,"<"&EDATE(DATE(2026,10,1),1)) -> 0 | E19: =SUMIFS('Daily Inward'!$J:$J,'Daily Inward'!$E:$E,"Services",'Daily Inward'!$B:$B,">="&DATE(2026,10,1),'Daily Inward'!$B:$B,"<"&EDATE(DATE(2026,10,1),1)) -> 0 | F19: =SUMIFS('Daily Inward'!$J:$J,'Daily Inward'!$E:$E,"Patty Cash",'Daily Inward'!$B:$B,">="&DATE(2026,10,1),'Daily Inward'!$B:$B,"<"&EDATE(DATE(2026,10,1),1)) -> 0 | G19: =SUM(C19:F19) -> 0 | H19: =SUMIFS('Daily Issuance'!$O:$O,'Daily Issuance'!$E:$E,"Inventory",'Daily Issuance'!$B:$B,">="&DATE(2026,10,1),'Daily Issuance'!$B:$B,"<"&EDATE(DATE(2026,10,1),1)) -> 0 | I19: =SUMIFS('Daily Issuance'!$O:$O,'Daily Issuance'!$E:$E,"Non Inventory",'Daily Issuance'!$B:$B,">="&DATE(2026,10,1),'Daily Issuance'!$B:$B,"<"&EDATE(DATE(2026,10,1),1)) -> 0 | J19: =SUMIFS('Daily Issuance'!$O:$O,'Daily Issuance'!$E:$E,"Services",'Daily Issuance'!$B:$B,">="&DATE(2026,10,1),'Daily Issuance'!$B:$B,"<"&EDATE(DATE(2026,10,1),1)) -> 0 | K19: =SUMIFS('Daily Issuance'!$O:$O,'Daily Issuance'!$E:$E,"Patty Cash",'Daily Issuance'!$B:$B,">="&DATE(2026,10,1),'Daily Issuance'!$B:$B,"<"&EDATE(DATE(2026,10,1),1)) -> 0 | L19: =SUM(H19:K19) -> 0
B20: Nov 2026 | C20: =SUMIFS('Daily Inward'!$J:$J,'Daily Inward'!$E:$E,"Inventory",'Daily Inward'!$B:$B,">="&DATE(2026,11,1),'Daily Inward'!$B:$B,"<"&EDATE(DATE(2026,11,1),1)) -> 0 | D20: =SUMIFS('Daily Inward'!$J:$J,'Daily Inward'!$E:$E,"Non Inventory",'Daily Inward'!$B:$B,">="&DATE(2026,11,1),'Daily Inward'!$B:$B,"<"&EDATE(DATE(2026,11,1),1)) -> 0 | E20: =SUMIFS('Daily Inward'!$J:$J,'Daily Inward'!$E:$E,"Services",'Daily Inward'!$B:$B,">="&DATE(2026,11,1),'Daily Inward'!$B:$B,"<"&EDATE(DATE(2026,11,1),1)) -> 0 | F20: =SUMIFS('Daily Inward'!$J:$J,'Daily Inward'!$E:$E,"Patty Cash",'Daily Inward'!$B:$B,">="&DATE(2026,11,1),'Daily Inward'!$B:$B,"<"&EDATE(DATE(2026,11,1),1)) -> 0 | G20: =SUM(C20:F20) -> 0 | H20: =SUMIFS('Daily Issuance'!$O:$O,'Daily Issuance'!$E:$E,"Inventory",'Daily Issuance'!$B:$B,">="&DATE(2026,11,1),'Daily Issuance'!$B:$B,"<"&EDATE(DATE(2026,11,1),1)) -> 0 | I20: =SUMIFS('Daily Issuance'!$O:$O,'Daily Issuance'!$E:$E,"Non Inventory",'Daily Issuance'!$B:$B,">="&DATE(2026,11,1),'Daily Issuance'!$B:$B,"<"&EDATE(DATE(2026,11,1),1)) -> 0 | J20: =SUMIFS('Daily Issuance'!$O:$O,'Daily Issuance'!$E:$E,"Services",'Daily Issuance'!$B:$B,">="&DATE(2026,11,1),'Daily Issuance'!$B:$B,"<"&EDATE(DATE(2026,11,1),1)) -> 0 | K20: =SUMIFS('Daily Issuance'!$O:$O,'Daily Issuance'!$E:$E,"Patty Cash",'Daily Issuance'!$B:$B,">="&DATE(2026,11,1),'Daily Issuance'!$B:$B,"<"&EDATE(DATE(2026,11,1),1)) -> 0 | L20: =SUM(H20:K20) -> 0
B21: Dec 2026 | C21: =SUMIFS('Daily Inward'!$J:$J,'Daily Inward'!$E:$E,"Inventory",'Daily Inward'!$B:$B,">="&DATE(2026,12,1),'Daily Inward'!$B:$B,"<"&EDATE(DATE(2026,12,1),1)) -> 0 | D21: =SUMIFS('Daily Inward'!$J:$J,'Daily Inward'!$E:$E,"Non Inventory",'Daily Inward'!$B:$B,">="&DATE(2026,12,1),'Daily Inward'!$B:$B,"<"&EDATE(DATE(2026,12,1),1)) -> 0 | E21: =SUMIFS('Daily Inward'!$J:$J,'Daily Inward'!$E:$E,"Services",'Daily Inward'!$B:$B,">="&DATE(2026,12,1),'Daily Inward'!$B:$B,"<"&EDATE(DATE(2026,12,1),1)) -> 0 | F21: =SUMIFS('Daily Inward'!$J:$J,'Daily Inward'!$E:$E,"Patty Cash",'Daily Inward'!$B:$B,">="&DATE(2026,12,1),'Daily Inward'!$B:$B,"<"&EDATE(DATE(2026,12,1),1)) -> 0 | G21: =SUM(C21:F21) -> 0 | H21: =SUMIFS('Daily Issuance'!$O:$O,'Daily Issuance'!$E:$E,"Inventory",'Daily Issuance'!$B:$B,">="&DATE(2026,12,1),'Daily Issuance'!$B:$B,"<"&EDATE(DATE(2026,12,1),1)) -> 0 | I21: =SUMIFS('Daily Issuance'!$O:$O,'Daily Issuance'!$E:$E,"Non Inventory",'Daily Issuance'!$B:$B,">="&DATE(2026,12,1),'Daily Issuance'!$B:$B,"<"&EDATE(DATE(2026,12,1),1)) -> 0 | J21: =SUMIFS('Daily Issuance'!$O:$O,'Daily Issuance'!$E:$E,"Services",'Daily Issuance'!$B:$B,">="&DATE(2026,12,1),'Daily Issuance'!$B:$B,"<"&EDATE(DATE(2026,12,1),1)) -> 0 | K21: =SUMIFS('Daily Issuance'!$O:$O,'Daily Issuance'!$E:$E,"Patty Cash",'Daily Issuance'!$B:$B,">="&DATE(2026,12,1),'Daily Issuance'!$B:$B,"<"&EDATE(DATE(2026,12,1),1)) -> 0 | L21: =SUM(H21:K21) -> 0
B22: GRAND TOTAL | C22: =SUM(C14:C21) -> 1086500 | D22: =SUM(D14:D21) -> 1734685.8 | E22: =SUM(E14:E21) -> 1183200 | F22: =SUM(F14:F21) -> 23751.208 | G22: =SUM(G14:G21) -> 4028137 | H22: =SUM(H14:H21) -> 3338614 | I22: =SUM(I14:I21) -> 1153611.8 | J22: =SUM(J14:J21) -> 1183200 | ... L22: =SUM(L14:L21) -> 5700567.4
B24: MONTHLY MACHINE HIGH / LOW AUTO SYSTEM
B26: Total Machine Work | C26: Active Months | D26: Highest Month | E26: Lowest Active Month | F26: Machines Tracked | G26: Months Needing Focus | I26: How to read
B27: =SUM('Machine Issuance Dashboard'!$AP$6:$AP$58) -> 5691603.8 | C27: =COUNTIF(C31:C38,">0") -> 2 | D27: =INDEX(B31:B38,MATCH(MAX(C31:C38),C31:C38,0)) -> May | E27: {=IFERROR(INDEX(B31:B38,MATCH(MIN(_xlfn._xlws.FILTER(C31:C38,C31:C38>0)),C31:C38,0)),"No Data")} -> Jun | F27: =COUNTA('Machine Issuance Dashboard'!$A$6:$A$57) -> 52 | G27: =COUNTIF(J31:J38,"Focus") -> 2 | I27: High machine | J27: Month mein sab se zyada work/spend | K27: Red flag | L27: Check reason / maintenance
I28: Low active machine | J28: Zero ko ignore karke lowest active | K28: Amber | L28: Verify usage / idle issue
I29: No Data | J29: Month mein machine work nahi mila | K29: Gray | L29: Source update required
B30: Month | C30: Total Work | D30: Most Work Machine | E30: Most Amount | F30: Least Active Machine | G30: Least Amount | I30: Top Share | J30: Focus Level | K30: Quick Action | L30: Data Check
B31: May | C31: =SUM('Machine Issuance Dashboard'!$F$6:$F$57) -> 2863371 | D31: =IF(C31=0,"No Data",INDEX('Machine Issuance Dashboard'!$A$6:$A$57,MATCH(MAX('Machine Issuance Dashboard'!$F$6:$F$57),'Machine Issuance Dashboard'!$F$6:$F$57,0))) -> Auto Fryer | E31: =IF(C31=0,0,MAX('Machine Issuance Dashboard'!$F$6:$F$57)) -> 1232577 | F31: {=IF(C31=0,"No Data",IFERROR(INDEX('Machine Issuance Dashboard'!$A$6:$A$57,MATCH(MIN(_xlfn._xlws.FILTER('Machine Issuance Dashboard'!$F$6:$F$57,'Machine Issuance Dashboard'!$F$6:$F$57>0)),'Machine Issuance Dashboard'!$F$6:$F$57,0)),"No Active"))} -> DB Water Chiller | G31: {=IF(C31=0,0,IFERROR(MIN(_xlfn._xlws.FILTER('Machine Issuance Dashboard'!$F$6:$F$57,'Machine Issuance Dashboard'!$F$6:$F$57>0)),0))} -> 183 | I31: =IF(C31=0,0,E31/C31) -> 0.4304636 | J31: =IF(C31=0,"No Data",IF(I31>=40%,"Focus",IF(I31>=25%,"Watch","Normal"))) -> Focus | K31: =IF(J31="Focus","Check top machine immediately",IF(J31="Watch","Monitor monthly",IF(J31="Normal","OK","Update source"))) -> Check top machine immediately | L31: =IF(C31=0,"No Data","OK") -> OK
B32: Jun | C32: =SUM('Machine Issuance Dashboard'!$K$6:$K$57) -> 2303222 | D32: =IF(C32=0,"No Data",INDEX('Machine Issuance Dashboard'!$A$6:$A$57,MATCH(MAX('Machine Issuance Dashboard'!$K$6:$K$57),'Machine Issuance Dashboard'!$K$6:$K$57,0))) -> Ishida No: 02 | E32: =IF(C32=0,0,MAX('Machine Issuance Dashboard'!$K$6:$K$57)) -> 1007768 | F32: {=IF(C32=0,"No Data",IFERROR(INDEX('Machine Issuance Dashboard'!$A$6:$A$57,MATCH(MIN(_xlfn._xlws.FILTER('Machine Issuance Dashboard'!$K$6:$K$57,'Machine Issuance Dashboard'!$K$6:$K$57>0)),'Machine Issuance Dashboard'!$K$6:$K$57,0)),"No Active"))} -> Hand Pallet | G32: {=IF(C32=0,0,IFERROR(MIN(_xlfn._xlws.FILTER('Machine Issuance Dashboard'!$K$6:$K$57,'Machine Issuance Dashboard'!$K$6:$K$57>0)),0))} -> 45 | I32: =IF(C32=0,0,E32/C32) -> 0.43754705 | J32: =IF(C32=0,"No Data",IF(I32>=40%,"Focus",IF(I32>=25%,"Watch","Normal"))) -> Focus | K32: =IF(J32="Focus","Check top machine immediately",IF(J32="Watch","Monitor monthly",IF(J32="Normal","OK","Update source"))) -> Check top machine immediately | L32: =IF(C32=0,"No Data","OK") -> OK
B33: Jul | C33: =SUM('Machine Issuance Dashboard'!$P$6:$P$57) -> 0 | D33: =IF(C33=0,"No Data",INDEX('Machine Issuance Dashboard'!$A$6:$A$57,MATCH(MAX('Machine Issuance Dashboard'!$P$6:$P$57),'Machine Issuance Dashboard'!$P$6:$P$57,0))) -> No Data | E33: =IF(C33=0,0,MAX('Machine Issuance Dashboard'!$P$6:$P$57)) -> 0 | F33: {=IF(C33=0,"No Data",IFERROR(INDEX('Machine Issuance Dashboard'!$A$6:$A$57,MATCH(MIN(_xlfn._xlws.FILTER('Machine Issuance Dashboard'!$P$6:$P$57,'Machine Issuance Dashboard'!$P$6:$P$57>0)),'Machine Issuance Dashboard'!$P$6:$P$57,0)),"No Active"))} -> No Data | G33: {=IF(C33=0,0,IFERROR(MIN(_xlfn._xlws.FILTER('Machine Issuance Dashboard'!$P$6:$P$57,'Machine Issuance Dashboard'!$P$6:$P$57>0)),0))} -> 0 | I33: =IF(C33=0,0,E33/C33) -> 0 | J33: =IF(C33=0,"No Data",IF(I33>=40%,"Focus",IF(I33>=25%,"Watch","Normal"))) -> No Data | K33: =IF(J33="Focus","Check top machine immediately",IF(J33="Watch","Monitor monthly",IF(J33="Normal","OK","Update source"))) -> Update source | L33: =IF(C33=0,"No Data","OK") -> No Data
B34: Aug | C34: =SUM('Machine Issuance Dashboard'!$U$6:$U$57) -> 0 | D34: =IF(C34=0,"No Data",INDEX('Machine Issuance Dashboard'!$A$6:$A$57,MATCH(MAX('Machine Issuance Dashboard'!$U$6:$U$57),'Machine Issuance Dashboard'!$U$6:$U$57,0))) -> No Data | E34: =IF(C34=0,0,MAX('Machine Issuance Dashboard'!$U$6:$U$57)) -> 0 | F34: {=IF(C34=0,"No Data",IFERROR(INDEX('Machine Issuance Dashboard'!$A$6:$A$57,MATCH(MIN(_xlfn._xlws.FILTER('Machine Issuance Dashboard'!$U$6:$U$57,'Machine Issuance Dashboard'!$U$6:$U$57>0)),'Machine Issuance Dashboard'!$U$6:$U$57,0)),"No Active"))} -> No Data | G34: {=IF(C34=0,0,IFERROR(MIN(_xlfn._xlws.FILTER('Machine Issuance Dashboard'!$U$6:$U$57,'Machine Issuance Dashboard'!$U$6:$U$57>0)),0))} -> 0 | I34: =IF(C34=0,0,E34/C34) -> 0 | J34: =IF(C34=0,"No Data",IF(I34>=40%,"Focus",IF(I34>=25%,"Watch","Normal"))) -> No Data | K34: =IF(J34="Focus","Check top machine immediately",IF(J34="Watch","Monitor monthly",IF(J34="Normal","OK","Update source"))) -> Update source | L34: =IF(C34=0,"No Data","OK") -> No Data
B35: Sep | C35: =SUM('Machine Issuance Dashboard'!$Z$6:$Z$57) -> 0 | D35: =IF(C35=0,"No Data",INDEX('Machine Issuance Dashboard'!$A$6:$A$57,MATCH(MAX('Machine Issuance Dashboard'!$Z$6:$Z$57),'Machine Issuance Dashboard'!$Z$6:$Z$57,0))) -> No Data | E35: =IF(C35=0,0,MAX('Machine Issuance Dashboard'!$Z$6:$Z$57)) -> 0 | F35: {=IF(C35=0,"No Data",IFERROR(INDEX('Machine Issuance Dashboard'!$A$6:$A$57,MATCH(MIN(_xlfn._xlws.FILTER('Machine Issuance Dashboard'!$Z$6:$Z$57,'Machine Issuance Dashboard'!$Z$6:$Z$57>0)),'Machine Issuance Dashboard'!$Z$6:$Z$57,0)),"No Active"))} -> No Data | G35: {=IF(C35=0,0,IFERROR(MIN(_xlfn._xlws.FILTER('Machine Issuance Dashboard'!$Z$6:$Z$57,'Machine Issuance Dashboard'!$Z$6:$Z$57>0)),0))} -> 0 | I35: =IF(C35=0,0,E35/C35) -> 0 | J35: =IF(C35=0,"No Data",IF(I35>=40%,"Focus",IF(I35>=25%,"Watch","Normal"))) -> No Data | K35: =IF(J35="Focus","Check top machine immediately",IF(J35="Watch","Monitor monthly",IF(J35="Normal","OK","Update source"))) -> Update source | L35: =IF(C35=0,"No Data","OK") -> No Data
B36: Oct | C36: =SUM('Machine Issuance Dashboard'!$AE$6:$AE$57) -> 0 | D36: =IF(C36=0,"No Data",INDEX('Machine Issuance Dashboard'!$A$6:$A$57,MATCH(MAX('Machine Issuance Dashboard'!$AE$6:$AE$57),'Machine Issuance Dashboard'!$AE$6:$AE$57,0))) -> No Data | E36: =IF(C36=0,0,MAX('Machine Issuance Dashboard'!$AE$6:$AE$57)) -> 0 | F36: {=IF(C36=0,"No Data",IFERROR(INDEX('Machine Issuance Dashboard'!$A$6:$A$57,MATCH(MIN(_xlfn._xlws.FILTER('Machine Issuance Dashboard'!$AE$6:$AE$57,'Machine Issuance Dashboard'!$AE$6:$AE$57>0)),'Machine Issuance Dashboard'!$AE$6:$AE$57,0)),"No Active"))} -> No Data | G36: {=IF(C36=0,0,IFERROR(MIN(_xlfn._xlws.FILTER('Machine Issuance Dashboard'!$AE$6:$AE$57,'Machine Issuance Dashboard'!$AE$6:$AE$57>0)),0))} -> 0 | I36: =IF(C36=0,0,E36/C36) -> 0 | J36: =IF(C36=0,"No Data",IF(I36>=40%,"Focus",IF(I36>=25%,"Watch","Normal"))) -> No Data | K36: =IF(J36="Focus","Check top machine immediately",IF(J36="Watch","Monitor monthly",IF(J36="Normal","OK","Update source"))) -> Update source | L36: =IF(C36=0,"No Data","OK") -> No Data
B37: Nov | C37: =SUM('Machine Issuance Dashboard'!$AJ$6:$AJ$57) -> 0 | D37: =IF(C37=0,"No Data",INDEX('Machine Issuance Dashboard'!$A$6:$A$57,MATCH(MAX('Machine Issuance Dashboard'!$AJ$6:$AJ$57),'Machine Issuance Dashboard'!$AJ$6:$AJ$57,0))) -> No Data | E37: =IF(C37=0,0,MAX('Machine Issuance Dashboard'!$AJ$6:$AJ$57)) -> 0 | F37: {=IF(C37=0,"No Data",IFERROR(INDEX('Machine Issuance Dashboard'!$A$6:$A$57,MATCH(MIN(_xlfn._xlws.FILTER('Machine Issuance Dashboard'!$AJ$6:$AJ$57,'Machine Issuance Dashboard'!$AJ$6:$AJ$57>0)),'Machine Issuance Dashboard'!$AJ$6:$AJ$57,0)),"No Active"))} -> No Data | G37: {=IF(C37=0,0,IFERROR(MIN(_xlfn._xlws.FILTER('Machine Issuance Dashboard'!$AJ$6:$AJ$57,'Machine Issuance Dashboard'!$AJ$6:$AJ$57>0)),0))} -> 0 | I37: =IF(C37=0,0,E37/C37) -> 0 | J37: =IF(C37=0,"No Data",IF(I37>=40%,"Focus",IF(I37>=25%,"Watch","Normal"))) -> No Data | K37: =IF(J37="Focus","Check top machine immediately",IF(J37="Watch","Monitor monthly",IF(J37="Normal","OK","Update source"))) -> Update source | L37: =IF(C37=0,"No Data","OK") -> No Data
B38: Dec | C38: =SUM('Machine Issuance Dashboard'!$AO$6:$AO$57) -> 0 | D38: =IF(C38=0,"No Data",INDEX('Machine Issuance Dashboard'!$A$6:$A$57,MATCH(MAX('Machine Issuance Dashboard'!$AO$6:$AO$57),'Machine Issuance Dashboard'!$AO$6:$AO$57,0))) -> No Data | E38: =IF(C38=0,0,MAX('Machine Issuance Dashboard'!$AO$6:$AO$57)) -> 0 | F38: {=IF(C38=0,"No Data",IFERROR(INDEX('Machine Issuance Dashboard'!$A$6:$A$57,MATCH(MIN(_xlfn._xlws.FILTER('Machine Issuance Dashboard'!$AO$6:$AO$57,'Machine Issuance Dashboard'!$AO$6:$AO$57>0)),'Machine Issuance Dashboard'!$AO$6:$AO$57,0)),"No Active"))} -> No Data | G38: {=IF(C38=0,0,IFERROR(MIN(_xlfn._xlws.FILTER('Machine Issuance Dashboard'!$AO$6:$AO$57,'Machine Issuance Dashboard'!$AO$6:$AO$57>0)),0))} -> 0 | I38: =IF(C38=0,0,E38/C38) -> 0 | J38: =IF(C38=0,"No Data",IF(I38>=40%,"Focus",IF(I38>=25%,"Watch","Normal"))) -> No Data | K38: =IF(J38="Focus","Check top machine immediately",IF(J38="Watch","Monitor monthly",IF(J38="Normal","OK","Update source"))) -> Update source | L38: =IF(C38=0,"No Data","OK") -> No Data
B41: TOP 5 MACHINES - FULL YEAR | I41: LOW / IDLE WATCHLIST
B42: Rank | C42: Machine | D42: Year Total | E42: Share | F42: Major Month | G42: Action | I42: Machine | J42: Year Total | K42: Active Months | L42: Status
B43: 1 | C43: =INDEX('Machine Issuance Dashboard'!$A$6:$A$57,MATCH(LARGE('Machine Issuance Dashboard'!$AP$6:$AP$57,B43),'Machine Issuance Dashboard'!$AP$6:$AP$57,0)) -> Auto Fryer | D43: =LARGE('Machine Issuance Dashboard'!$AP$6:$AP$57,B43) -> 1232577 | E43: =D43/$B$27 -> 0.21656058 | F43: {=_xlfn.LET(_xlpm.mach,C43,_xlpm.rowNo,MATCH(_xlpm.mach,'Machine Issuance Dashboard'!$A$6:$A$57,0),_xlpm.vals,CHOOSE({1,2,3,4,5,6,7,8},INDEX('Machine Issuance Dashboard'!$F$6:$F$57,_xlpm.rowNo),INDEX('Machine Issuance Dashboard'!$K$6:$K$57,_xlpm.rowNo),INDEX('Machine Issuance Dashboard'!$P$6:$P$57,_xlpm.rowNo),INDEX('Machine Issuance Dashboard'!$U$6:$U$57,_xlpm.rowNo),INDEX('Machine Issuance Dashboard'!$Z$6:$Z$57,_xlpm.rowNo),INDEX('Machine Issuance Dashboard'!$AE$6:$AE$57,_xlpm.rowNo),INDEX('Machine Issuance Dashboard'!$AJ$6:$AJ$57,_xlpm.rowNo),INDEX('Machine Issuance Dashboard'!$AO$6:$AO$57,_xlpm.rowNo)),INDEX({"May","Jun","Jul","Aug","Sep","Oct","Nov","Dec"},MATCH(MAX(_xlpm.vals),_xlpm.vals,0)))} -> May | G43: =IF(E43>=20%,"Priority check",IF(E43>=10%,"Watch","Normal")) -> Priority check | I43: {=IFERROR(INDEX(_xlfn._xlws.FILTER('Machine Issuance Dashboard'!$A$6:$A$57,'Machine Issuance Dashboard'!$AP$6:$AP$57>0),MATCH(SMALL(_xlfn._xlws.FILTER('Machine Issuance Dashboard'!$AP$6:$AP$57,'Machine Issuance Dashboard'!$AP$6:$AP$57>0),1),_xlfn._xlws.FILTER('Machine Issuance Dashboard'!$AP$6:$AP$57,'Machine Issuance Dashboard'!$AP$6:$AP$57>0),0)),"No Data")} -> Batch Fryer No: 02 | J43: =IFERROR(INDEX('Machine Issuance Dashboard'!$AP$6:$AP$57,MATCH(I43,'Machine Issuance Dashboard'!$A$6:$A$57,0)),0) -> 230 | K43: =IF(I43="No Data",0,--(INDEX('Machine Issuance Dashboard'!$F$6:$F$57,MATCH(I43,'Machine Issuance Dashboard'!$A$6:$A$57,0))>0)+--(INDEX('Machine Issuance Dashboard'!$K$6:$K$57,MATCH(I43,'Machine Issuance Dashboard'!$A$6:$A$57,0))>0)+--(INDEX('Machine Issuance Dashboard'!$P$6:$P$57,MATCH(I43,'Machine Issuance Dashboard'!$A$6:$A$57,0))>0)+--(INDEX('Machine Issuance Dashboard'!$U$6:$U$57,MATCH(I43,'Machine Issuance Dashboard'!$A$6:$A$57,0))>0)+--(INDEX('Machine Issuance Dashboard'!$Z$6:$Z$57,MATCH(I43,'Machine Issuance Dashboard'!$A$6:$A$57,0))>0)+--(INDEX('Machine Issuance Dashboard'!$AE$6:$AE$57,MATCH(I43,'Machine Issuance Dashboard'!$A$6:$A$57,0))>0)+--(INDEX('Machine Issuance Dashboard'!$AJ$6:$AJ$57,MATCH(I43,'Machine Issuance Dashboard'!$A$6:$A$57,0))>0)+--(INDEX('Machine Issuance Dashboard'!$AO$6:$AO$57,MATCH(I43,'Machine Issuance Dashboard'!$A$6:$A$57,0))>0)) -> 1 | L43: =IF(J43=0,"Idle",IF(K43<=1,"Low Use","Active")) -> Low Use
B44: 2 | C44: =INDEX('Machine Issuance Dashboard'!$A$6:$A$57,MATCH(LARGE('Machine Issuance Dashboard'!$AP$6:$AP$57,B44),'Machine Issuance Dashboard'!$AP$6:$AP$57,0)) -> Ishida No: 02 | D44: =LARGE('Machine Issuance Dashboard'!$AP$6:$AP$57,B44) -> 1017774 | E44: =D44/$B$27 -> 0.17882025 | F44: {=_xlfn.LET(_xlpm.mach,C44,_xlpm.rowNo,MATCH(_xlpm.mach,'Machine Issuance Dashboard'!$A$6:$A$57,0),_xlpm.vals,CHOOSE({1,2,3,4,5,6,7,8},INDEX('Machine Issuance Dashboard'!$F$6:$F$57,_xlpm.rowNo),INDEX('Machine Issuance Dashboard'!$K$6:$K$57,_xlpm.rowNo),INDEX('Machine Issuance Dashboard'!$P$6:$P$57,_xlpm.rowNo),INDEX('Machine Issuance Dashboard'!$U$6:$U$57,_xlpm.rowNo),INDEX('Machine Issuance Dashboard'!$Z$6:$Z$57,_xlpm.rowNo),INDEX('Machine Issuance Dashboard'!$AE$6:$AE$57,_xlpm.rowNo),INDEX('Machine Issuance Dashboard'!$AJ$6:$AJ$57,_xlpm.rowNo),INDEX('Machine Issuance Dashboard'!$AO$6:$AO$57,_xlpm.rowNo)),INDEX({"May","Jun","Jul","Aug","Sep","Oct","Nov","Dec"},MATCH(MAX(_xlpm.vals),_xlpm.vals,0)))} -> Jun | G44: =IF(E44>=20%,"Priority check",IF(E44>=10%,"Watch","Normal")) -> Watch | I44: {=IFERROR(INDEX(_xlfn._xlws.FILTER('Machine Issuance Dashboard'!$A$6:$A$57,'Machine Issuance Dashboard'!$AP$6:$AP$57>0),MATCH(SMALL(_xlfn._xlws.FILTER('Machine Issuance Dashboard'!$AP$6:$AP$57,'Machine Issuance Dashboard'!$AP$6:$AP$57>0),2),_xlfn._xlws.FILTER('Machine Issuance Dashboard'!$AP$6:$AP$57,'Machine Issuance Dashboard'!$AP$6:$AP$57>0),0)),"No Data")} -> Korea No: 04 | J44: =IFERROR(INDEX('Machine Issuance Dashboard'!$AP$6:$AP$57,MATCH(I44,'Machine Issuance Dashboard'!$A$6:$A$57,0)),0) -> 450 | K44: =IF(I44="No Data",0,--(INDEX('Machine Issuance Dashboard'!$F$6:$F$57,MATCH(I44,'Machine Issuance Dashboard'!$A$6:$A$57,0))>0)+--(INDEX('Machine Issuance Dashboard'!$K$6:$K$57,MATCH(I44,'Machine Issuance Dashboard'!$A$6:$A$57,0))>0)+--(INDEX('Machine Issuance Dashboard'!$P$6:$P$57,MATCH(I44,'Machine Issuance Dashboard'!$A$6:$A$57,0))>0)+--(INDEX('Machine Issuance Dashboard'!$U$6:$U$57,MATCH(I44,'Machine Issuance Dashboard'!$A$6:$A$57,0))>0)+--(INDEX('Machine Issuance Dashboard'!$Z$6:$Z$57,MATCH(I44,'Machine Issuance Dashboard'!$A$6:$A$57,0))>0)+--(INDEX('Machine Issuance Dashboard'!$AE$6:$AE$57,MATCH(I44,'Machine Issuance Dashboard'!$A$6:$A$57,0))>0)+--(INDEX('Machine Issuance Dashboard'!$AJ$6:$AJ$57,MATCH(I44,'Machine Issuance Dashboard'!$A$6:$A$57,0))>0)+--(INDEX('Machine Issuance Dashboard'!$AO$6:$AO$57,MATCH(I44,'Machine Issuance Dashboard'!$A$6:$A$57,0))>0)) -> 2 | L44: =IF(J44=0,"Idle",IF(K44<=1,"Low Use","Active")) -> Active
B45: 3 | C45: =INDEX('Machine Issuance Dashboard'!$A$6:$A$57,MATCH(LARGE('Machine Issuance Dashboard'!$AP$6:$AP$57,B45),'Machine Issuance Dashboard'!$AP$6:$AP$57,0)) -> Ishida No: 14 | D45: =LARGE('Machine Issuance Dashboard'!$AP$6:$AP$57,B45) -> 501227 | E45: =D45/$B$27 -> 0.088064281 | F45: {=_xlfn.LET(_xlpm.mach,C45,_xlpm.rowNo,MATCH(_xlpm.mach,'Machine Issuance Dashboard'!$A$6:$A$57,0),_xlpm.vals,CHOOSE({1,2,3,4,5,6,7,8},INDEX('Machine Issuance Dashboard'!$F$6:$F$57,_xlpm.rowNo),INDEX('Machine Issuance Dashboard'!$K$6:$K$57,_xlpm.rowNo),INDEX('Machine Issuance Dashboard'!$P$6:$P$57,_xlpm.rowNo),INDEX('Machine Issuance Dashboard'!$U$6:$U$57,_xlpm.rowNo),INDEX('Machine Issuance Dashboard'!$Z$6:$Z$57,_xlpm.rowNo),INDEX('Machine Issuance Dashboard'!$AE$6:$AE$57,_xlpm.rowNo),INDEX('Machine Issuance Dashboard'!$AJ$6:$AJ$57,_xlpm.rowNo),INDEX('Machine Issuance Dashboard'!$AO$6:$AO$57,_xlpm.rowNo)),INDEX({"May","Jun","Jul","Aug","Sep","Oct","Nov","Dec"},MATCH(MAX(_xlpm.vals),_xlpm.vals,0)))} -> Jun | G45: =IF(E45>=20%,"Priority check",IF(E45>=10%,"Watch","Normal")) -> Normal | I45: {=IFERROR(INDEX(_xlfn._xlws.FILTER('Machine Issuance Dashboard'!$A$6:$A$57,'Machine Issuance Dashboard'!$AP$6:$AP$57>0),MATCH(SMALL(_xlfn._xlws.FILTER('Machine Issuance Dashboard'!$AP$6:$AP$57,'Machine Issuance Dashboard'!$AP$6:$AP$57>0),3),_xlfn._xlws.FILTER('Machine Issuance Dashboard'!$AP$6:$AP$57,'Machine Issuance Dashboard'!$AP$6:$AP$57>0),0)),"No Data")} -> Sama No: 04 | J45: =IFERROR(INDEX('Machine Issuance Dashboard'!$AP$6:$AP$57,MATCH(I45,'Machine Issuance Dashboard'!$A$6:$A$57,0)),0) -> 900 | K45: =IF(I45="No Data",0,--(INDEX('Machine Issuance Dashboard'!$F$6:$F$57,MATCH(I45,'Machine Issuance Dashboard'!$A$6:$A$57,0))>0)+--(INDEX('Machine Issuance Dashboard'!$K$6:$K$57,MATCH(I45,'Machine Issuance Dashboard'!$A$6:$A$57,0))>0)+--(INDEX('Machine Issuance Dashboard'!$P$6:$P$57,MATCH(I45,'Machine Issuance Dashboard'!$A$6:$A$57,0))>0)+--(INDEX('Machine Issuance Dashboard'!$U$6:$U$57,MATCH(I45,'Machine Issuance Dashboard'!$A$6:$A$57,0))>0)+--(INDEX('Machine Issuance Dashboard'!$Z$6:$Z$57,MATCH(I45,'Machine Issuance Dashboard'!$A$6:$A$57,0))>0)+--(INDEX('Machine Issuance Dashboard'!$AE$6:$AE$57,MATCH(I45,'Machine Issuance Dashboard'!$A$6:$A$57,0))>0)+--(INDEX('Machine Issuance Dashboard'!$AJ$6:$AJ$57,MATCH(I45,'Machine Issuance Dashboard'!$A$6:$A$57,0))>0)+--(INDEX('Machine Issuance Dashboard'!$AO$6:$AO$57,MATCH(I45,'Machine Issuance Dashboard'!$A$6:$A$57,0))>0)) -> 1 | L45: =IF(J45=0,"Idle",IF(K45<=1,"Low Use","Active")) -> Low Use
B46: 4 | C46: =INDEX('Machine Issuance Dashboard'!$A$6:$A$57,MATCH(LARGE('Machine Issuance Dashboard'!$AP$6:$AP$57,B46),'Machine Issuance Dashboard'!$AP$6:$AP$57,0)) -> LPG Plant | D46: =LARGE('Machine Issuance Dashboard'!$AP$6:$AP$57,B46) -> 440000 | E46: =D46/$B$27 -> 0.077306857 | F46: {=_xlfn.LET(_xlpm.mach,C46,_xlpm.rowNo,MATCH(_xlpm.mach,'Machine Issuance Dashboard'!$A$6:$A$57,0),_xlpm.vals,CHOOSE({1,2,3,4,5,6,7,8},INDEX('Machine Issuance Dashboard'!$F$6:$F$57,_xlpm.rowNo),INDEX('Machine Issuance Dashboard'!$K$6:$K$57,_xlpm.rowNo),INDEX('Machine Issuance Dashboard'!$P$6:$P$57,_xlpm.rowNo),INDEX('Machine Issuance Dashboard'!$U$6:$U$57,_xlpm.rowNo),INDEX('Machine Issuance Dashboard'!$Z$6:$Z$57,_xlpm.rowNo),INDEX('Machine Issuance Dashboard'!$AE$6:$AE$57,_xlpm.rowNo),INDEX('Machine Issuance Dashboard'!$AJ$6:$AJ$57,_xlpm.rowNo),INDEX('Machine Issuance Dashboard'!$AO$6:$AO$57,_xlpm.rowNo)),INDEX({"May","Jun","Jul","Aug","Sep","Oct","Nov","Dec"},MATCH(MAX(_xlpm.vals),_xlpm.vals,0)))} -> May | G46: =IF(E46>=20%,"Priority check",IF(E46>=10%,"Watch","Normal")) -> Normal | I46: {=IFERROR(INDEX(_xlfn._xlws.FILTER('Machine Issuance Dashboard'!$A$6:$A$57,'Machine Issuance Dashboard'!$AP$6:$AP$57>0),MATCH(SMALL(_xlfn._xlws.FILTER('Machine Issuance Dashboard'!$AP$6:$AP$57,'Machine Issuance Dashboard'!$AP$6:$AP$57>0),4),_xlfn._xlws.FILTER('Machine Issuance Dashboard'!$AP$6:$AP$57,'Machine Issuance Dashboard'!$AP$6:$AP$57>0),0)),"No Data")} -> Workshop | J46: =IFERROR(INDEX('Machine Issuance Dashboard'!$AP$6:$AP$57,MATCH(I46,'Machine Issuance Dashboard'!$A$6:$A$57,0)),0) -> 1010 | K46: =IF(I46="No Data",0,--(INDEX('Machine Issuance Dashboard'!$F$6:$F$57,MATCH(I46,'Machine Issuance Dashboard'!$A$6:$A$57,0))>0)+--(INDEX('Machine Issuance Dashboard'!$K$6:$K$57,MATCH(I46,'Machine Issuance Dashboard'!$A$6:$A$57,0))>0)+--(INDEX('Machine Issuance Dashboard'!$P$6:$P$57,MATCH(I46,'Machine Issuance Dashboard'!$A$6:$A$57,0))>0)+--(INDEX('Machine Issuance Dashboard'!$U$6:$U$57,MATCH(I46,'Machine Issuance Dashboard'!$A$6:$A$57,0))>0)+--(INDEX('Machine Issuance Dashboard'!$Z$6:$Z$57,MATCH(I46,'Machine Issuance Dashboard'!$A$6:$A$57,0))>0)+--(INDEX('Machine Issuance Dashboard'!$AE$6:$AE$57,MATCH(I46,'Machine Issuance Dashboard'!$A$6:$A$57,0))>0)+--(INDEX('Machine Issuance Dashboard'!$AJ$6:$AJ$57,MATCH(I46,'Machine Issuance Dashboard'!$A$6:$A$57,0))>0)+--(INDEX('Machine Issuance Dashboard'!$AO$6:$AO$57,MATCH(I46,'Machine Issuance Dashboard'!$A$6:$A$57,0))>0)) -> 1 | L46: =IF(J46=0,"Idle",IF(K46<=1,"Low Use","Active")) -> Low Use
B47: 5 | C47: =INDEX('Machine Issuance Dashboard'!$A$6:$A$57,MATCH(LARGE('Machine Issuance Dashboard'!$AP$6:$AP$57,B47),'Machine Issuance Dashboard'!$AP$6:$AP$57,0)) -> Tecalit No: 02 | D47: =LARGE('Machine Issuance Dashboard'!$AP$6:$AP$57,B47) -> 435242 | E47: =D47/$B$27 -> 0.076470888 | F47: {=_xlfn.LET(_xlpm.mach,C47,_xlpm.rowNo,MATCH(_xlpm.mach,'Machine Issuance Dashboard'!$A$6:$A$57,0),_xlpm.vals,CHOOSE({1,2,3,4,5,6,7,8},INDEX('Machine Issuance Dashboard'!$F$6:$F$57,_xlpm.rowNo),INDEX('Machine Issuance Dashboard'!$K$6:$K$57,_xlpm.rowNo),INDEX('Machine Issuance Dashboard'!$P$6:$P$57,_xlpm.rowNo),INDEX('Machine Issuance Dashboard'!$U$6:$U$57,_xlpm.rowNo),INDEX('Machine Issuance Dashboard'!$Z$6:$Z$57,_xlpm.rowNo),INDEX('Machine Issuance Dashboard'!$AE$6:$AE$57,_xlpm.rowNo),INDEX('Machine Issuance Dashboard'!$AJ$6:$AJ$57,_xlpm.rowNo),INDEX('Machine Issuance Dashboard'!$AO$6:$AO$57,_xlpm.rowNo)),INDEX({"May","Jun","Jul","Aug","Sep","Oct","Nov","Dec"},MATCH(MAX(_xlpm.vals),_xlpm.vals,0)))} -> May | G47: =IF(E47>=20%,"Priority check",IF(E47>=10%,"Watch","Normal")) -> Normal | I47: {=IFERROR(INDEX(_xlfn._xlws.FILTER('Machine Issuance Dashboard'!$A$6:$A$57,'Machine Issuance Dashboard'!$AP$6:$AP$57>0),MATCH(SMALL(_xlfn._xlws.FILTER('Machine Issuance Dashboard'!$AP$6:$AP$57,'Machine Issuance Dashboard'!$AP$6:$AP$57>0),5),_xlfn._xlws.FILTER('Machine Issuance Dashboard'!$AP$6:$AP$57,'Machine Issuance Dashboard'!$AP$6:$AP$57>0),0)),"No Data")} -> Hand Pallet | J47: =IFERROR(INDEX('Machine Issuance Dashboard'!$AP$6:$AP$57,MATCH(I47,'Machine Issuance Dashboard'!$A$6:$A$57,0)),0) -> 1805 | K47: =IF(I47="No Data",0,--(INDEX('Machine Issuance Dashboard'!$F$6:$F$57,MATCH(I47,'Machine Issuance Dashboard'!$A$6:$A$57,0))>0)+--(INDEX('Machine Issuance Dashboard'!$K$6:$K$57,MATCH(I47,'Machine Issuance Dashboard'!$A$6:$A$57,0))>0)+--(INDEX('Machine Issuance Dashboard'!$P$6:$P$57,MATCH(I47,'Machine Issuance Dashboard'!$A$6:$A$57,0))>0)+--(INDEX('Machine Issuance Dashboard'!$U$6:$U$57,MATCH(I47,'Machine Issuance Dashboard'!$A$6:$A$57,0))>0)+--(INDEX('Machine Issuance Dashboard'!$Z$6:$Z$57,MATCH(I47,'Machine Issuance Dashboard'!$A$6:$A$57,0))>0)+--(INDEX('Machine Issuance Dashboard'!$AE$6:$AE$57,MATCH(I47,'Machine Issuance Dashboard'!$A$6:$A$57,0))>0)+--(INDEX('Machine Issuance Dashboard'!$AJ$6:$AJ$57,MATCH(I47,'Machine Issuance Dashboard'!$A$6:$A$57,0))>0)+--(INDEX('Machine Issuance Dashboard'!$AO$6:$AO$57,MATCH(I47,'Machine Issuance Dashboard'!$A$6:$A$57,0))>0)) -> 2 | L47: =IF(J47=0,"Idle",IF(K47<=1,"Low Use","Active")) -> Active
B49: MACHINE CONTROL CENTER
B52: Total Machine Spend | C52: ='Machine Issuance Dashboard'!$AP$60 -> 5700567.4 | D52: Top Machine | E52: =INDEX('Machine Issuance Dashboard'!$A$6:$A$57,MATCH(MAX('Machine Issuance Dashboard'!$AP$6:$AP$57),'Machine Issuance Dashboard'!$AP$6:$AP$57,0)) -> Auto Fryer | H52: Active Machines | I52: =COUNTIF('Machine Issuance Dashboard'!$AP$6:$AP$57,">0") -> 44 | J52: Idle Machines | K52: =COUNTIF('Machine Issuance Dashboard'!$AP$6:$AP$57,0) -> 8
B56: MONTHLY TREND | H56: TOP 5 MACHINES
B57: Month | C57: Total Spend | D57: Top Machine | E57: Top Amount | F57: Signal | H57: Rank | I57: Machine | J57: Spend | K57: Share | L57: Action
B58: May | C58: ='Machine Issuance Dashboard'!$F$60 -> 2870885 | D58: =IF(C58=0,"No Data",INDEX('Machine Issuance Dashboard'!$A$6:$A$59,MATCH(MAX('Machine Issuance Dashboard'!$F$6:$F$59),'Machine Issuance Dashboard'!$F$6:$F$59,0))) -> Auto Fryer | E58: =MAX('Machine Issuance Dashboard'!$F$6:$F$59) -> 1232577 | F58: =IF(C58=0,"No Data",IF(E58/C58>=40%,"Focus",IF(E58/C58>=25%,"Watch","OK"))) -> Focus | H58: 1 | I58: =INDEX('Machine Issuance Dashboard'!$A$6:$A$57,MATCH(LARGE('Machine Issuance Dashboard'!$AP$6:$AP$57,H58),'Machine Issuance Dashboard'!$AP$6:$AP$57,0)) -> Auto Fryer | J58: =LARGE('Machine Issuance Dashboard'!$AP$6:$AP$57,H58) -> 1232577 | K58: =J58/$C$52 -> 0.21622005 | L58: =IF(K58>=20%,"Priority",IF(K58>=10%,"Watch","OK")) -> Priority
B59: Jun | C59: ='Machine Issuance Dashboard'!$K$60 -> 2829682.5 | D59: =IF(C59=0,"No Data",INDEX('Machine Issuance Dashboard'!$A$6:$A$59,MATCH(MAX('Machine Issuance Dashboard'!$K$6:$K$59),'Machine Issuance Dashboard'!$K$6:$K$59,0))) -> Ishida No: 02 | E59: =MAX('Machine Issuance Dashboard'!$K$6:$K$59) -> 1007768 | F59: =IF(C59=0,"No Data",IF(E59/C59>=40%,"Focus",IF(E59/C59>=25%,"Watch","OK"))) -> Watch | H59: 2 | I59: =INDEX('Machine Issuance Dashboard'!$A$6:$A$57,MATCH(LARGE('Machine Issuance Dashboard'!$AP$6:$AP$57,H59),'Machine Issuance Dashboard'!$AP$6:$AP$57,0)) -> Ishida No: 02 | J59: =LARGE('Machine Issuance Dashboard'!$AP$6:$AP$57,H59) -> 1017774 | K59: =J59/$C$52 -> 0.17853907 | L59: =IF(K59>=20%,"Priority",IF(K59>=10%,"Watch","OK")) -> Watch
B60: Jul | C60: ='Machine Issuance Dashboard'!$P$60 -> 0 | D60: =IF(C60=0,"No Data",INDEX('Machine Issuance Dashboard'!$A$6:$A$59,MATCH(MAX('Machine Issuance Dashboard'!$P$6:$P$59),'Machine Issuance Dashboard'!$P$6:$P$59,0))) -> No Data | E60: =MAX('Machine Issuance Dashboard'!$P$6:$P$59) -> 0 | F60: =IF(C60=0,"No Data",IF(E60/C60>=40%,"Focus",IF(E60/C60>=25%,"Watch","OK"))) -> No Data | H60: 3 | I60: =INDEX('Machine Issuance Dashboard'!$A$6:$A$57,MATCH(LARGE('Machine Issuance Dashboard'!$AP$6:$AP$57,H60),'Machine Issuance Dashboard'!$AP$6:$AP$57,0)) -> Ishida No: 14 | J60: =LARGE('Machine Issuance Dashboard'!$AP$6:$AP$57,H60) -> 501227 | K60: =J60/$C$52 -> 0.087925809 | L60: =IF(K60>=20%,"Priority",IF(K60>=10%,"Watch","OK")) -> OK
B61: Aug | C61: ='Machine Issuance Dashboard'!$U$60 -> 0 | D61: =IF(C61=0,"No Data",INDEX('Machine Issuance Dashboard'!$A$6:$A$59,MATCH(MAX('Machine Issuance Dashboard'!$U$6:$U$59),'Machine Issuance Dashboard'!$U$6:$U$59,0))) -> No Data | E61: =MAX('Machine Issuance Dashboard'!$U$6:$U$59) -> 0 | F61: =IF(C61=0,"No Data",IF(E61/C61>=40%,"Focus",IF(E61/C61>=25%,"Watch","OK"))) -> No Data | H61: 4 | I61: =INDEX('Machine Issuance Dashboard'!$A$6:$A$57,MATCH(LARGE('Machine Issuance Dashboard'!$AP$6:$AP$57,H61),'Machine Issuance Dashboard'!$AP$6:$AP$57,0)) -> LPG Plant | J61: =LARGE('Machine Issuance Dashboard'!$AP$6:$AP$57,H61) -> 440000 | K61: =J61/$C$52 -> 0.077185299 | L61: =IF(K61>=20%,"Priority",IF(K61>=10%,"Watch","OK")) -> OK
B62: Sep | C62: ='Machine Issuance Dashboard'!$Z$60 -> 0 | D62: =IF(C62=0,"No Data",INDEX('Machine Issuance Dashboard'!$A$6:$A$59,MATCH(MAX('Machine Issuance Dashboard'!$Z$6:$Z$59),'Machine Issuance Dashboard'!$Z$6:$Z$59,0))) -> No Data | E62: =MAX('Machine Issuance Dashboard'!$Z$6:$Z$59) -> 0 | F62: =IF(C62=0,"No Data",IF(E62/C62>=40%,"Focus",IF(E62/C62>=25%,"Watch","OK"))) -> No Data | H62: 5 | I62: =INDEX('Machine Issuance Dashboard'!$A$6:$A$57,MATCH(LARGE('Machine Issuance Dashboard'!$AP$6:$AP$57,H62),'Machine Issuance Dashboard'!$AP$6:$AP$57,0)) -> Tecalit No: 02 | J62: =LARGE('Machine Issuance Dashboard'!$AP$6:$AP$57,H62) -> 435242 | K62: =J62/$C$52 -> 0.076350645 | L62: =IF(K62>=20%,"Priority",IF(K62>=10%,"Watch","OK")) -> OK
B63: Oct | C63: ='Machine Issuance Dashboard'!$AE$60 -> 0 | D63: =IF(C63=0,"No Data",INDEX('Machine Issuance Dashboard'!$A$6:$A$59,MATCH(MAX('Machine Issuance Dashboard'!$AE$6:$AE$59),'Machine Issuance Dashboard'!$AE$6:$AE$59,0))) -> No Data | E63: =MAX('Machine Issuance Dashboard'!$AE$6:$AE$59) -> 0 | F63: =IF(C63=0,"No Data",IF(E63/C63>=40%,"Focus",IF(E63/C63>=25%,"Watch","OK"))) -> No Data
B64: Nov | C64: ='Machine Issuance Dashboard'!$AJ$60 -> 0 | D64: =IF(C64=0,"No Data",INDEX('Machine Issuance Dashboard'!$A$6:$A$59,MATCH(MAX('Machine Issuance Dashboard'!$AJ$6:$AJ$59),'Machine Issuance Dashboard'!$AJ$6:$AJ$59,0))) -> No Data | E64: =MAX('Machine Issuance Dashboard'!$AJ$6:$AJ$59) -> 0 | F64: =IF(C64=0,"No Data",IF(E64/C64>=40%,"Focus",IF(E64/C64>=25%,"Watch","OK"))) -> No Data
B65: Dec | C65: ='Machine Issuance Dashboard'!$AO$60 -> 0 | D65: =IF(C65=0,"No Data",INDEX('Machine Issuance Dashboard'!$A$6:$A$59,MATCH(MAX('Machine Issuance Dashboard'!$AO$6:$AO$59),'Machine Issuance Dashboard'!$AO$6:$AO$59,0))) -> No Data | E65: =MAX('Machine Issuance Dashboard'!$AO$6:$AO$59) -> 0 | F65: =IF(C65=0,"No Data",IF(E65/C65>=40%,"Focus",IF(E65/C65>=25%,"Watch","OK"))) -> No Data
B68: OPERATIONS COMMAND CENTER
B69: management view for stock value, inward flow, issuance pressure, category mix, and action priorities
B71: Total Stock Value | D71: Total Inward | F71: Total Issuance | H71: Net Movement | J71: Machine Focus
B72: =$F$5 -> 23077289 | D72: =$G$22 -> 4028137 | F72: =$L$22 -> 5700567.4 | H72: =$G$22-$L$22 -> -1672430.4 | J72: =COUNTIF($J$31:$J$38,"Focus") -> 2
B73: =IF(B72>=20000000,"Strong Base",IF(B72>=10000000,"Stable Base","Low Base")) -> Strong Base | D73: =IF(D72>0,"Active Inflow","No Inflow") -> Active Inflow | F73: =IF(F72>D72,"High Outflow",IF(F72=D72,"Balanced","Controlled")) -> High Outflow | H73: =IF(H72<0,"Outflow Higher",IF(H72=0,"Balanced","Inflow Higher")) -> Outflow Higher | J73: =IF(J72>=2,"Priority Review",IF(J72=1,"Watch","Normal")) -> Priority Review
B75: CATEGORY PERFORMANCE SUMMARY
B76: Category | C76: Stock Value | D76: Stock Mix | E76: Inward Value | F76: Inward Mix | G76: Issuance Value | H76: Issuance Mix | I76: Net Flow | J76: Pressure | K76: Status | L76: Recommended Action
B77: Inventory | C77: =$B$5 -> 14080023 | D77: =IFERROR(C77/$F$5,0) -> 0.61012464 | E77: =C$22 -> 1086500 | F77: =IFERROR(E77/$G$22,0) -> 0.26972767 | G77: =H$22 -> 3338614 | H77: =IFERROR(G77/$L$22,0) -> 0.58566345 | I77: =E77-G77 -> -2252114 | J77: =IFERROR(G77/E77-1,0) -> 2.0728155 | K77: =IF(J77>0.15,"High Pressure",IF(J77<-0.15,"Low Pressure","Balanced")) -> High Pressure | L77: =IF(K77="High Pressure","Review issuance control",IF(K77="Low Pressure","Check inward plan","Maintain current control")) -> Review issuance control
B78: Non Inventory | C78: =$D$5 -> 8997266.4 | D78: =IFERROR(C78/$F$5,0) -> 0.38987536 | E78: =D$22 -> 1734685.8 | F78: =IFERROR(E78/$G$22,0) -> 0.43064221 | G78: =I$22 -> 1153611.8 | H78: =IFERROR(G78/$L$22,0) -> 0.20236789 | I78: =E78-G78 -> 581074 | J78: =IFERROR(G78/E78-1,0) -> -0.33497363 | K78: =IF(J78>0.15,"High Pressure",IF(J78<-0.15,"Low Pressure","Balanced")) -> Low Pressure | L78: =IF(K78="High Pressure","Review usage / approvals",IF(K78="Low Pressure","Check buying need","Maintain current control")) -> Check buying need
B79: Services | C79: =0 -> 0 | D79: =IFERROR(C79/$F$5,0) -> 0 | E79: =E$22 -> 1183200 | F79: =IFERROR(E79/$G$22,0) -> 0.2937338 | G79: =J$22 -> 1183200 | H79: =IFERROR(G79/$L$22,0) -> 0.20755829 | I79: =E79-G79 -> 0 | J79: =IFERROR(G79/E79-1,0) -> 0 | K79: =IF(J79>0.15,"High Pressure",IF(J79<-0.15,"Low Pressure","Balanced")) -> Balanced | L79: =IF(K79="High Pressure","Validate service billing",IF(K79="Low Pressure","Confirm pending service work","Maintain current control")) -> Maintain current control
B80: Patty Cash | C80: =0 -> 0 | D80: =IFERROR(C80/$F$5,0) -> 0 | E80: =F$22 -> 23751.208 | F80: =IFERROR(E80/$G$22,0) -> 0.0058963258 | G80: =K$22 -> 25141.608 | H80: =IFERROR(G80/$L$22,0) -> 0.0044103695 | I80: =E80-G80 -> -1390.4 | J80: =IFERROR(G80/E80-1,0) -> 0.058540179 | K80: =IF(J80>0.15,"High Pressure",IF(J80<-0.15,"Low Pressure","Balanced")) -> Balanced | L80: =IF(K80="High Pressure","Audit petty cash spend",IF(K80="Low Pressure","Check pending claims","Maintain discipline")) -> Maintain discipline
B83: MANAGEMENT ALERT BOARD
B84: Priority | C84: Alert Area | D84: Trigger | E84: Current Reading | F84: Risk Level | G84: Owner Action | H84: Review Frequency | I84: Data Source | J84: Impact | K84: Decision Needed | L84: Status
B85: 1 | C85: Issuance vs Inward | D85: Issuance higher than inward | E85: =$L$22-$G$22 -> 1672430.4 | F85: =IF(E85>0,"High",IF(E85=0,"Medium","Low")) -> High | G85: Control issuance approvals | H85: Weekly | I85: Monthly Summary | J85: Working capital | K85: Approve control limit | L85: =IF(F85="High","Immediate",IF(F85="Medium","Watch","OK")) -> Immediate
B86: 2 | C86: Machine Concentration | D86: Top machine share above 40% | E86: =MAX($I$31:$I$38) -> 0.43754705 | F86: =IF(E86>=40%,"High",IF(E86>=25%,"Medium","Low")) -> High | G86: Check top machine reason | H86: Weekly | I86: Machine Dashboard | J86: Maintenance / utilization | K86: Investigate variance | L86: =IF(F86="High","Immediate",IF(F86="Medium","Watch","OK")) -> Immediate
B87: 3 | C87: Inventory Mix | D87: Inventory stock share movement | E87: =$B$5/$F$5 -> 0.61012464 | F87: =IF(E87>=70%,"Medium",IF(E87<=35%,"Medium","Low")) -> Low | G87: Monitor stock balance | H87: Monthly | I87: Stock Cards | J87: Stock planning | K87: Set target mix | L87: =IF(F87="High","Immediate",IF(F87="Medium","Watch","OK")) -> OK
B88: 4 | C88: Low / Idle Machines | D88: Idle / low use machines exist | E88: =$K$52 -> 8 | F88: =IF(E88>=5,"Medium","Low") -> Medium | G88: Verify idle machine list | H88: Monthly | I88: Machine Watchlist | J88: Asset utilization | K88: Keep / repair / retire | L88: =IF(F88="High","Immediate",IF(F88="Medium","Watch","OK")) -> Watch
B89: 5 | C89: Petty Cash Control | D89: Cash spend requires discipline | E89: =SUM($F$22,$K$22) -> 48892.817 | F89: =IF(E89>50000,"Medium","Low") -> Low | G89: Review supporting vouchers | H89: Weekly | I89: Petty Cash | J89: Spend governance | K89: Set approval threshold | L89: =IF(F89="High","Immediate",IF(F89="Medium","Watch","OK")) -> OK
B90: 6 | C90: Future Months Data | D90: Jul-Dec data availability | E90: =COUNTIF($L$33:$L$38,"No Data") -> 6 | F90: =IF(E90>=3,"Medium",IF(E90=0,"Low","Watch")) -> Medium | G90: Update source monthly data | H90: Monthly | I90: Monthly Trend | J90: Reporting completeness | K90: Close reporting gap | L90: =IF(F90="High","Immediate",IF(F90="Medium","Watch","OK")) -> Watch
B93: Note: This command center is live-linked to stock, inward, issuance, and machine dashboard totals. Update source sheets to refresh all signals automatically.

Sheet Machine Issuance Dashboard
A1: Machine Wise Issuance Dashboard
A2: Inventory + Non Inventory issuance value by Equipment/Machine Issuance from May 2026 to Dec 2026
A3: Machine Name | B3: May-2026 | G3: Jun-2026 | L3: Jul-2026 | Q3: Aug-2026 | V3: Sep-2026 | AA3: Oct-2026 | AF3: Nov-2026 | AK3: Dec-2026 | AP3: Year Total
B4: 46143 | C4: 46143 | D4: 46143 | E4: 46143 | F4: 46143 | G4: 46174 | H4: 46174 | I4: 46174 | J4: 46174 | K4: 46174 | L4: 46204 | M4: 46204 | N4: 46204 | O4: 46204 | P4: 46204 | Q4: 46235 | R4: 46235 | S4: 46235 | T4: 46235 | U4: 46235 | V4: 46266 | W4: 46266 | X4: 46266 | Y4: 46266 | Z4: 46266 | AA4: 46296 | AB4: 46296 | AC4: 46296 | AD4: 46296 | AE4: 46296 | AF4: 46327 | AG4: 46327 | AH4: 46327 | AI4: 46327 | AJ4: 46327 | AK4: 46357 | AL4: 46357 | AM4: 46357 | AN4: 46357 | AO4: 46357
B5: Inventory | C5: Non Inventory | D5: Services | E5: Patty Cash | F5: Month Total | G5: Inventory | H5: Non Inventory | I5: Services | J5: Patty Csh | K5: Month Total | L5: Inventory | M5: Non Inventory | N5: Services | O5: Patty Cash | P5: Month Total | Q5: Inventory | R5: Non Inventory | S5: Services | T5: Patty Cash | U5: Month Total | V5: Inventory | W5: Non Inventory | X5: Services | Y5: Patty Cash | Z5: Month Total | AA5: Inventory | AB5: Non Inventory | AC5: Services | AD5: Patty Cash | AE5: Month Total | AF5: Inventory | AG5: Non Inventory | AH5: Services | AI5: Patty Cash | AJ5: Month Total | AK5: Inventory | AL5: Non Inventory | AM5: Services | AN5: Patty Cash | AO5: Month Total
A6: Ishida No: 01 | B6: =IFERROR(SUMIFS('Daily Issuance'!$O:$O,'Daily Issuance'!$I:$I,$A6,'Daily Issuance'!$E:$E,"Inventory",'Daily Issuance'!$B:$B,">="&DATE(2026,5,1),'Daily Issuance'!$B:$B,"<"&DATE(2026,6,1)),0) -> 167000 | C6: =IFERROR(SUMIFS('Daily Issuance'!$O:$O,'Daily Issuance'!$I:$I,$A6,'Daily Issuance'!$E:$E,"Non Inventory",'Daily Issuance'!$B:$B,">="&DATE(2026,5,1),'Daily Issuance'!$B:$B,"<"&DATE(2026,6,1)),0) -> 672 | D6: =IFERROR(SUMIFS('Daily Issuance'!$O:$O,'Daily Issuance'!$I:$I,$A6,'Daily Issuance'!$E:$E,"Services",'Daily Issuance'!$B:$B,">="&DATE(2026,5,1),'Daily Issuance'!$B:$B,"<"&DATE(2026,6,1)),0) -> 0 | E6: =IFERROR(SUMIFS('Daily Issuance'!$O:$O,'Daily Issuance'!$I:$I,$A6,'Daily Issuance'!$E:$E,"Patty Cash",'Daily Issuance'!$B:$B,">="&DATE(2026,5,1),'Daily Issuance'!$B:$B,"<"&DATE(2026,6,1)),0) -> 0 | F6: =SUM(B6:E6) -> 167672 | G6: =IFERROR(SUMIFS('Daily Issuance'!$O$4:$O$991,'Daily Issuance'!$I$4:$I$991,$A6,'Daily Issuance'!$E$4:$E$991,"Inventory",'Daily Issuance'!$B$4:$B$991,">="&DATE(2026,6,1),'Daily Issuance'!$B$4:$B$991,"<"&DATE(2026,7,1)),0) -> 16450 | H6: =IFERROR(SUMIFS('Daily Issuance'!$O$4:$O$991,'Daily Issuance'!$I$4:$I$991,$A6,'Daily Issuance'!$E$4:$E$991,"Non Inventory",'Daily Issuance'!$B$4:$B$991,">="&DATE(2026,6,1),'Daily Issuance'!$B$4:$B$991,"<"&DATE(2026,7,1)),0) -> 512 | I6: =IFERROR(SUMIFS('Daily Issuance'!$O$4:$O$991,'Daily Issuance'!$I$4:$I$991,$A6,'Daily Issuance'!$E$4:$E$991,"Services",'Daily Issuance'!$B$4:$B$991,">="&DATE(2026,6,1),'Daily Issuance'!$B$4:$B$991,"<"&DATE(2026,7,1)),0) -> 0 | J6: =IFERROR(SUMIFS('Daily Issuance'!$O:$O,'Daily Issuance'!$I:$I,$A6,'Daily Issuance'!$E:$E,"Patty Cash",'Daily Issuance'!$B:$B,">="&DATE(2026,6,1),'Daily Issuance'!$B:$B,"<"&DATE(2026,7,1)),0) -> 0 | K6: =SUM(G6:J6) -> 16962 | L6: =IFERROR(SUMIFS('Daily Issuance'!$O$4:$O$991,'Daily Issuance'!$I$4:$I$991,$A6,'Daily Issuance'!$E$4:$E$991,"Inventory",'Daily Issuance'!$B$4:$B$991,">="&DATE(2026,7,1),'Daily Issuance'!$B$4:$B$991,"<"&DATE(2026,8,1)),0) -> 0 | M6: =IFERROR(SUMIFS('Daily Issuance'!$O$4:$O$991,'Daily Issuance'!$I$4:$I$991,$A6,'Daily Issuance'!$E$4:$E$991,"Non Inventory",'Daily Issuance'!$B$4:$B$991,">="&DATE(2026,7,1),'Daily Issuance'!$B$4:$B$991,"<"&DATE(2026,8,1)),0) -> 0 | N6: =IFERROR(SUMIFS('Daily Issuance'!$O$4:$O$991,'Daily Issuance'!$I$4:$I$991,$A6,'Daily Issuance'!$E$4:$E$991,"Services",'Daily Issuance'!$B$4:$B$991,">="&DATE(2026,7,1),'Daily Issuance'!$B$4:$B$991,"<"&DATE(2026,8,1)),0) -> 0 | O6: =IFERROR(SUMIFS('Daily Issuance'!$O:$O,'Daily Issuance'!$I:$I,$A6,'Daily Issuance'!$E:$E,"Patty Cash",'Daily Issuance'!$B:$B,">="&DATE(2026,7,1),'Daily Issuance'!$B:$B,"<"&DATE(2026,8,1)),0) -> 0 | P6: =SUM(L6:O6) -> 0 | Q6: =IFERROR(SUMIFS('Daily Issuance'!$O$4:$O$991,'Daily Issuance'!$I$4:$I$991,$A6,'Daily Issuance'!$E$4:$E$991,"Inventory",'Daily Issuance'!$B$4:$B$991,">="&DATE(2026,8,1),'Daily Issuance'!$B$4:$B$991,"<"&DATE(2026,9,1)),0) -> 0 | R6: =IFERROR(SUMIFS('Daily Issuance'!$O$4:$O$991,'Daily Issuance'!$I$4:$I$991,$A6,'Daily Issuance'!$E$4:$E$991,"Non Inventory",'Daily Issuance'!$B$4:$B$991,">="&DATE(2026,8,1),'Daily Issuance'!$B$4:$B$991,"<"&DATE(2026,9,1)),0) -> 0 | S6: =IFERROR(SUMIFS('Daily Issuance'!$O$4:$O$991,'Daily Issuance'!$I$4:$I$991,$A6,'Daily Issuance'!$E$4:$E$991,"Services",'Daily Issuance'!$B$4:$B$991,">="&DATE(2026,8,1),'Daily Issuance'!$B$4:$B$991,"<"&DATE(2026,9,1)),0) -> 0 | T6: =IFERROR(SUMIFS('Daily Issuance'!$O:$O,'Daily Issuance'!$I:$I,$A6,'Daily Issuance'!$E:$E,"Patty Cash",'Daily Issuance'!$B:$B,">="&DATE(2026,8,1),'Daily Issuance'!$B:$B,"<"&DATE(2026,9,1)),0) -> 0 | U6: =SUM(Q6:T6) -> 0 | V6: =IFERROR(SUMIFS('Daily Issuance'!$O$4:$O$991,'Daily Issuance'!$I$4:$I$991,$A6,'Daily Issuance'!$E$4:$E$991,"Inventory",'Daily Issuance'!$B$4:$B$991,">="&DATE(2026,9,1),'Daily Issuance'!$B$4:$B$991,"<"&DATE(2026,10,1)),0) -> 0 | W6: =IFERROR(SUMIFS('Daily Issuance'!$O$4:$O$991,'Daily Issuance'!$I$4:$I$991,$A6,'Daily Issuance'!$E$4:$E$991,"Non Inventory",'Daily Issuance'!$B$4:$B$991,">="&DATE(2026,9,1),'Daily Issuance'!$B$4:$B$991,"<"&DATE(2026,10,1)),0) -> 0 | X6: =IFERROR(SUMIFS('Daily Issuance'!$O$4:$O$991,'Daily Issuance'!$I$4:$I$991,$A6,'Daily Issuance'!$E$4:$E$991,"Services",'Daily Issuance'!$B$4:$B$991,">="&DATE(2026,9,1),'Daily Issuance'!$B$4:$B$991,"<"&DATE(2026,10,1)),0) -> 0 | Y6: =IFERROR(SUMIFS('Daily Issuance'!$O:$O,'Daily Issuance'!$I:$I,$A6,'Daily Issuance'!$E:$E,"Patty Cash",'Daily Issuance'!$B:$B,">="&DATE(2026,9,1),'Daily Issuance'!$B:$B,"<"&DATE(2026,10,1)),0) -> 0 | Z6: =SUM(V6:Y6) -> 0 | AA6: =IFERROR(SUMIFS('Daily Issuance'!$O$4:$O$991,'Daily Issuance'!$I$4:$I$991,$A6,'Daily Issuance'!$E$4:$E$991,"Inventory",'Daily Issuance'!$B$4:$B$991,">="&DATE(2026,10,1),'Daily Issuance'!$B$4:$B$991,"<"&DATE(2026,11,1)),0) -> 0 | AB6: =IFERROR(SUMIFS('Daily Issuance'!$O$4:$O$991,'Daily Issuance'!$I$4:$I$991,$A6,'Daily Issuance'!$E$4:$E$991,"Non Inventory",'Daily Issuance'!$B$4:$B$991,">="&DATE(2026,10,1),'Daily Issuance'!$B$4:$B$991,"<"&DATE(2026,11,1)),0) -> 0 | AC6: =IFERROR(SUMIFS('Daily Issuance'!$O$4:$O$991,'Daily Issuance'!$I$4:$I$991,$A6,'Daily Issuance'!$E$4:$E$991,"Services",'Daily Issuance'!$B$4:$B$991,">="&DATE(2026,10,1),'Daily Issuance'!$B$4:$B$991,"<"&DATE(2026,11,1)),0) -> 0 | AD6: =IFERROR(SUMIFS('Daily Issuance'!$O:$O,'Daily Issuance'!$I:$I,$A6,'Daily Issuance'!$E:$E,"Patty Cash",'Daily Issuance'!$B:$B,">="&DATE(2026,10,1),'Daily Issuance'!$B:$B,"<"&DATE(2026,11,1)),0) -> 0 | AE6: =SUM(AA6:AD6) -> 0 | AF6: =IFERROR(SUMIFS('Daily Issuance'!$O$4:$O$991,'Daily Issuance'!$I$4:$I$991,$A6,'Daily Issuance'!$E$4:$E$991,"Inventory",'Daily Issuance'!$B$4:$B$991,">="&DATE(2026,11,1),'Daily Issuance'!$B$4:$B$991,"<"&DATE(2026,12,1)),0) -> 0 | AG6: =IFERROR(SUMIFS('Daily Issuance'!$O$4:$O$991,'Daily Issuance'!$I$4:$I$991,$A6,'Daily Issuance'!$E$4:$E$991,"Non Inventory",'Daily Issuance'!$B$4:$B$991,">="&DATE(2026,11,1),'Daily Issuance'!$B$4:$B$991,"<"&DATE(2026,12,1)),0) -> 0 | AH6: =IFERROR(SUMIFS('Daily Issuance'!$O$4:$O$991,'Daily Issuance'!$I$4:$I$991,$A6,'Daily Issuance'!$E$4:$E$991,"Services",'Daily Issuance'!$B$4:$B$991,">="&DATE(2026,11,1),'Daily Issuance'!$B$4:$B$991,"<"&DATE(2026,12,1)),0) -> 0 | AI6: =IFERROR(SUMIFS('Daily Issuance'!$O:$O,'Daily Issuance'!$I:$I,$A6,'Daily Issuance'!$E:$E,"Patty Cash",'Daily Issuance'!$B:$B,">="&DATE(2026,11,1),'Daily Issuance'!$B:$B,"<"&DATE(2026,12,1)),0) -> 0 | AJ6: =SUM(AF6:AI6) -> 0 | AK6: =IFERROR(SUMIFS('Daily Issuance'!$O$4:$O$991,'Daily Issuance'!$I$4:$I$991,$A6,'Daily Issuance'!$E$4:$E$991,"Inventory",'Daily Issuance'!$B$4:$B$991,">="&DATE(2026,12,1),'Daily Issuance'!$B$4:$B$991,"<"&DATE(2027,1,1)),0) -> 0 | AL6: =IFERROR(SUMIFS('Daily Issuance'!$O$4:$O$991,'Daily Issuance'!$I$4:$I$991,$A6,'Daily Issuance'!$E$4:$E$991,"Non Inventory",'Daily Issuance'!$B$4:$B$991,">="&DATE(2026,12,1),'Daily Issuance'!$B$4:$B$991,"<"&DATE(2027,1,1)),0) -> 0 | AM6: =IFERROR(SUMIFS('Daily Issuance'!$O$4:$O$991,'Daily Issuance'!$I$4:$I$991,$A6,'Daily Issuance'!$E$4:$E$991,"Services",'Daily Issuance'!$B$4:$B$991,">="&DATE(2026,12,1),'Daily Issuance'!$B$4:$B$991,"<"&DATE(2027,1,1)),0) -> 0 | AN6: =IFERROR(SUMIFS('Daily Issuance'!$O:$O,'Daily Issuance'!$I:$I,$A6,'Daily Issuance'!$E:$E,"Patty Cash",'Daily Issuance'!$B:$B,">="&DATE(2026,12,1),'Daily Issuance'!$B:$B,"<"&DATE(2027,1,1)),0) -> 0 | AO6: =SUM(AK6:AN6) -> 0 | AP6: =SUM(F6,K6,P6,U6,Z6,AE6,AJ6,AO6) -> 184634
A7: Ishida No: 02 | B7: =IFERROR(SUMIFS('Daily Issuance'!$O:$O,'Daily Issuance'!$I:$I,$A7,'Daily Issuance'!$E:$E,"Inventory",'Daily Issuance'!$B:$B,">="&DATE(2026,5,1),'Daily Issuance'!$B:$B,"<"&DATE(2026,6,1)),0) -> 8550 | C7: =IFERROR(SUMIFS('Daily Issuance'!$O:$O,'Daily Issuance'!$I:$I,$A7,'Daily Issuance'!$E:$E,"Non Inventory",'Daily Issuance'!$B:$B,">="&DATE(2026,5,1),'Daily Issuance'!$B:$B,"<"&DATE(2026,6,1)),0) -> 1456 | D7: =IFERROR(SUMIFS('Daily Issuance'!$O:$O,'Daily Issuance'!$I:$I,$A7,'Daily Issuance'!$E:$E,"Services",'Daily Issuance'!$B:$B,">="&DATE(2026,5,1),'Daily Issuance'!$B:$B,"<"&DATE(2026,6,1)),0) -> 0 | E7: =IFERROR(SUMIFS('Daily Issuance'!$O:$O,'Daily Issuance'!$I:$I,$A7,'Daily Issuance'!$E:$E,"Patty Cash",'Daily Issuance'!$B:$B,">="&DATE(2026,5,1),'Daily Issuance'!$B:$B,"<"&DATE(2026,6,1)),0) -> 0 | F7: =SUM(B7:E7) -> 10006 | G7: =IFERROR(SUMIFS('Daily Issuance'!$O$4:$O$991,'Daily Issuance'!$I$4:$I$991,$A7,'Daily Issuance'!$E$4:$E$991,"Inventory",'Daily Issuance'!$B$4:$B$991,">="&DATE(2026,6,1),'Daily Issuance'!$B$4:$B$991,"<"&DATE(2026,7,1)),0) -> 1007000 | H7: =IFERROR(SUMIFS('Daily Issuance'!$O$4:$O$991,'Daily Issuance'!$I$4:$I$991,$A7,'Daily Issuance'!$E$4:$E$991,"Non Inventory",'Daily Issuance'!$B$4:$B$991,">="&DATE(2026,6,1),'Daily Issuance'!$B$4:$B$991,"<"&DATE(2026,7,1)),0) -> 768 | I7: =IFERROR(SUMIFS('Daily Issuance'!$O$4:$O$991,'Daily Issuance'!$I$4:$I$991,$A7,'Daily Issuance'!$E$4:$E$991,"Services",'Daily Issuance'!$B$4:$B$991,">="&DATE(2026,6,1),'Daily Issuance'!$B$4:$B$991,"<"&DATE(2026,7,1)),0) -> 0 | J7: =IFERROR(SUMIFS('Daily Issuance'!$O:$O,'Daily Issuance'!$I:$I,$A7,'Daily Issuance'!$E:$E,"Patty Cash",'Daily Issuance'!$B:$B,">="&DATE(2026,6,1),'Daily Issuance'!$B:$B,"<"&DATE(2026,7,1)),0) -> 0 | K7: =SUM(G7:J7) -> 1007768 | L7: =IFERROR(SUMIFS('Daily Issuance'!$O$4:$O$991,'Daily Issuance'!$I$4:$I$991,$A7,'Daily Issuance'!$E$4:$E$991,"Inventory",'Daily Issuance'!$B$4:$B$991,">="&DATE(2026,7,1),'Daily Issuance'!$B$4:$B$991,"<"&DATE(2026,8,1)),0) -> 0 | M7: =IFERROR(SUMIFS('Daily Issuance'!$O$4:$O$991,'Daily Issuance'!$I$4:$I$991,$A7,'Daily Issuance'!$E$4:$E$991,"Non Inventory",'Daily Issuance'!$B$4:$B$991,">="&DATE(2026,7,1),'Daily Issuance'!$B$4:$B$991,"<"&DATE(2026,8,1)),0) -> 0 | N7: =IFERROR(SUMIFS('Daily Issuance'!$O$4:$O$991,'Daily Issuance'!$I$4:$I$991,$A7,'Daily Issuance'!$E$4:$E$991,"Services",'Daily Issuance'!$B$4:$B$991,">="&DATE(2026,7,1),'Daily Issuance'!$B$4:$B$991,"<"&DATE(2026,8,1)),0) -> 0 | O7: =IFERROR(SUMIFS('Daily Issuance'!$O:$O,'Daily Issuance'!$I:$I,$A7,'Daily Issuance'!$E:$E,"Patty Cash",'Daily Issuance'!$B:$B,">="&DATE(2026,7,1),'Daily Issuance'!$B:$B,"<"&DATE(2026,8,1)),0) -> 0 | P7: =SUM(L7:O7) -> 0 | Q7: =IFERROR(SUMIFS('Daily Issuance'!$O$4:$O$991,'Daily Issuance'!$I$4:$I$991,$A7,'Daily Issuance'!$E$4:$E$991,"Inventory",'Daily Issuance'!$B$4:$B$991,">="&DATE(2026,8,1),'Daily Issuance'!$B$4:$B$991,"<"&DATE(2026,9,1)),0) -> 0 | R7: =IFERROR(SUMIFS('Daily Issuance'!$O$4:$O$991,'Daily Issuance'!$I$4:$I$991,$A7,'Daily Issuance'!$E$4:$E$991,"Non Inventory",'Daily Issuance'!$B$4:$B$991,">="&DATE(2026,8,1),'Daily Issuance'!$B$4:$B$991,"<"&DATE(2026,9,1)),0) -> 0 | S7: =IFERROR(SUMIFS('Daily Issuance'!$O$4:$O$991,'Daily Issuance'!$I$4:$I$991,$A7,'Daily Issuance'!$E$4:$E$991,"Services",'Daily Issuance'!$B$4:$B$991,">="&DATE(2026,8,1),'Daily Issuance'!$B$4:$B$991,"<"&DATE(2026,9,1)),0) -> 0 | T7: =IFERROR(SUMIFS('Daily Issuance'!$O:$O,'Daily Issuance'!$I:$I,$A7,'Daily Issuance'!$E:$E,"Patty Cash",'Daily Issuance'!$B:$B,">="&DATE(2026,8,1),'Daily Issuance'!$B:$B,"<"&DATE(2026,9,1)),0) -> 0 | U7: =SUM(Q7:T7) -> 0 | V7: =IFERROR(SUMIFS('Daily Issuance'!$O$4:$O$991,'Daily Issuance'!$I$4:$I$991,$A7,'Daily Issuance'!$E$4:$E$991,"Inventory",'Daily Issuance'!$B$4:$B$991,">="&DATE(2026,9,1),'Daily Issuance'!$B$4:$B$991,"<"&DATE(2026,10,1)),0) -> 0 | W7: =IFERROR(SUMIFS('Daily Issuance'!$O$4:$O$991,'Daily Issuance'!$I$4:$I$991,$A7,'Daily Issuance'!$E$4:$E$991,"Non Inventory",'Daily Issuance'!$B$4:$B$991,">="&DATE(2026,9,1),'Daily Issuance'!$B$4:$B$991,"<"&DATE(2026,10,1)),0) -> 0 | X7: =IFERROR(SUMIFS('Daily Issuance'!$O$4:$O$991,'Daily Issuance'!$I$4:$I$991,$A7,'Daily Issuance'!$E$4:$E$991,"Services",'Daily Issuance'!$B$4:$B$991,">="&DATE(2026,9,1),'Daily Issuance'!$B$4:$B$991,"<"&DATE(2026,10,1)),0) -> 0 | Y7: =IFERROR(SUMIFS('Daily Issuance'!$O:$O,'Daily Issuance'!$I:$I,$A7,'Daily Issuance'!$E:$E,"Patty Cash",'Daily Issuance'!$B:$B,">="&DATE(2026,9,1),'Daily Issuance'!$B:$B,"<"&DATE(2026,10,1)),0) -> 0 | Z7: =SUM(V7:Y7) -> 0 | AA7: =IFERROR(SUMIFS('Daily Issuance'!$O$4:$O$991,'Daily Issuance'!$I$4:$I$991,$A7,'Daily Issuance'!$E$4:$E$991,"Inventory",'Daily Issuance'!$B$4:$B$991,">="&DATE(2026,10,1),'Daily Issuance'!$B$4:$B$991,"<"&DATE(2026,11,1)),0) -> 0 | AB7: =IFERROR(SUMIFS('Daily Issuance'!$O$4:$O$991,'Daily Issuance'!$I$4:$I$991,$A7,'Daily Issuance'!$E$4:$E$991,"Non Inventory",'Daily Issuance'!$B$4:$B$991,">="&DATE(2026,10,1),'Daily Issuance'!$B$4:$B$991,"<"&DATE(2026,11,1)),0) -> 0 | AC7: =IFERROR(SUMIFS('Daily Issuance'!$O$4:$O$991,'Daily Issuance'!$I$4:$I$991,$A7,'Daily Issuance'!$E$4:$E$991,"Services",'Daily Issuance'!$B$4:$B$991,">="&DATE(2026,10,1),'Daily Issuance'!$B$4:$B$991,"<"&DATE(2026,11,1)),0) -> 0 | AD7: =IFERROR(SUMIFS('Daily Issuance'!$O:$O,'Daily Issuance'!$I:$I,$A7,'Daily Issuance'!$E:$E,"Patty Cash",'Daily Issuance'!$B:$B,">="&DATE(2026,10,1),'Daily Issuance'!$B:$B,"<"&DATE(2026,11,1)),0) -> 0 | AE7: =SUM(AA7:AD7) -> 0 | AF7: =IFERROR(SUMIFS('Daily Issuance'!$O$4:$O$991,'Daily Issuance'!$I$4:$I$991,$A7,'Daily Issuance'!$E$4:$E$991,"Inventory",'Daily Issuance'!$B$4:$B$991,">="&DATE(2026,11,1),'Daily Issuance'!$B$4:$B$991,"<"&DATE(2026,12,1)),0) -> 0 | AG7: =IFERROR(SUMIFS('Daily Issuance'!$O$4:$O$991,'Daily Issuance'!$I$4:$I$991,$A7,'Daily Issuance'!$E$4:$E$991,"Non Inventory",'Daily Issuance'!$B$4:$B$991,">="&DATE(2026,11,1),'Daily Issuance'!$B$4:$B$991,"<"&DATE(2026,12,1)),0) -> 0 | AH7: =IFERROR(SUMIFS('Daily Issuance'!$O$4:$O$991,'Daily Issuance'!$I$4:$I$991,$A7,'Daily Issuance'!$E$4:$E$991,"Services",'Daily Issuance'!$B$4:$B$991,">="&DATE(2026,11,1),'Daily Issuance'!$B$4:$B$991,"<"&DATE(2026,12,1)),0) -> 0 | AI7: =IFERROR(SUMIFS('Daily Issuance'!$O:$O,'Daily Issuance'!$I:$I,$A7,'Daily Issuance'!$E:$E,"Patty Cash",'Daily Issuance'!$B:$B,">="&DATE(2026,11,1),'Daily Issuance'!$B:$B,"<"&DATE(2026,12,1)),0) -> 0 | AJ7: =SUM(AF7:AI7) -> 0 | AK7: =IFERROR(SUMIFS('Daily Issuance'!$O$4:$O$991,'Daily Issuance'!$I$4:$I$991,$A7,'Daily Issuance'!$E$4:$E$991,"Inventory",'Daily Issuance'!$B$4:$B$991,">="&DATE(2026,12,1),'Daily Issuance'!$B$4:$B$991,"<"&DATE(2027,1,1)),0) -> 0 | AL7: =IFERROR(SUMIFS('Daily Issuance'!$O$4:$O$991,'Daily Issuance'!$I$4:$I$991,$A7,'Daily Issuance'!$E$4:$E$991,"Non Inventory",'Daily Issuance'!$B$4:$B$991,">="&DATE(2026,12,1),'Daily Issuance'!$B$4:$B$991,"<"&DATE(2027,1,1)),0) -> 0 | AM7: =IFERROR(SUMIFS('Daily Issuance'!$O$4:$O$991,'Daily Issuance'!$I$4:$I$991,$A7,'Daily Issuance'!$E$4:$E$991,"Services",'Daily Issuance'!$B$4:$B$991,">="&DATE(2026,12,1),'Daily Issuance'!$B$4:$B$991,"<"&DATE(2027,1,1)),0) -> 0 | AN7: =IFERROR(SUMIFS('Daily Issuance'!$O:$O,'Daily Issuance'!$I:$I,$A7,'Daily Issuance'!$E:$E,"Patty Cash",'Daily Issuance'!$B:$B,">="&DATE(2026,12,1),'Daily Issuance'!$B:$B,"<"&DATE(2027,1,1)),0) -> 0 | AO7: =SUM(AK7:AN7) -> 0 | AP7: =SUM(F7,K7,P7,U7,Z7,AE7,AJ7,AO7) -> 1017774
A8: Ishida No: 03 | B8: =IFERROR(SUMIFS('Daily Issuance'!$O:$O,'Daily Issuance'!$I:$I,$A8,'Daily Issuance'!$E:$E,"Inventory",'Daily Issuance'!$B:$B,">="&DATE(2026,5,1),'Daily Issuance'!$B:$B,"<"&DATE(2026,6,1)),0) -> 16852 | C8: =IFERROR(SUMIFS('Daily Issuance'!$O:$O,'Daily Issuance'!$I:$I,$A8,'Daily Issuance'!$E:$E,"Non Inventory",'Daily Issuance'!$B:$B,">="&DATE(2026,5,1),'Daily Issuance'!$B:$B,"<"&DATE(2026,6,1)),0) -> 6000 | D8: =IFERROR(SUMIFS('Daily Issuance'!$O:$O,'Daily Issuance'!$I:$I,$A8,'Daily Issuance'!$E:$E,"Services",'Daily Issuance'!$B:$B,">="&DATE(2026,5,1),'Daily Issuance'!$B:$B,"<"&DATE(2026,6,1)),0) -> 0 | E8: =IFERROR(SUMIFS('Daily Issuance'!$O:$O,'Daily Issuance'!$I:$I,$A8,'Daily Issuance'!$E:$E,"Patty Cash",'Daily Issuance'!$B:$B,">="&DATE(2026,5,1),'Daily Issuance'!$B:$B,"<"&DATE(2026,6,1)),0) -> 0 | F8: =SUM(B8:E8) -> 22852 | G8: =IFERROR(SUMIFS('Daily Issuance'!$O$4:$O$991,'Daily Issuance'!$I$4:$I$991,$A8,'Daily Issuance'!$E$4:$E$991,"Inventory",'Daily Issuance'!$B$4:$B$991,">="&DATE(2026,6,1),'Daily Issuance'!$B$4:$B$991,"<"&DATE(2026,7,1)),0) -> 1650 | H8: =IFERROR(SUMIFS('Daily Issuance'!$O$4:$O$991,'Daily Issuance'!$I$4:$I$991,$A8,'Daily Issuance'!$E$4:$E$991,"Non Inventory",'Daily Issuance'!$B$4:$B$991,">="&DATE(2026,6,1),'Daily Issuance'!$B$4:$B$991,"<"&DATE(2026,7,1)),0) -> 512 | I8: =IFERROR(SUMIFS('Daily Issuance'!$O$4:$O$991,'Daily Issuance'!$I$4:$I$991,$A8,'Daily Issuance'!$E$4:$E$991,"Services",'Daily Issuance'!$B$4:$B$991,">="&DATE(2026,6,1),'Daily Issuance'!$B$4:$B$991,"<"&DATE(2026,7,1)),0) -> 0 | J8: =IFERROR(SUMIFS('Daily Issuance'!$O:$O,'Daily Issuance'!$I:$I,$A8,'Daily Issuance'!$E:$E,"Patty Cash",'Daily Issuance'!$B:$B,">="&DATE(2026,6,1),'Daily Issuance'!$B:$B,"<"&DATE(2026,7,1)),0) -> 0 | K8: =SUM(G8:J8) -> 2162 | L8: =IFERROR(SUMIFS('Daily Issuance'!$O$4:$O$991,'Daily Issuance'!$I$4:$I$991,$A8,'Daily Issuance'!$E$4:$E$991,"Inventory",'Daily Issuance'!$B$4:$B$991,">="&DATE(2026,7,1),'Daily Issuance'!$B$4:$B$991,"<"&DATE(2026,8,1)),0) -> 0 | M8: =IFERROR(SUMIFS('Daily Issuance'!$O$4:$O$991,'Daily Issuance'!$I$4:$I$991,$A8,'Daily Issuance'!$E$4:$E$991,"Non Inventory",'Daily Issuance'!$B$4:$B$991,">="&DATE(2026,7,1),'Daily Issuance'!$B$4:$B$991,"<"&DATE(2026,8,1)),0) -> 0 | N8: =IFERROR(SUMIFS('Daily Issuance'!$O$4:$O$991,'Daily Issuance'!$I$4:$I$991,$A8,'Daily Issuance'!$E$4:$E$991,"Services",'Daily Issuance'!$B$4:$B$991,">="&DATE(2026,7,1),'Daily Issuance'!$B$4:$B$991,"<"&DATE(2026,8,1)),0) -> 0 | O8: =IFERROR(SUMIFS('Daily Issuance'!$O:$O,'Daily Issuance'!$I:$I,$A8,'Daily Issuance'!$E:$E,"Patty Cash",'Daily Issuance'!$B:$B,">="&DATE(2026,7,1),'Daily Issuance'!$B:$B,"<"&DATE(2026,8,1)),0) -> 0 | P8: =SUM(L8:O8) -> 0 | Q8: =IFERROR(SUMIFS('Daily Issuance'!$O$4:$O$991,'Daily Issuance'!$I$4:$I$991,$A8,'Daily Issuance'!$E$4:$E$991,"Inventory",'Daily Issuance'!$B$4:$B$991,">="&DATE(2026,8,1),'Daily Issuance'!$B$4:$B$991,"<"&DATE(2026,9,1)),0) -> 0 | R8: =IFERROR(SUMIFS('Daily Issuance'!$O$4:$O$991,'Daily Issuance'!$I$4:$I$991,$A8,'Daily Issuance'!$E$4:$E$991,"Non Inventory",'Daily Issuance'!$B$4:$B$991,">="&DATE(2026,8,1),'Daily Issuance'!$B$4:$B$991,"<"&DATE(2026,9,1)),0) -> 0 | S8: =IFERROR(SUMIFS('Daily Issuance'!$O$4:$O$991,'Daily Issuance'!$I$4:$I$991,$A8,'Daily Issuance'!$E$4:$E$991,"Services",'Daily Issuance'!$B$4:$B$991,">="&DATE(2026,8,1),'Daily Issuance'!$B$4:$B$991,"<"&DATE(2026,9,1)),0) -> 0 | T8: =IFERROR(SUMIFS('Daily Issuance'!$O:$O,'Daily Issuance'!$I:$I,$A8,'Daily Issuance'!$E:$E,"Patty Cash",'Daily Issuance'!$B:$B,">="&DATE(2026,8,1),'Daily Issuance'!$B:$B,"<"&DATE(2026,9,1)),0) -> 0 | U8: =SUM(Q8:T8) -> 0 | V8: =IFERROR(SUMIFS('Daily Issuance'!$O$4:$O$991,'Daily Issuance'!$I$4:$I$991,$A8,'Daily Issuance'!$E$4:$E$991,"Inventory",'Daily Issuance'!$B$4:$B$991,">="&DATE(2026,9,1),'Daily Issuance'!$B$4:$B$991,"<"&DATE(2026,10,1)),0) -> 0 | W8: =IFERROR(SUMIFS('Daily Issuance'!$O$4:$O$991,'Daily Issuance'!$I$4:$I$991,$A8,'Daily Issuance'!$E$4:$E$991,"Non Inventory",'Daily Issuance'!$B$4:$B$991,">="&DATE(2026,9,1),'Daily Issuance'!$B$4:$B$991,"<"&DATE(2026,10,1)),0) -> 0 | X8: =IFERROR(SUMIFS('Daily Issuance'!$O$4:$O$991,'Daily Issuance'!$I$4:$I$991,$A8,'Daily Issuance'!$E$4:$E$991,"Services",'Daily Issuance'!$B$4:$B$991,">="&DATE(2026,9,1),'Daily Issuance'!$B$4:$B$991,"<"&DATE(2026,10,1)),0) -> 0 | Y8: =IFERROR(SUMIFS('Daily Issuance'!$O:$O,'Daily Issuance'!$I:$I,$A8,'Daily Issuance'!$E:$E,"Patty Cash",'Daily Issuance'!$B:$B,">="&DATE(2026,9,1),'Daily Issuance'!$B:$B,"<"&DATE(2026,10,1)),0) -> 0 | Z8: =SUM(V8:Y8) -> 0 | AA8: =IFERROR(SUMIFS('Daily Issuance'!$O$4:$O$991,'Daily Issuance'!$I$4:$I$991,$A8,'Daily Issuance'!$E$4:$E$991,"Inventory",'Daily Issuance'!$B$4:$B$991,">="&DATE(2026,10,1),'Daily Issuance'!$B$4:$B$991,"<"&DATE(2026,11,1)),0) -> 0 | AB8: =IFERROR(SUMIFS('Daily Issuance'!$O$4:$O$991,'Daily Issuance'!$I$4:$I$991,$A8,'Daily Issuance'!$E$4:$E$991,"Non Inventory",'Daily Issuance'!$B$4:$B$991,">="&DATE(2026,10,1),'Daily Issuance'!$B$4:$B$991,"<"&DATE(2026,11,1)),0) -> 0 | AC8: =IFERROR(SUMIFS('Daily Issuance'!$O$4:$O$991,'Daily Issuance'!$I$4:$I$991,$A8,'Daily Issuance'!$E$4:$E$991,"Services",'Daily Issuance'!$B$4:$B$991,">="&DATE(2026,10,1),'Daily Issuance'!$B$4:$B$991,"<"&DATE(2026,11,1)),0) -> 0 | AD8: =IFERROR(SUMIFS('Daily Issuance'!$O:$O,'Daily Issuance'!$I:$I,$A8,'Daily Issuance'!$E:$E,"Patty Cash",'Daily Issuance'!$B:$B,">="&DATE(2026,10,1),'Daily Issuance'!$B:$B,"<"&DATE(2026,11,1)),0) -> 0 | AE8: =SUM(AA8:AD8) -> 0 | AF8: =IFERROR(SUMIFS('Daily Issuance'!$O$4:$O$991,'Daily Issuance'!$I$4:$I$991,$A8,'Daily Issuance'!$E$4:$E$991,"Inventory",'Daily Issuance'!$B$4:$B$991,">="&DATE(2026,11,1),'Daily Issuance'!$B$4:$B$991,"<"&DATE(2026,12,1)),0) -> 0 | AG8: =IFERROR(SUMIFS('Daily Issuance'!$O$4:$O$991,'Daily Issuance'!$I$4:$I$991,$A8,'Daily Issuance'!$E$4:$E$991,"Non Inventory",'Daily Issuance'!$B$4:$B$991,">="&DATE(2026,11,1),'Daily Issuance'!$B$4:$B$991,"<"&DATE(2026,12,1)),0) -> 0 | AH8: =IFERROR(SUMIFS('Daily Issuance'!$O$4:$O$991,'Daily Issuance'!$I$4:$I$991,$A8,'Daily Issuance'!$E$4:$E$991,"Services",'Daily Issuance'!$B$4:$B$991,">="&DATE(2026,11,1),'Daily Issuance'!$B$4:$B$991,"<"&DATE(2026,12,1)),0) -> 0 | AI8: =IFERROR(SUMIFS('Daily Issuance'!$O:$O,'Daily Issuance'!$I:$I,$A8,'Daily Issuance'!$E:$E,"Patty Cash",'Daily Issuance'!$B:$B,">="&DATE(2026,11,1),'Daily Issuance'!$B:$B,"<"&DATE(2026,12,1)),0) -> 0 | AJ8: =SUM(AF8:AI8) -> 0 | AK8: =IFERROR(SUMIFS('Daily Issuance'!$O$4:$O$991,'Daily Issuance'!$I$4:$I$991,$A8,'Daily Issuance'!$E$4:$E$991,"Inventory",'Daily Issuance'!$B$4:$B$991,">="&DATE(2026,12,1),'Daily Issuance'!$B$4:$B$991,"<"&DATE(2027,1,1)),0) -> 0 | AL8: =IFERROR(SUMIFS('Daily Issuance'!$O$4:$O$991,'Daily Issuance'!$I$4:$I$991,$A8,'Daily Issuance'!$E$4:$E$991,"Non Inventory",'Daily Issuance'!$B$4:$B$991,">="&DATE(2026,12,1),'Daily Issuance'!$B$4:$B$991,"<"&DATE(2027,1,1)),0) -> 0 | AM8: =IFERROR(SUMIFS('Daily Issuance'!$O$4:$O$991,'Daily Issuance'!$I$4:$I$991,$A8,'Daily Issuance'!$E$4:$E$991,"Services",'Daily Issuance'!$B$4:$B$991,">="&DATE(2026,12,1),'Daily Issuance'!$B$4:$B$991,"<"&DATE(2027,1,1)),0) -> 0 | AN8: =IFERROR(SUMIFS('Daily Issuance'!$O:$O,'Daily Issuance'!$I:$I,$A8,'Daily Issuance'!$E:$E,"Patty Cash",'Daily Issuance'!$B:$B,">="&DATE(2026,12,1),'Daily Issuance'!$B:$B,"<"&DATE(2027,1,1)),0) -> 0 | AO8: =SUM(AK8:AN8) -> 0 | AP8: =SUM(F8,K8,P8,U8,Z8,AE8,AJ8,AO8) -> 25014
A9: Ishida No: 04 | B9: =IFERROR(SUMIFS('Daily Issuance'!$O:$O,'Daily Issuance'!$I:$I,$A9,'Daily Issuance'!$E:$E,"Inventory",'Daily Issuance'!$B:$B,">="&DATE(2026,5,1),'Daily Issuance'!$B:$B,"<"&DATE(2026,6,1)),0) -> 0 | C9: =IFERROR(SUMIFS('Daily Issuance'!$O:$O,'Daily Issuance'!$I:$I,$A9,'Daily Issuance'!$E:$E,"Non Inventory",'Daily Issuance'!$B:$B,">="&DATE(2026,5,1),'Daily Issuance'!$B:$B,"<"&DATE(2026,6,1)),0) -> 256 | D9: =IFERROR(SUMIFS('Daily Issuance'!$O:$O,'Daily Issuance'!$I:$I,$A9,'Daily Issuance'!$E:$E,"Services",'Daily Issuance'!$B:$B,">="&DATE(2026,5,1),'Daily Issuance'!$B:$B,"<"&DATE(2026,6,1)),0) -> 0 | E9: =IFERROR(SUMIFS('Daily Issuance'!$O:$O,'Daily Issuance'!$I:$I,$A9,'Daily Issuance'!$E:$E,"Patty Cash",'Daily Issuance'!$B:$B,">="&DATE(2026,5,1),'Daily Issuance'!$B:$B,"<"&DATE(2026,6,1)),0) -> 0 | F9: =SUM(B9:E9) -> 256 | G9: =IFERROR(SUMIFS('Daily Issuance'!$O$4:$O$991,'Daily Issuance'!$I$4:$I$991,$A9,'Daily Issuance'!$E$4:$E$991,"Inventory",'Daily Issuance'!$B$4:$B$991,">="&DATE(2026,6,1),'Daily Issuance'!$B$4:$B$991,"<"&DATE(2026,7,1)),0) -> 5000 | H9: =IFERROR(SUMIFS('Daily Issuance'!$O$4:$O$991,'Daily Issuance'!$I$4:$I$991,$A9,'Daily Issuance'!$E$4:$E$991,"Non Inventory",'Daily Issuance'!$B$4:$B$991,">="&DATE(2026,6,1),'Daily Issuance'!$B$4:$B$991,"<"&DATE(2026,7,1)),0) -> 512 | I9: =IFERROR(SUMIFS('Daily Issuance'!$O$4:$O$991,'Daily Issuance'!$I$4:$I$991,$A9,'Daily Issuance'!$E$4:$E$991,"Services",'Daily Issuance'!$B$4:$B$991,">="&DATE(2026,6,1),'Daily Issuance'!$B$4:$B$991,"<"&DATE(2026,7,1)),0) -> 0 | J9: =IFERROR(SUMIFS('Daily Issuance'!$O:$O,'Daily Issuance'!$I:$I,$A9,'Daily Issuance'!$E:$E,"Patty Cash",'Daily Issuance'!$B:$B,">="&DATE(2026,6,1),'Daily Issuance'!$B:$B,"<"&DATE(2026,7,1)),0) -> 0 | K9: =SUM(G9:J9) -> 5512 | L9: =IFERROR(SUMIFS('Daily Issuance'!$O$4:$O$991,'Daily Issuance'!$I$4:$I$991,$A9,'Daily Issuance'!$E$4:$E$991,"Inventory",'Daily Issuance'!$B$4:$B$991,">="&DATE(2026,7,1),'Daily Issuance'!$B$4:$B$991,"<"&DATE(2026,8,1)),0) -> 0 | M9: =IFERROR(SUMIFS('Daily Issuance'!$O$4:$O$991,'Daily Issuance'!$I$4:$I$991,$A9,'Daily Issuance'!$E$4:$E$991,"Non Inventory",'Daily Issuance'!$B$4:$B$991,">="&DATE(2026,7,1),'Daily Issuance'!$B$4:$B$991,"<"&DATE(2026,8,1)),0) -> 0 | N9: =IFERROR(SUMIFS('Daily Issuance'!$O$4:$O$991,'Daily Issuance'!$I$4:$I$991,$A9,'Daily Issuance'!$E$4:$E$991,"Services",'Daily Issuance'!$B$4:$B$991,">="&DATE(2026,7,1),'Daily Issuance'!$B$4:$B$991,"<"&DATE(2026,8,1)),0) -> 0 | O9: =IFERROR(SUMIFS('Daily Issuance'!$O:$O,'Daily Issuance'!$I:$I,$A9,'Daily Issuance'!$E:$E,"Patty Cash",'Daily Issuance'!$B:$B,">="&DATE(2026,7,1),'Daily Issuance'!$B:$B,"<"&DATE(2026,8,1)),0) -> 0 | P9: =SUM(L9:O9) -> 0 | Q9: =IFERROR(SUMIFS('Daily Issuance'!$O$4:$O$991,'Daily Issuance'!$I$4:$I$991,$A9,'Daily Issuance'!$E$4:$E$991,"Inventory",'Daily Issuance'!$B$4:$B$991,">="&DATE(2026,8,1),'Daily Issuance'!$B$4:$B$991,"<"&DATE(2026,9,1)),0) -> 0 | R9: =IFERROR(SUMIFS('Daily Issuance'!$O$4:$O$991,'Daily Issuance'!$I$4:$I$991,$A9,'Daily Issuance'!$E$4:$E$991,"Non Inventory",'Daily Issuance'!$B$4:$B$991,">="&DATE(2026,8,1),'Daily Issuance'!$B$4:$B$991,"<"&DATE(2026,9,1)),0) -> 0 | S9: =IFERROR(SUMIFS('Daily Issuance'!$O$4:$O$991,'Daily Issuance'!$I$4:$I$991,$A9,'Daily Issuance'!$E$4:$E$991,"Services",'Daily Issuance'!$B$4:$B$991,">="&DATE(2026,8,1),'Daily Issuance'!$B$4:$B$991,"<"&DATE(2026,9,1)),0) -> 0 | T9: =IFERROR(SUMIFS('Daily Issuance'!$O:$O,'Daily Issuance'!$I:$I,$A9,'Daily Issuance'!$E:$E,"Patty Cash",'Daily Issuance'!$B:$B,">="&DATE(2026,8,1),'Daily Issuance'!$B:$B,"<"&DATE(2026,9,1)),0) -> 0 | U9: =SUM(Q9:T9) -> 0 | V9: =IFERROR(SUMIFS('Daily Issuance'!$O$4:$O$991,'Daily Issuance'!$I$4:$I$991,$A9,'Daily Issuance'!$E$4:$E$991,"Inventory",'Daily Issuance'!$B$4:$B$991,">="&DATE(2026,9,1),'Daily Issuance'!$B$4:$B$991,"<"&DATE(2026,10,1)),0) -> 0 | W9: =IFERROR(SUMIFS('Daily Issuance'!$O$4:$O$991,'Daily Issuance'!$I$4:$I$991,$A9,'Daily Issuance'!$E$4:$E$991,"Non Inventory",'Daily Issuance'!$B$4:$B$991,">="&DATE(2026,9,1),'Daily Issuance'!$B$4:$B$991,"<"&DATE(2026,10,1)),0) -> 0 | X9: =IFERROR(SUMIFS('Daily Issuance'!$O$4:$O$991,'Daily Issuance'!$I$4:$I$991,$A9,'Daily Issuance'!$E$4:$E$991,"Services",'Daily Issuance'!$B$4:$B$991,">="&DATE(2026,9,1),'Daily Issuance'!$B$4:$B$991,"<"&DATE(2026,10,1)),0) -> 0 | Y9: =IFERROR(SUMIFS('Daily Issuance'!$O:$O,'Daily Issuance'!$I:$I,$A9,'Daily Issuance'!$E:$E,"Patty Cash",'Daily Issuance'!$B:$B,">="&DATE(2026,9,1),'Daily Issuance'!$B:$B,"<"&DATE(2026,10,1)),0) -> 0 | Z9: =SUM(V9:Y9) -> 0 | AA9: =IFERROR(SUMIFS('Daily Issuance'!$O$4:$O$991,'Daily Issuance'!$I$4:$I$991,$A9,'Daily Issuance'!$E$4:$E$991,"Inventory",'Daily Issuance'!$B$4:$B$991,">="&DATE(2026,10,1),'Daily Issuance'!$B$4:$B$991,"<"&DATE(2026,11,1)),0) -> 0 | AB9: =IFERROR(SUMIFS('Daily Issuance'!$O$4:$O$991,'Daily Issuance'!$I$4:$I$991,$A9,'Daily Issuance'!$E$4:$E$991,"Non Inventory",'Daily Issuance'!$B$4:$B$991,">="&DATE(2026,10,1),'Daily Issuance'!$B$4:$B$991,"<"&DATE(2026,11,1)),0) -> 0 | AC9: =IFERROR(SUMIFS('Daily Issuance'!$O$4:$O$991,'Daily Issuance'!$I$4:$I$991,$A9,'Daily Issuance'!$E$4:$E$991,"Services",'Daily Issuance'!$B$4:$B$991,">="&DATE(2026,10,1),'Daily Issuance'!$B$4:$B$991,"<"&DATE(2026,11,1)),0) -> 0 | AD9: =IFERROR(SUMIFS('Daily Issuance'!$O:$O,'Daily Issuance'!$I:$I,$A9,'Daily Issuance'!$E:$E,"Patty Cash",'Daily Issuance'!$B:$B,">="&DATE(2026,10,1),'Daily Issuance'!$B:$B,"<"&DATE(2026,11,1)),0) -> 0 | AE9: =SUM(AA9:AD9) -> 0 | AF9: =IFERROR(SUMIFS('Daily Issuance'!$O$4:$O$991,'Daily Issuance'!$I$4:$I$991,$A9,'Daily Issuance'!$E$4:$E$991,"Inventory",'Daily Issuance'!$B$4:$B$991,">="&DATE(2026,11,1),'Daily Issuance'!$B$4:$B$991,"<"&DATE(2026,12,1)),0) -> 0 | AG9: =IFERROR(SUMIFS('Daily Issuance'!$O$4:$O$991,'Daily Issuance'!$I$4:$I$991,$A9,'Daily Issuance'!$E$4:$E$991,"Non Inventory",'Daily Issuance'!$B$4:$B$991,">="&DATE(2026,11,1),'Daily Issuance'!$B$4:$B$991,"<"&DATE(2026,12,1)),0) -> 0 | AH9: =IFERROR(SUMIFS('Daily Issuance'!$O$4:$O$991,'Daily Issuance'!$I$4:$I$991,$A9,'Daily Issuance'!$E$4:$E$991,"Services",'Daily Issuance'!$B$4:$B$991,">="&DATE(2026,11,1),'Daily Issuance'!$B$4:$B$991,"<"&DATE(2026,12,1)),0) -> 0 | AI9: =IFERROR(SUMIFS('Daily Issuance'!$O:$O,'Daily Issuance'!$I:$I,$A9,'Daily Issuance'!$E:$E,"Patty Cash",'Daily Issuance'!$B:$B,">="&DATE(2026,11,1),'Daily Issuance'!$B:$B,"<"&DATE(2026,12,1)),0) -> 0 | AJ9: =SUM(AF9:AI9) -> 0 | AK9: =IFERROR(SUMIFS('Daily Issuance'!$O$4:$O$991,'Daily Issuance'!$I$4:$I$991,$A9,'Daily Issuance'!$E$4:$E$991,"Inventory",'Daily Issuance'!$B$4:$B$991,">="&DATE(2026,12,1),'Daily Issuance'!$B$4:$B$991,"<"&DATE(2027,1,1)),0) -> 0 | AL9: =IFERROR(SUMIFS('Daily Issuance'!$O$4:$O$991,'Daily Issuance'!$I$4:$I$991,$A9,'Daily Issuance'!$E$4:$E$991,"Non Inventory",'Daily Issuance'!$B$4:$B$991,">="&DATE(2026,12,1),'Daily Issuance'!$B$4:$B$991,"<"&DATE(2027,1,1)),0) -> 0 | AM9: =IFERROR(SUMIFS('Daily Issuance'!$O$4:$O$991,'Daily Issuance'!$I$4:$I$991,$A9,'Daily Issuance'!$E$4:$E$991,"Services",'Daily Issuance'!$B$4:$B$991,">="&DATE(2026,12,1),'Daily Issuance'!$B$4:$B$991,"<"&DATE(2027,1,1)),0) -> 0 | AN9: =IFERROR(SUMIFS('Daily Issuance'!$O:$O,'Daily Issuance'!$I:$I,$A9,'Daily Issuance'!$E:$E,"Patty Cash",'Daily Issuance'!$B:$B,">="&DATE(2026,12,1),'Daily Issuance'!$B:$B,"<"&DATE(2027,1,1)),0) -> 0 | AO9: =SUM(AK9:AN9) -> 0 | AP9: =SUM(F9,K9,P9,U9,Z9,AE9,AJ9,AO9) -> 5768
A10: Ishida No: 05 | B10: =IFERROR(SUMIFS('Daily Issuance'!$O:$O,'Daily Issuance'!$I:$I,$A10,'Daily Issuance'!$E:$E,"Inventory",'Daily Issuance'!$B:$B,">="&DATE(2026,5,1),'Daily Issuance'!$B:$B,"<"&DATE(2026,6,1)),0) -> 15650 | C10: =IFERROR(SUMIFS('Daily Issuance'!$O:$O,'Daily Issuance'!$I:$I,$A10,'Daily Issuance'!$E:$E,"Non Inventory",'Daily Issuance'!$B:$B,">="&DATE(2026,5,1),'Daily Issuance'!$B:$B,"<"&DATE(2026,6,1)),0) -> 1650 | D10: =IFERROR(SUMIFS('Daily Issuance'!$O:$O,'Daily Issuance'!$I:$I,$A10,'Daily Issuance'!$E:$E,"Services",'Daily Issuance'!$B:$B,">="&DATE(2026,5,1),'Daily Issuance'!$B:$B,"<"&DATE(2026,6,1)),0) -> 0 | E10: =IFERROR(SUMIFS('Daily Issuance'!$O:$O,'Daily Issuance'!$I:$I,$A10,'Daily Issuance'!$E:$E,"Patty Cash",'Daily Issuance'!$B:$B,">="&DATE(2026,5,1),'Daily Issuance'!$B:$B,"<"&DATE(2026,6,1)),0) -> 0 | F10: =SUM(B10:E10) -> 17300 | G10: =IFERROR(SUMIFS('Daily Issuance'!$O$4:$O$991,'Daily Issuance'!$I$4:$I$991,$A10,'Daily Issuance'!$E$4:$E$991,"Inventory",'Daily Issuance'!$B$4:$B$991,">="&DATE(2026,6,1),'Daily Issuance'!$B$4:$B$991,"<"&DATE(2026,7,1)),0) -> 470 | H10: =IFERROR(SUMIFS('Daily Issuance'!$O$4:$O$991,'Daily Issuance'!$I$4:$I$991,$A10,'Daily Issuance'!$E$4:$E$991,"Non Inventory",'Daily Issuance'!$B$4:$B$991,">="&DATE(2026,6,1),'Daily Issuance'!$B$4:$B$991,"<"&DATE(2026,7,1)),0) -> 512 | I10: =IFERROR(SUMIFS('Daily Issuance'!$O$4:$O$991,'Daily Issuance'!$I$4:$I$991,$A10,'Daily Issuance'!$E$4:$E$991,"Services",'Daily Issuance'!$B$4:$B$991,">="&DATE(2026,6,1),'Daily Issuance'!$B$4:$B$991,"<"&DATE(2026,7,1)),0) -> 0 | J10: =IFERROR(SUMIFS('Daily Issuance'!$O:$O,'Daily Issuance'!$I:$I,$A10,'Daily Issuance'!$E:$E,"Patty Cash",'Daily Issuance'!$B:$B,">="&DATE(2026,6,1),'Daily Issuance'!$B:$B,"<"&DATE(2026,7,1)),0) -> 0 | K10: =SUM(G10:J10) -> 982 | L10: =IFERROR(SUMIFS('Daily Issuance'!$O$4:$O$991,'Daily Issuance'!$I$4:$I$991,$A10,'Daily Issuance'!$E$4:$E$991,"Inventory",'Daily Issuance'!$B$4:$B$991,">="&DATE(2026,7,1),'Daily Issuance'!$B$4:$B$991,"<"&DATE(2026,8,1)),0) -> 0 | M10: =IFERROR(SUMIFS('Daily Issuance'!$O$4:$O$991,'Daily Issuance'!$I$4:$I$991,$A10,'Daily Issuance'!$E$4:$E$991,"Non Inventory",'Daily Issuance'!$B$4:$B$991,">="&DATE(2026,7,1),'Daily Issuance'!$B$4:$B$991,"<"&DATE(2026,8,1)),0) -> 0 | N10: =IFERROR(SUMIFS('Daily Issuance'!$O$4:$O$991,'Daily Issuance'!$I$4:$I$991,$A10,'Daily Issuance'!$E$4:$E$991,"Services",'Daily Issuance'!$B$4:$B$991,">="&DATE(2026,7,1),'Daily Issuance'!$B$4:$B$991,"<"&DATE(2026,8,1)),0) -> 0 | O10: =IFERROR(SUMIFS('Daily Issuance'!$O:$O,'Daily Issuance'!$I:$I,$A10,'Daily Issuance'!$E:$E,"Patty Cash",'Daily Issuance'!$B:$B,">="&DATE(2026,7,1),'Daily Issuance'!$B:$B,"<"&DATE(2026,8,1)),0) -> 0 | P10: =SUM(L10:O10) -> 0 | Q10: =IFERROR(SUMIFS('Daily Issuance'!$O$4:$O$991,'Daily Issuance'!$I$4:$I$991,$A10,'Daily Issuance'!$E$4:$E$991,"Inventory",'Daily Issuance'!$B$4:$B$991,">="&DATE(2026,8,1),'Daily Issuance'!$B$4:$B$991,"<"&DATE(2026,9,1)),0) -> 0 | R10: =IFERROR(SUMIFS('Daily Issuance'!$O$4:$O$991,'Daily Issuance'!$I$4:$I$991,$A10,'Daily Issuance'!$E$4:$E$991,"Non Inventory",'Daily Issuance'!$B$4:$B$991,">="&DATE(2026,8,1),'Daily Issuance'!$B$4:$B$991,"<"&DATE(2026,9,1)),0) -> 0 | S10: =IFERROR(SUMIFS('Daily Issuance'!$O$4:$O$991,'Daily Issuance'!$I$4:$I$991,$A10,'Daily Issuance'!$E$4:$E$991,"Services",'Daily Issuance'!$B$4:$B$991,">="&DATE(2026,8,1),'Daily Issuance'!$B$4:$B$991,"<"&DATE(2026,9,1)),0) -> 0 | T10: =IFERROR(SUMIFS('Daily Issuance'!$O:$O,'Daily Issuance'!$I:$I,$A10,'Daily Issuance'!$E:$E,"Patty Cash",'Daily Issuance'!$B:$B,">="&DATE(2026,8,1),'Daily Issuance'!$B:$B,"<"&DATE(2026,9,1)),0) -> 0 | U10: =SUM(Q10:T10) -> 0 | V10: =IFERROR(SUMIFS('Daily Issuance'!$O$4:$O$991,'Daily Issuance'!$I$4:$I$991,$A10,'Daily Issuance'!$E$4:$E$991,"Inventory",'Daily Issuance'!$B$4:$B$991,">="&DATE(2026,9,1),'Daily Issuance'!$B$4:$B$991,"<"&DATE(2026,10,1)),0) -> 0 | W10: =IFERROR(SUMIFS('Daily Issuance'!$O$4:$O$991,'Daily Issuance'!$I$4:$I$991,$A10,'Daily Issuance'!$E$4:$E$991,"Non Inventory",'Daily Issuance'!$B$4:$B$991,">="&DATE(2026,9,1),'Daily Issuance'!$B$4:$B$991,"<"&DATE(2026,10,1)),0) -> 0 | X10: =IFERROR(SUMIFS('Daily Issuance'!$O$4:$O$991,'Daily Issuance'!$I$4:$I$991,$A10,'Daily Issuance'!$E$4:$E$991,"Services",'Daily Issuance'!$B$4:$B$991,">="&DATE(2026,9,1),'Daily Issuance'!$B$4:$B$991,"<"&DATE(2026,10,1)),0) -> 0 | Y10: =IFERROR(SUMIFS('Daily Issuance'!$O:$O,'Daily Issuance'!$I:$I,$A10,'Daily Issuance'!$E:$E,"Patty Cash",'Daily Issuance'!$B:$B,">="&DATE(2026,9,1),'Daily Issuance'!$B:$B,"<"&DATE(2026,10,1)),0) -> 0 | Z10: =SUM(V10:Y10) -> 0 | AA10: =IFERROR(SUMIFS('Daily Issuance'!$O$4:$O$991,'Daily Issuance'!$I$4:$I$991,$A10,'Daily Issuance'!$E$4:$E$991,"Inventory",'Daily Issuance'!$B$4:$B$991,">="&DATE(2026,10,1),'Daily Issuance'!$B$4:$B$991,"<"&DATE(2026,11,1)),0) -> 0 | AB10: =IFERROR(SUMIFS('Daily Issuance'!$O$4:$O$991,'Daily Issuance'!$I$4:$I$991,$A10,'Daily Issuance'!$E$4:$E$991,"Non Inventory",'Daily Issuance'!$B$4:$B$991,">="&DATE(2026,10,1),'Daily Issuance'!$B$4:$B$991,"<"&DATE(2026,11,1)),0) -> 0 | AC10: =IFERROR(SUMIFS('Daily Issuance'!$O$4:$O$991,'Daily Issuance'!$I$4:$I$991,$A10,'Daily Issuance'!$E$4:$E$991,"Services",'Daily Issuance'!$B$4:$B$991,">="&DATE(2026,10,1),'Daily Issuance'!$B$4:$B$991,"<"&DATE(2026,11,1)),0) -> 0 | AD10: =IFERROR(SUMIFS('Daily Issuance'!$O:$O,'Daily Issuance'!$I:$I,$A10,'Daily Issuance'!$E:$E,"Patty Cash",'Daily Issuance'!$B:$B,">="&DATE(2026,10,1),'Daily Issuance'!$B:$B,"<"&DATE(2026,11,1)),0) -> 0 | AE10: =SUM(AA10:AD10) -> 0 | AF10: =IFERROR(SUMIFS('Daily Issuance'!$O$4:$O$991,'Daily Issuance'!$I$4:$I$991,$A10,'Daily Issuance'!$E$4:$E$991,"Inventory",'Daily Issuance'!$B$4:$B$991,">="&DATE(2026,11,1),'Daily Issuance'!$B$4:$B$991,"<"&DATE(2026,12,1)),0) -> 0 | AG10: =IFERROR(SUMIFS('Daily Issuance'!$O$4:$O$991,'Daily Issuance'!$I$4:$I$991,$A10,'Daily Issuance'!$E$4:$E$991,"Non Inventory",'Daily Issuance'!$B$4:$B$991,">="&DATE(2026,11,1),'Daily Issuance'!$B$4:$B$991,"<"&DATE(2026,12,1)),0) -> 0 | AH10: =IFERROR(SUMIFS('Daily Issuance'!$O$4:$O$991,'Daily Issuance'!$I$4:$I$991,$A10,'Daily Issuance'!$E$4:$E$991,"Services",'Daily Issuance'!$B$4:$B$991,">="&DATE(2026,11,1),'Daily Issuance'!$B$4:$B$991,"<"&DATE(2026,12,1)),0) -> 0 | AI10: =IFERROR(SUMIFS('Daily Issuance'!$O:$O,'Daily Issuance'!$I:$I,$A10,'Daily Issuance'!$E:$E,"Patty Cash",'Daily Issuance'!$B:$B,">="&DATE(2026,11,1),'Daily Issuance'!$B:$B,"<"&DATE(2026,12,1)),0) -> 0 | AJ10: =SUM(AF10:AI10) -> 0 | AK10: =IFERROR(SUMIFS('Daily Issuance'!$O$4:$O$991,'Daily Issuance'!$I$4:$I$991,$A10,'Daily Issuance'!$E$4:$E$991,"Inventory",'Daily Issuance'!$B$4:$B$991,">="&DATE(2026,12,1),'Daily Issuance'!$B$4:$B$991,"<"&DATE(2027,1,1)),0) -> 0 | AL10: =IFERROR(SUMIFS('Daily Issuance'!$O$4:$O$991,'Daily Issuance'!$I$4:$I$991,$A10,'Daily Issuance'!$E$4:$E$991,"Non Inventory",'Daily Issuance'!$B$4:$B$991,">="&DATE(2026,12,1),'Daily Issuance'!$B$4:$B$991,"<"&DATE(2027,1,1)),0) -> 0 | AM10: =IFERROR(SUMIFS('Daily Issuance'!$O$4:$O$991,'Daily Issuance'!$I$4:$I$991,$A10,'Daily Issuance'!$E$4:$E$991,"Services",'Daily Issuance'!$B$4:$B$991,">="&DATE(2026,12,1),'Daily Issuance'!$B$4:$B$991,"<"&DATE(2027,1,1)),0) -> 0 | AN10: =IFERROR(SUMIFS('Daily Issuance'!$O:$O,'Daily Issuance'!$I:$I,$A10,'Daily Issuance'!$E:$E,"Patty Cash",'Daily Issuance'!$B:$B,">="&DATE(2026,12,1),'Daily Issuance'!$B:$B,"<"&DATE(2027,1,1)),0) -> 0 | AO10: =SUM(AK10:AN10) -> 0 | AP10: =SUM(F10,K10,P10,U10,Z10,AE10,AJ10,AO10) -> 18282
A11: Ishida No: 06 | B11: =IFERROR(SUMIFS('Daily Issuance'!$O:$O,'Daily Issuance'!$I:$I,$A11,'Daily Issuance'!$E:$E,"Inventory",'Daily Issuance'!$B:$B,">="&DATE(2026,5,1),'Daily Issuance'!$B:$B,"<"&DATE(2026,6,1)),0) -> 10000 | C11: =IFERROR(SUMIFS('Daily Issuance'!$O:$O,'Daily Issuance'!$I:$I,$A11,'Daily Issuance'!$E:$E,"Non Inventory",'Daily Issuance'!$B:$B,">="&DATE(2026,5,1),'Daily Issuance'!$B:$B,"<"&DATE(2026,6,1)),0) -> 1456 | D11: =IFERROR(SUMIFS('Daily Issuance'!$O:$O,'Daily Issuance'!$I:$I,$A11,'Daily Issuance'!$E:$E,"Services",'Daily Issuance'!$B:$B,">="&DATE(2026,5,1),'Daily Issuance'!$B:$B,"<"&DATE(2026,6,1)),0) -> 0 | E11: =IFERROR(SUMIFS('Daily Issuance'!$O:$O,'Daily Issuance'!$I:$I,$A11,'Daily Issuance'!$E:$E,"Patty Cash",'Daily Issuance'!$B:$B,">="&DATE(2026,5,1),'Daily Issuance'!$B:$B,"<"&DATE(2026,6,1)),0) -> 0 | F11: =SUM(B11:E11) -> 11456 | G11: =IFERROR(SUMIFS('Daily Issuance'!$O$4:$O$991,'Daily Issuance'!$I$4:$I$991,$A11,'Daily Issuance'!$E$4:$E$991,"Inventory",'Daily Issuance'!$B$4:$B$991,">="&DATE(2026,6,1),'Daily Issuance'!$B$4:$B$991,"<"&DATE(2026,7,1)),0) -> 4900 | H11: =IFERROR(SUMIFS('Daily Issuance'!$O$4:$O$991,'Daily Issuance'!$I$4:$I$991,$A11,'Daily Issuance'!$E$4:$E$991,"Non Inventory",'Daily Issuance'!$B$4:$B$991,">="&DATE(2026,6,1),'Daily Issuance'!$B$4:$B$991,"<"&DATE(2026,7,1)),0) -> 512 | I11: =IFERROR(SUMIFS('Daily Issuance'!$O$4:$O$991,'Daily Issuance'!$I$4:$I$991,$A11,'Daily Issuance'!$E$4:$E$991,"Services",'Daily Issuance'!$B$4:$B$991,">="&DATE(2026,6,1),'Daily Issuance'!$B$4:$B$991,"<"&DATE(2026,7,1)),0) -> 0 | J11: =IFERROR(SUMIFS('Daily Issuance'!$O:$O,'Daily Issuance'!$I:$I,$A11,'Daily Issuance'!$E:$E,"Patty Cash",'Daily Issuance'!$B:$B,">="&DATE(2026,6,1),'Daily Issuance'!$B:$B,"<"&DATE(2026,7,1)),0) -> 0 | K11: =SUM(G11:J11) -> 5412 | L11: =IFERROR(SUMIFS('Daily Issuance'!$O$4:$O$991,'Daily Issuance'!$I$4:$I$991,$A11,'Daily Issuance'!$E$4:$E$991,"Inventory",'Daily Issuance'!$B$4:$B$991,">="&DATE(2026,7,1),'Daily Issuance'!$B$4:$B$991,"<"&DATE(2026,8,1)),0) -> 0 | M11: =IFERROR(SUMIFS('Daily Issuance'!$O$4:$O$991,'Daily Issuance'!$I$4:$I$991,$A11,'Daily Issuance'!$E$4:$E$991,"Non Inventory",'Daily Issuance'!$B$4:$B$991,">="&DATE(2026,7,1),'Daily Issuance'!$B$4:$B$991,"<"&DATE(2026,8,1)),0) -> 0 | N11: =IFERROR(SUMIFS('Daily Issuance'!$O$4:$O$991,'Daily Issuance'!$I$4:$I$991,$A11,'Daily Issuance'!$E$4:$E$991,"Services",'Daily Issuance'!$B$4:$B$991,">="&DATE(2026,7,1),'Daily Issuance'!$B$4:$B$991,"<"&DATE(2026,8,1)),0) -> 0 | O11: =IFERROR(SUMIFS('Daily Issuance'!$O:$O,'Daily Issuance'!$I:$I,$A11,'Daily Issuance'!$E:$E,"Patty Cash",'Daily Issuance'!$B:$B,">="&DATE(2026,7,1),'Daily Issuance'!$B:$B,"<"&DATE(2026,8,1)),0) -> 0 | P11: =SUM(L11:O11) -> 0 | Q11: =IFERROR(SUMIFS('Daily Issuance'!$O$4:$O$991,'Daily Issuance'!$I$4:$I$991,$A11,'Daily Issuance'!$E$4:$E$991,"Inventory",'Daily Issuance'!$B$4:$B$991,">="&DATE(2026,8,1),'Daily Issuance'!$B$4:$B$991,"<"&DATE(2026,9,1)),0) -> 0 | R11: =IFERROR(SUMIFS('Daily Issuance'!$O$4:$O$991,'Daily Issuance'!$I$4:$I$991,$A11,'Daily Issuance'!$E$4:$E$991,"Non Inventory",'Daily Issuance'!$B$4:$B$991,">="&DATE(2026,8,1),'Daily Issuance'!$B$4:$B$991,"<"&DATE(2026,9,1)),0) -> 0 | S11: =IFERROR(SUMIFS('Daily Issuance'!$O$4:$O$991,'Daily Issuance'!$I$4:$I$991,$A11,'Daily Issuance'!$E$4:$E$991,"Services",'Daily Issuance'!$B$4:$B$991,">="&DATE(2026,8,1),'Daily Issuance'!$B$4:$B$991,"<"&DATE(2026,9,1)),0) -> 0 | T11: =IFERROR(SUMIFS('Daily Issuance'!$O:$O,'Daily Issuance'!$I:$I,$A11,'Daily Issuance'!$E:$E,"Patty Cash",'Daily Issuance'!$B:$B,">="&DATE(2026,8,1),'Daily Issuance'!$B:$B,"<"&DATE(2026,9,1)),0) -> 0 | U11: =SUM(Q11:T11) -> 0 | V11: =IFERROR(SUMIFS('Daily Issuance'!$O$4:$O$991,'Daily Issuance'!$I$4:$I$991,$A11,'Daily Issuance'!$E$4:$E$991,"Inventory",'Daily Issuance'!$B$4:$B$991,">="&DATE(2026,9,1),'Daily Issuance'!$B$4:$B$991,"<"&DATE(2026,10,1)),0) -> 0 | W11: =IFERROR(SUMIFS('Daily Issuance'!$O$4:$O$991,'Daily Issuance'!$I$4:$I$991,$A11,'Daily Issuance'!$E$4:$E$991,"Non Inventory",'Daily Issuance'!$B$4:$B$991,">="&DATE(2026,9,1),'Daily Issuance'!$B$4:$B$991,"<"&DATE(2026,10,1)),0) -> 0 | X11: =IFERROR(SUMIFS('Daily Issuance'!$O$4:$O$991,'Daily Issuance'!$I$4:$I$991,$A11,'Daily Issuance'!$E$4:$E$991,"Services",'Daily Issuance'!$B$4:$B$991,">="&DATE(2026,9,1),'Daily Issuance'!$B$4:$B$991,"<"&DATE(2026,10,1)),0) -> 0 | Y11: =IFERROR(SUMIFS('Daily Issuance'!$O:$O,'Daily Issuance'!$I:$I,$A11,'Daily Issuance'!$E:$E,"Patty Cash",'Daily Issuance'!$B:$B,">="&DATE(2026,9,1),'Daily Issuance'!$B:$B,"<"&DATE(2026,10,1)),0) -> 0 | Z11: =SUM(V11:Y11) -> 0 | AA11: =IFERROR(SUMIFS('Daily Issuance'!$O$4:$O$991,'Daily Issuance'!$I$4:$I$991,$A11,'Daily Issuance'!$E$4:$E$991,"Inventory",'Daily Issuance'!$B$4:$B$991,">="&DATE(2026,10,1),'Daily Issuance'!$B$4:$B$991,"<"&DATE(2026,11,1)),0) -> 0 | AB11: =IFERROR(SUMIFS('Daily Issuance'!$O$4:$O$991,'Daily Issuance'!$I$4:$I$991,$A11,'Daily Issuance'!$E$4:$E$991,"Non Inventory",'Daily Issuance'!$B$4:$B$991,">="&DATE(2026,10,1),'Daily Issuance'!$B$4:$B$991,"<"&DATE(2026,11,1)),0) -> 0 | AC11: =IFERROR(SUMIFS('Daily Issuance'!$O$4:$O$991,'Daily Issuance'!$I$4:$I$991,$A11,'Daily Issuance'!$E$4:$E$991,"Services",'Daily Issuance'!$B$4:$B$991,">="&DATE(2026,10,1),'Daily Issuance'!$B$4:$B$991,"<"&DATE(2026,11,1)),0) -> 0 | AD11: =IFERROR(SUMIFS('Daily Issuance'!$O:$O,'Daily Issuance'!$I:$I,$A11,'Daily Issuance'!$E:$E,"Patty Cash",'Daily Issuance'!$B:$B,">="&DATE(2026,10,1),'Daily Issuance'!$B:$B,"<"&DATE(2026,11,1)),0) -> 0 | AE11: =SUM(AA11:AD11) -> 0 | AF11: =IFERROR(SUMIFS('Daily Issuance'!$O$4:$O$991,'Daily Issuance'!$I$4:$I$991,$A11,'Daily Issuance'!$E$4:$E$991,"Inventory",'Daily Issuance'!$B$4:$B$991,">="&DATE(2026,11,1),'Daily Issuance'!$B$4:$B$991,"<"&DATE(2026,12,1)),0) -> 0 | AG11: =IFERROR(SUMIFS('Daily Issuance'!$O$4:$O$991,'Daily Issuance'!$I$4:$I$991,$A11,'Daily Issuance'!$E$4:$E$991,"Non Inventory",'Daily Issuance'!$B$4:$B$991,">="&DATE(2026,11,1),'Daily Issuance'!$B$4:$B$991,"<"&DATE(2026,12,1)),0) -> 0 | AH11: =IFERROR(SUMIFS('Daily Issuance'!$O$4:$O$991,'Daily Issuance'!$I$4:$I$991,$A11,'Daily Issuance'!$E$4:$E$991,"Services",'Daily Issuance'!$B$4:$B$991,">="&DATE(2026,11,1),'Daily Issuance'!$B$4:$B$991,"<"&DATE(2026,12,1)),0) -> 0 | AI11: =IFERROR(SUMIFS('Daily Issuance'!$O:$O,'Daily Issuance'!$I:$I,$A11,'Daily Issuance'!$E:$E,"Patty Cash",'Daily Issuance'!$B:$B,">="&DATE(2026,11,1),'Daily Issuance'!$B:$B,"<"&DATE(2026,12,1)),0) -> 0 | AJ11: =SUM(AF11:AI11) -> 0 | AK11: =IFERROR(SUMIFS('Daily Issuance'!$O$4:$O$991,'Daily Issuance'!$I$4:$I$991,$A11,'Daily Issuance'!$E$4:$E$991,"Inventory",'Daily Issuance'!$B$4:$B$991,">="&DATE(2026,12,1),'Daily Issuance'!$B$4:$B$991,"<"&DATE(2027,1,1)),0) -> 0 | AL11: =IFERROR(SUMIFS('Daily Issuance'!$O$4:$O$991,'Daily Issuance'!$I$4:$I$991,$A11,'Daily Issuance'!$E$4:$E$991,"Non Inventory",'Daily Issuance'!$B$4:$B$991,">="&DATE(2026,12,1),'Daily Issuance'!$B$4:$B$991,"<"&DATE(2027,1,1)),0) -> 0 | AM11: =IFERROR(SUMIFS('Daily Issuance'!$O$4:$O$991,'Daily Issuance'!$I$4:$I$991,$A11,'Daily Issuance'!$E$4:$E$991,"Services",'Daily Issuance'!$B$4:$B$991,">="&DATE(2026,12,1),'Daily Issuance'!$B$4:$B$991,"<"&DATE(2027,1,1)),0) -> 0 | AN11: =IFERROR(SUMIFS('Daily Issuance'!$O:$O,'Daily Issuance'!$I:$I,$A11,'Daily Issuance'!$E:$E,"Patty Cash",'Daily Issuance'!$B:$B,">="&DATE(2026,12,1),'Daily Issuance'!$B:$B,"<"&DATE(2027,1,1)),0) -> 0 | AO11: =SUM(AK11:AN11) -> 0 | AP11: =SUM(F11,K11,P11,U11,Z11,AE11,AJ11,AO11) -> 16868
A12: Ishida No: 07 | B12: =IFERROR(SUMIFS('Daily Issuance'!$O:$O,'Daily Issuance'!$I:$I,$A12,'Daily Issuance'!$E:$E,"Inventory",'Daily Issuance'!$B:$B,">="&DATE(2026,5,1),'Daily Issuance'!$B:$B,"<"&DATE(2026,6,1)),0) -> 4638 | C12: =IFERROR(SUMIFS('Daily Issuance'!$O:$O,'Daily Issuance'!$I:$I,$A12,'Daily Issuance'!$E:$E,"Non Inventory",'Daily Issuance'!$B:$B,">="&DATE(2026,5,1),'Daily Issuance'!$B:$B,"<"&DATE(2026,6,1)),0) -> 0 | D12: =IFERROR(SUMIFS('Daily Issuance'!$O:$O,'Daily Issuance'!$I:$I,$A12,'Daily Issuance'!$E:$E,"Services",'Daily Issuance'!$B:$B,">="&DATE(2026,5,1),'Daily Issuance'!$B:$B,"<"&DATE(2026,6,1)),0) -> 0 | E12: =IFERROR(SUMIFS('Daily Issuance'!$O:$O,'Daily Issuance'!$I:$I,$A12,'Daily Issuance'!$E:$E,"Patty Cash",'Daily Issuance'!$B:$B,">="&DATE(2026,5,1),'Daily Issuance'!$B:$B,"<"&DATE(2026,6,1)),0) -> 0 | F12: =SUM(B12:E12) -> 4638 | G12: =IFERROR(SUMIFS('Daily Issuance'!$O$4:$O$991,'Daily Issuance'!$I$4:$I$991,$A12,'Daily Issuance'!$E$4:$E$991,"Inventory",'Daily Issuance'!$B$4:$B$991,">="&DATE(2026,6,1),'Daily Issuance'!$B$4:$B$991,"<"&DATE(2026,7,1)),0) -> 0 | H12: =IFERROR(SUMIFS('Daily Issuance'!$O$4:$O$991,'Daily Issuance'!$I$4:$I$991,$A12,'Daily Issuance'!$E$4:$E$991,"Non Inventory",'Daily Issuance'!$B$4:$B$991,">="&DATE(2026,6,1),'Daily Issuance'!$B$4:$B$991,"<"&DATE(2026,7,1)),0) -> 256 | I12: =IFERROR(SUMIFS('Daily Issuance'!$O$4:$O$991,'Daily Issuance'!$I$4:$I$991,$A12,'Daily Issuance'!$E$4:$E$991,"Services",'Daily Issuance'!$B$4:$B$991,">="&DATE(2026,6,1),'Daily Issuance'!$B$4:$B$991,"<"&DATE(2026,7,1)),0) -> 0 | J12: =IFERROR(SUMIFS('Daily Issuance'!$O:$O,'Daily Issuance'!$I:$I,$A12,'Daily Issuance'!$E:$E,"Patty Cash",'Daily Issuance'!$B:$B,">="&DATE(2026,6,1),'Daily Issuance'!$B:$B,"<"&DATE(2026,7,1)),0) -> 0 | K12: =SUM(G12:J12) -> 256 | L12: =IFERROR(SUMIFS('Daily Issuance'!$O$4:$O$991,'Daily Issuance'!$I$4:$I$991,$A12,'Daily Issuance'!$E$4:$E$991,"Inventory",'Daily Issuance'!$B$4:$B$991,">="&DATE(2026,7,1),'Daily Issuance'!$B$4:$B$991,"<"&DATE(2026,8,1)),0) -> 0 | M12: =IFERROR(SUMIFS('Daily Issuance'!$O$4:$O$991,'Daily Issuance'!$I$4:$I$991,$A12,'Daily Issuance'!$E$4:$E$991,"Non Inventory",'Daily Issuance'!$B$4:$B$991,">="&DATE(2026,7,1),'Daily Issuance'!$B$4:$B$991,"<"&DATE(2026,8,1)),0) -> 0 | N12: =IFERROR(SUMIFS('Daily Issuance'!$O$4:$O$991,'Daily Issuance'!$I$4:$I$991,$A12,'Daily Issuance'!$E$4:$E$991,"Services",'Daily Issuance'!$B$4:$B$991,">="&DATE(2026,7,1),'Daily Issuance'!$B$4:$B$991,"<"&DATE(2026,8,1)),0) -> 0 | O12: =IFERROR(SUMIFS('Daily Issuance'!$O:$O,'Daily Issuance'!$I:$I,$A12,'Daily Issuance'!$E:$E,"Patty Cash",'Daily Issuance'!$B:$B,">="&DATE(2026,7,1),'Daily Issuance'!$B:$B,"<"&DATE(2026,8,1)),0) -> 0 | P12: =SUM(L12:O12) -> 0 | Q12: =IFERROR(SUMIFS('Daily Issuance'!$O$4:$O$991,'Daily Issuance'!$I$4:$I$991,$A12,'Daily Issuance'!$E$4:$E$991,"Inventory",'Daily Issuance'!$B$4:$B$991,">="&DATE(2026,8,1),'Daily Issuance'!$B$4:$B$991,"<"&DATE(2026,9,1)),0) -> 0 | R12: =IFERROR(SUMIFS('Daily Issuance'!$O$4:$O$991,'Daily Issuance'!$I$4:$I$991,$A12,'Daily Issuance'!$E$4:$E$991,"Non Inventory",'Daily Issuance'!$B$4:$B$991,">="&DATE(2026,8,1),'Daily Issuance'!$B$4:$B$991,"<"&DATE(2026,9,1)),0) -> 0 | S12: =IFERROR(SUMIFS('Daily Issuance'!$O$4:$O$991,'Daily Issuance'!$I$4:$I$991,$A12,'Daily Issuance'!$E$4:$E$991,"Services",'Daily Issuance'!$B$4:$B$991,">="&DATE(2026,8,1),'Daily Issuance'!$B$4:$B$991,"<"&DATE(2026,9,1)),0) -> 0 | T12: =IFERROR(SUMIFS('Daily Issuance'!$O:$O,'Daily Issuance'!$I:$I,$A12,'Daily Issuance'!$E:$E,"Patty Cash",'Daily Issuance'!$B:$B,">="&DATE(2026,8,1),'Daily Issuance'!$B:$B,"<"&DATE(2026,9,1)),0) -> 0 | U12: =SUM(Q12:T12) -> 0 | V12: =IFERROR(SUMIFS('Daily Issuance'!$O$4:$O$991,'Daily Issuance'!$I$4:$I$991,$A12,'Daily Issuance'!$E$4:$E$991,"Inventory",'Daily Issuance'!$B$4:$B$991,">="&DATE(2026,9,1),'Daily Issuance'!$B$4:$B$991,"<"&DATE(2026,10,1)),0) -> 0 | W12: =IFERROR(SUMIFS('Daily Issuance'!$O$4:$O$991,'Daily Issuance'!$I$4:$I$991,$A12,'Daily Issuance'!$E$4:$E$991,"Non Inventory",'Daily Issuance'!$B$4:$B$991,">="&DATE(2026,9,1),'Daily Issuance'!$B$4:$B$991,"<"&DATE(2026,10,1)),0) -> 0 | X12: =IFERROR(SUMIFS('Daily Issuance'!$O$4:$O$991,'Daily Issuance'!$I$4:$I$991,$A12,'Daily Issuance'!$E$4:$E$991,"Services",'Daily Issuance'!$B$4:$B$991,">="&DATE(2026,9,1),'Daily Issuance'!$B$4:$B$991,"<"&DATE(2026,10,1)),0) -> 0 | Y12: =IFERROR(SUMIFS('Daily Issuance'!$O:$O,'Daily Issuance'!$I:$I,$A12,'Daily Issuance'!$E:$E,"Patty Cash",'Daily Issuance'!$B:$B,">="&DATE(2026,9,1),'Daily Issuance'!$B:$B,"<"&DATE(2026,10,1)),0) -> 0 | Z12: =SUM(V12:Y12) -> 0 | AA12: =IFERROR(SUMIFS('Daily Issuance'!$O$4:$O$991,'Daily Issuance'!$I$4:$I$991,$A12,'Daily Issuance'!$E$4:$E$991,"Inventory",'Daily Issuance'!$B$4:$B$991,">="&DATE(2026,10,1),'Daily Issuance'!$B$4:$B$991,"<"&DATE(2026,11,1)),0) -> 0 | AB12: =IFERROR(SUMIFS('Daily Issuance'!$O$4:$O$991,'Daily Issuance'!$I$4:$I$991,$A12,'Daily Issuance'!$E$4:$E$991,"Non Inventory",'Daily Issuance'!$B$4:$B$991,">="&DATE(2026,10,1),'Daily Issuance'!$B$4:$B$991,"<"&DATE(2026,11,1)),0) -> 0 | AC12: =IFERROR(SUMIFS('Daily Issuance'!$O$4:$O$991,'Daily Issuance'!$I$4:$I$991,$A12,'Daily Issuance'!$E$4:$E$991,"Services",'Daily Issuance'!$B$4:$B$991,">="&DATE(2026,10,1),'Daily Issuance'!$B$4:$B$991,"<"&DATE(2026,11,1)),0) -> 0 | AD12: =IFERROR(SUMIFS('Daily Issuance'!$O:$O,'Daily Issuance'!$I:$I,$A12,'Daily Issuance'!$E:$E,"Patty Cash",'Daily Issuance'!$B:$B,">="&DATE(2026,10,1),'Daily Issuance'!$B:$B,"<"&DATE(2026,11,1)),0) -> 0 | AE12: =SUM(AA12:AD12) -> 0 | AF12: =IFERROR(SUMIFS('Daily Issuance'!$O$4:$O$991,'Daily Issuance'!$I$4:$I$991,$A12,'Daily Issuance'!$E$4:$E$991,"Inventory",'Daily Issuance'!$B$4:$B$991,">="&DATE(2026,11,1),'Daily Issuance'!$B$4:$B$991,"<"&DATE(2026,12,1)),0) -> 0 | AG12: =IFERROR(SUMIFS('Daily Issuance'!$O$4:$O$991,'Daily Issuance'!$I$4:$I$991,$A12,'Daily Issuance'!$E$4:$E$991,"Non Inventory",'Daily Issuance'!$B$4:$B$991,">="&DATE(2026,11,1),'Daily Issuance'!$B$4:$B$991,"<"&DATE(2026,12,1)),0) -> 0 | AH12: =IFERROR(SUMIFS('Daily Issuance'!$O$4:$O$991,'Daily Issuance'!$I$4:$I$991,$A12,'Daily Issuance'!$E$4:$E$991,"Services",'Daily Issuance'!$B$4:$B$991,">="&DATE(2026,11,1),'Daily Issuance'!$B$4:$B$991,"<"&DATE(2026,12,1)),0) -> 0 | AI12: =IFERROR(SUMIFS('Daily Issuance'!$O:$O,'Daily Issuance'!$I:$I,$A12,'Daily Issuance'!$E:$E,"Patty Cash",'Daily Issuance'!$B:$B,">="&DATE(2026,11,1),'Daily Issuance'!$B:$B,"<"&DATE(2026,12,1)),0) -> 0 | AJ12: =SUM(AF12:AI12) -> 0 | AK12: =IFERROR(SUMIFS('Daily Issuance'!$O$4:$O$991,'Daily Issuance'!$I$4:$I$991,$A12,'Daily Issuance'!$E$4:$E$991,"Inventory",'Daily Issuance'!$B$4:$B$991,">="&DATE(2026,12,1),'Daily Issuance'!$B$4:$B$991,"<"&DATE(2027,1,1)),0) -> 0 | AL12: =IFERROR(SUMIFS('Daily Issuance'!$O$4:$O$991,'Daily Issuance'!$I$4:$I$991,$A12,'Daily Issuance'!$E$4:$E$991,"Non Inventory",'Daily Issuance'!$B$4:$B$991,">="&DATE(2026,12,1),'Daily Issuance'!$B$4:$B$991,"<"&DATE(2027,1,1)),0) -> 0 | AM12: =IFERROR(SUMIFS('Daily Issuance'!$O$4:$O$991,'Daily Issuance'!$I$4:$I$991,$A12,'Daily Issuance'!$E$4:$E$991,"Services",'Daily Issuance'!$B$4:$B$991,">="&DATE(2026,12,1),'Daily Issuance'!$B$4:$B$991,"<"&DATE(2027,1,1)),0) -> 0 | AN12: =IFERROR(SUMIFS('Daily Issuance'!$O:$O,'Daily Issuance'!$I:$I,$A12,'Daily Issuance'!$E:$E,"Patty Cash",'Daily Issuance'!$B:$B,">="&DATE(2026,12,1),'Daily Issuance'!$B:$B,"<"&DATE(2027,1,1)),0) -> 0 | AO12: =SUM(AK12:AN12) -> 0 | AP12: =SUM(F12,K12,P12,U12,Z12,AE12,AJ12,AO12) -> 4894
A13: Ishida No: 08 | B13: =IFERROR(SUMIFS('Daily Issuance'!$O:$O,'Daily Issuance'!$I:$I,$A13,'Daily Issuance'!$E:$E,"Inventory",'Daily Issuance'!$B:$B,">="&DATE(2026,5,1),'Daily Issuance'!$B:$B,"<"&DATE(2026,6,1)),0) -> 16275 | C13: =IFERROR(SUMIFS('Daily Issuance'!$O:$O,'Daily Issuance'!$I:$I,$A13,'Daily Issuance'!$E:$E,"Non Inventory",'Daily Issuance'!$B:$B,">="&DATE(2026,5,1),'Daily Issuance'!$B:$B,"<"&DATE(2026,6,1)),0) -> 256 | D13: =IFERROR(SUMIFS('Daily Issuance'!$O:$O,'Daily Issuance'!$I:$I,$A13,'Daily Issuance'!$E:$E,"Services",'Daily Issuance'!$B:$B,">="&DATE(2026,5,1),'Daily Issuance'!$B:$B,"<"&DATE(2026,6,1)),0) -> 0 | E13: =IFERROR(SUMIFS('Daily Issuance'!$O:$O,'Daily Issuance'!$I:$I,$A13,'Daily Issuance'!$E:$E,"Patty Cash",'Daily Issuance'!$B:$B,">="&DATE(2026,5,1),'Daily Issuance'!$B:$B,"<"&DATE(2026,6,1)),0) -> 0 | F13: =SUM(B13:E13) -> 16531 | G13: =IFERROR(SUMIFS('Daily Issuance'!$O$4:$O$991,'Daily Issuance'!$I$4:$I$991,$A13,'Daily Issuance'!$E$4:$E$991,"Inventory",'Daily Issuance'!$B$4:$B$991,">="&DATE(2026,6,1),'Daily Issuance'!$B$4:$B$991,"<"&DATE(2026,7,1)),0) -> 10758 | H13: =IFERROR(SUMIFS('Daily Issuance'!$O$4:$O$991,'Daily Issuance'!$I$4:$I$991,$A13,'Daily Issuance'!$E$4:$E$991,"Non Inventory",'Daily Issuance'!$B$4:$B$991,">="&DATE(2026,6,1),'Daily Issuance'!$B$4:$B$991,"<"&DATE(2026,7,1)),0) -> 256 | I13: =IFERROR(SUMIFS('Daily Issuance'!$O$4:$O$991,'Daily Issuance'!$I$4:$I$991,$A13,'Daily Issuance'!$E$4:$E$991,"Services",'Daily Issuance'!$B$4:$B$991,">="&DATE(2026,6,1),'Daily Issuance'!$B$4:$B$991,"<"&DATE(2026,7,1)),0) -> 0 | J13: =IFERROR(SUMIFS('Daily Issuance'!$O:$O,'Daily Issuance'!$I:$I,$A13,'Daily Issuance'!$E:$E,"Patty Cash",'Daily Issuance'!$B:$B,">="&DATE(2026,6,1),'Daily Issuance'!$B:$B,"<"&DATE(2026,7,1)),0) -> 0 | K13: =SUM(G13:J13) -> 11014 | L13: =IFERROR(SUMIFS('Daily Issuance'!$O$4:$O$991,'Daily Issuance'!$I$4:$I$991,$A13,'Daily Issuance'!$E$4:$E$991,"Inventory",'Daily Issuance'!$B$4:$B$991,">="&DATE(2026,7,1),'Daily Issuance'!$B$4:$B$991,"<"&DATE(2026,8,1)),0) -> 0 | M13: =IFERROR(SUMIFS('Daily Issuance'!$O$4:$O$991,'Daily Issuance'!$I$4:$I$991,$A13,'Daily Issuance'!$E$4:$E$991,"Non Inventory",'Daily Issuance'!$B$4:$B$991,">="&DATE(2026,7,1),'Daily Issuance'!$B$4:$B$991,"<"&DATE(2026,8,1)),0) -> 0 | N13: =IFERROR(SUMIFS('Daily Issuance'!$O$4:$O$991,'Daily Issuance'!$I$4:$I$991,$A13,'Daily Issuance'!$E$4:$E$991,"Services",'Daily Issuance'!$B$4:$B$991,">="&DATE(2026,7,1),'Daily Issuance'!$B$4:$B$991,"<"&DATE(2026,8,1)),0) -> 0 | O13: =IFERROR(SUMIFS('Daily Issuance'!$O:$O,'Daily Issuance'!$I:$I,$A13,'Daily Issuance'!$E:$E,"Patty Cash",'Daily Issuance'!$B:$B,">="&DATE(2026,7,1),'Daily Issuance'!$B:$B,"<"&DATE(2026,8,1)),0) -> 0 | P13: =SUM(L13:O13) -> 0 | Q13: =IFERROR(SUMIFS('Daily Issuance'!$O$4:$O$991,'Daily Issuance'!$I$4:$I$991,$A13,'Daily Issuance'!$E$4:$E$991,"Inventory",'Daily Issuance'!$B$4:$B$991,">="&DATE(2026,8,1),'Daily Issuance'!$B$4:$B$991,"<"&DATE(2026,9,1)),0) -> 0 | R13: =IFERROR(SUMIFS('Daily Issuance'!$O$4:$O$991,'Daily Issuance'!$I$4:$I$991,$A13,'Daily Issuance'!$E$4:$E$991,"Non Inventory",'Daily Issuance'!$B$4:$B$991,">="&DATE(2026,8,1),'Daily Issuance'!$B$4:$B$991,"<"&DATE(2026,9,1)),0) -> 0 | S13: =IFERROR(SUMIFS('Daily Issuance'!$O$4:$O$991,'Daily Issuance'!$I$4:$I$991,$A13,'Daily Issuance'!$E$4:$E$991,"Services",'Daily Issuance'!$B$4:$B$991,">="&DATE(2026,8,1),'Daily Issuance'!$B$4:$B$991,"<"&DATE(2026,9,1)),0) -> 0 | T13: =IFERROR(SUMIFS('Daily Issuance'!$O:$O,'Daily Issuance'!$I:$I,$A13,'Daily Issuance'!$E:$E,"Patty Cash",'Daily Issuance'!$B:$B,">="&DATE(2026,8,1),'Daily Issuance'!$B:$B,"<"&DATE(2026,9,1)),0) -> 0 | U13: =SUM(Q13:T13) -> 0 | V13: =IFERROR(SUMIFS('Daily Issuance'!$O$4:$O$991,'Daily Issuance'!$I$4:$I$991,$A13,'Daily Issuance'!$E$4:$E$991,"Inventory",'Daily Issuance'!$B$4:$B$991,">="&DATE(2026,9,1),'Daily Issuance'!$B$4:$B$991,"<"&DATE(2026,10,1)),0) -> 0 | W13: =IFERROR(SUMIFS('Daily Issuance'!$O$4:$O$991,'Daily Issuance'!$I$4:$I$991,$A13,'Daily Issuance'!$E$4:$E$991,"Non Inventory",'Daily Issuance'!$B$4:$B$991,">="&DATE(2026,9,1),'Daily Issuance'!$B$4:$B$991,"<"&DATE(2026,10,1)),0) -> 0 | X13: =IFERROR(SUMIFS('Daily Issuance'!$O$4:$O$991,'Daily Issuance'!$I$4:$I$991,$A13,'Daily Issuance'!$E$4:$E$991,"Services",'Daily Issuance'!$B$4:$B$991,">="&DATE(2026,9,1),'Daily Issuance'!$B$4:$B$991,"<"&DATE(2026,10,1)),0) -> 0 | Y13: =IFERROR(SUMIFS('Daily Issuance'!$O:$O,'Daily Issuance'!$I:$I,$A13,'Daily Issuance'!$E:$E,"Patty Cash",'Daily Issuance'!$B:$B,">="&DATE(2026,9,1),'Daily Issuance'!$B:$B,"<"&DATE(2026,10,1)),0) -> 0 | Z13: =SUM(V13:Y13) -> 0 | AA13: =IFERROR(SUMIFS('Daily Issuance'!$O$4:$O$991,'Daily Issuance'!$I$4:$I$991,$A13,'Daily Issuance'!$E$4:$E$991,"Inventory",'Daily Issuance'!$B$4:$B$991,">="&DATE(2026,10,1),'Daily Issuance'!$B$4:$B$991,"<"&DATE(2026,11,1)),0) -> 0 | AB13: =IFERROR(SUMIFS('Daily Issuance'!$O$4:$O$991,'Daily Issuance'!$I$4:$I$991,$A13,'Daily Issuance'!$E$4:$E$991,"Non Inventory",'Daily Issuance'!$B$4:$B$991,">="&DATE(2026,10,1),'Daily Issuance'!$B$4:$B$991,"<"&DATE(2026,11,1)),0) -> 0 | AC13: =IFERROR(SUMIFS('Daily Issuance'!$O$4:$O$991,'Daily Issuance'!$I$4:$I$991,$A13,'Daily Issuance'!$E$4:$E$991,"Services",'Daily Issuance'!$B$4:$B$991,">="&DATE(2026,10,1),'Daily Issuance'!$B$4:$B$991,"<"&DATE(2026,11,1)),0) -> 0 | AD13: =IFERROR(SUMIFS('Daily Issuance'!$O:$O,'Daily Issuance'!$I:$I,$A13,'Daily Issuance'!$E:$E,"Patty Cash",'Daily Issuance'!$B:$B,">="&DATE(2026,10,1),'Daily Issuance'!$B:$B,"<"&DATE(2026,11,1)),0) -> 0 | AE13: =SUM(AA13:AD13) -> 0 | AF13: =IFERROR(SUMIFS('Daily Issuance'!$O$4:$O$991,'Daily Issuance'!$I$4:$I$991,$A13,'Daily Issuance'!$E$4:$E$991,"Inventory",'Daily Issuance'!$B$4:$B$991,">="&DATE(2026,11,1),'Daily Issuance'!$B$4:$B$991,"<"&DATE(2026,12,1)),0) -> 0 | AG13: =IFERROR(SUMIFS('Daily Issuance'!$O$4:$O$991,'Daily Issuance'!$I$4:$I$991,$A13,'Daily Issuance'!$E$4:$E$991,"Non Inventory",'Daily Issuance'!$B$4:$B$991,">="&DATE(2026,11,1),'Daily Issuance'!$B$4:$B$991,"<"&DATE(2026,12,1)),0) -> 0 | AH13: =IFERROR(SUMIFS('Daily Issuance'!$O$4:$O$991,'Daily Issuance'!$I$4:$I$991,$A13,'Daily Issuance'!$E$4:$E$991,"Services",'Daily Issuance'!$B$4:$B$991,">="&DATE(2026,11,1),'Daily Issuance'!$B$4:$B$991,"<"&DATE(2026,12,1)),0) -> 0 | AI13: =IFERROR(SUMIFS('Daily Issuance'!$O:$O,'Daily Issuance'!$I:$I,$A13,'Daily Issuance'!$E:$E,"Patty Cash",'Daily Issuance'!$B:$B,">="&DATE(2026,11,1),'Daily Issuance'!$B:$B,"<"&DATE(2026,12,1)),0) -> 0 | AJ13: =SUM(AF13:AI13) -> 0 | AK13: =IFERROR(SUMIFS('Daily Issuance'!$O$4:$O$991,'Daily Issuance'!$I$4:$I$991,$A13,'Daily Issuance'!$E$4:$E$991,"Inventory",'Daily Issuance'!$B$4:$B$991,">="&DATE(2026,12,1),'Daily Issuance'!$B$4:$B$991,"<"&DATE(2027,1,1)),0) -> 0 | AL13: =IFERROR(SUMIFS('Daily Issuance'!$O$4:$O$991,'Daily Issuance'!$I$4:$I$991,$A13,'Daily Issuance'!$E$4:$E$991,"Non Inventory",'Daily Issuance'!$B$4:$B$991,">="&DATE(2026,12,1),'Daily Issuance'!$B$4:$B$991,"<"&DATE(2027,1,1)),0) -> 0 | AM13: =IFERROR(SUMIFS('Daily Issuance'!$O$4:$O$991,'Daily Issuance'!$I$4:$I$991,$A13,'Daily Issuance'!$E$4:$E$991,"Services",'Daily Issuance'!$B$4:$B$991,">="&DATE(2026,12,1),'Daily Issuance'!$B$4:$B$991,"<"&DATE(2027,1,1)),0) -> 0 | AN13: =IFERROR(SUMIFS('Daily Issuance'!$O:$O,'Daily Issuance'!$I:$I,$A13,'Daily Issuance'!$E:$E,"Patty Cash",'Daily Issuance'!$B:$B,">="&DATE(2026,12,1),'Daily Issuance'!$B:$B,"<"&DATE(2027,1,1)),0) -> 0 | AO13: =SUM(AK13:AN13) -> 0 | AP13: =SUM(F13,K13,P13,U13,Z13,AE13,AJ13,AO13) -> 27545
A14: Ishida No: 09 | B14: =IFERROR(SUMIFS('Daily Issuance'!$O:$O,'Daily Issuance'!$I:$I,$A14,'Daily Issuance'!$E:$E,"Inventory",'Daily Issuance'!$B:$B,">="&DATE(2026,5,1),'Daily Issuance'!$B:$B,"<"&DATE(2026,6,1)),0) -> 23500 | C14: =IFERROR(SUMIFS('Daily Issuance'!$O:$O,'Daily Issuance'!$I:$I,$A14,'Daily Issuance'!$E:$E,"Non Inventory",'Daily Issuance'!$B:$B,">="&DATE(2026,5,1),'Daily Issuance'!$B:$B,"<"&DATE(2026,6,1)),0) -> 1200 | D14: =IFERROR(SUMIFS('Daily Issuance'!$O:$O,'Daily Issuance'!$I:$I,$A14,'Daily Issuance'!$E:$E,"Services",'Daily Issuance'!$B:$B,">="&DATE(2026,5,1),'Daily Issuance'!$B:$B,"<"&DATE(2026,6,1)),0) -> 0 | E14: =IFERROR(SUMIFS('Daily Issuance'!$O:$O,'Daily Issuance'!$I:$I,$A14,'Daily Issuance'!$E:$E,"Patty Cash",'Daily Issuance'!$B:$B,">="&DATE(2026,5,1),'Daily Issuance'!$B:$B,"<"&DATE(2026,6,1)),0) -> 0 | F14: =SUM(B14:E14) -> 24700 | G14: =IFERROR(SUMIFS('Daily Issuance'!$O$4:$O$991,'Daily Issuance'!$I$4:$I$991,$A14,'Daily Issuance'!$E$4:$E$991,"Inventory",'Daily Issuance'!$B$4:$B$991,">="&DATE(2026,6,1),'Daily Issuance'!$B$4:$B$991,"<"&DATE(2026,7,1)),0) -> 9000 | H14: =IFERROR(SUMIFS('Daily Issuance'!$O$4:$O$991,'Daily Issuance'!$I$4:$I$991,$A14,'Daily Issuance'!$E$4:$E$991,"Non Inventory",'Daily Issuance'!$B$4:$B$991,">="&DATE(2026,6,1),'Daily Issuance'!$B$4:$B$991,"<"&DATE(2026,7,1)),0) -> 1024 | I14: =IFERROR(SUMIFS('Daily Issuance'!$O$4:$O$991,'Daily Issuance'!$I$4:$I$991,$A14,'Daily Issuance'!$E$4:$E$991,"Services",'Daily Issuance'!$B$4:$B$991,">="&DATE(2026,6,1),'Daily Issuance'!$B$4:$B$991,"<"&DATE(2026,7,1)),0) -> 0 | J14: =IFERROR(SUMIFS('Daily Issuance'!$O:$O,'Daily Issuance'!$I:$I,$A14,'Daily Issuance'!$E:$E,"Patty Cash",'Daily Issuance'!$B:$B,">="&DATE(2026,6,1),'Daily Issuance'!$B:$B,"<"&DATE(2026,7,1)),0) -> 0 | K14: =SUM(G14:J14) -> 10024 | L14: =IFERROR(SUMIFS('Daily Issuance'!$O$4:$O$991,'Daily Issuance'!$I$4:$I$991,$A14,'Daily Issuance'!$E$4:$E$991,"Inventory",'Daily Issuance'!$B$4:$B$991,">="&DATE(2026,7,1),'Daily Issuance'!$B$4:$B$991,"<"&DATE(2026,8,1)),0) -> 0 | M14: =IFERROR(SUMIFS('Daily Issuance'!$O$4:$O$991,'Daily Issuance'!$I$4:$I$991,$A14,'Daily Issuance'!$E$4:$E$991,"Non Inventory",'Daily Issuance'!$B$4:$B$991,">="&DATE(2026,7,1),'Daily Issuance'!$B$4:$B$991,"<"&DATE(2026,8,1)),0) -> 0 | N14: =IFERROR(SUMIFS('Daily Issuance'!$O$4:$O$991,'Daily Issuance'!$I$4:$I$991,$A14,'Daily Issuance'!$E$4:$E$991,"Services",'Daily Issuance'!$B$4:$B$991,">="&DATE(2026,7,1),'Daily Issuance'!$B$4:$B$991,"<"&DATE(2026,8,1)),0) -> 0 | O14: =IFERROR(SUMIFS('Daily Issuance'!$O:$O,'Daily Issuance'!$I:$I,$A14,'Daily Issuance'!$E:$E,"Patty Cash",'Daily Issuance'!$B:$B,">="&DATE(2026,7,1),'Daily Issuance'!$B:$B,"<"&DATE(2026,8,1)),0) -> 0 | P14: =SUM(L14:O14) -> 0 | Q14: =IFERROR(SUMIFS('Daily Issuance'!$O$4:$O$991,'Daily Issuance'!$I$4:$I$991,$A14,'Daily Issuance'!$E$4:$E$991,"Inventory",'Daily Issuance'!$B$4:$B$991,">="&DATE(2026,8,1),'Daily Issuance'!$B$4:$B$991,"<"&DATE(2026,9,1)),0) -> 0 | R14: =IFERROR(SUMIFS('Daily Issuance'!$O$4:$O$991,'Daily Issuance'!$I$4:$I$991,$A14,'Daily Issuance'!$E$4:$E$991,"Non Inventory",'Daily Issuance'!$B$4:$B$991,">="&DATE(2026,8,1),'Daily Issuance'!$B$4:$B$991,"<"&DATE(2026,9,1)),0) -> 0 | S14: =IFERROR(SUMIFS('Daily Issuance'!$O$4:$O$991,'Daily Issuance'!$I$4:$I$991,$A14,'Daily Issuance'!$E$4:$E$991,"Services",'Daily Issuance'!$B$4:$B$991,">="&DATE(2026,8,1),'Daily Issuance'!$B$4:$B$991,"<"&DATE(2026,9,1)),0) -> 0 | T14: =IFERROR(SUMIFS('Daily Issuance'!$O:$O,'Daily Issuance'!$I:$I,$A14,'Daily Issuance'!$E:$E,"Patty Cash",'Daily Issuance'!$B:$B,">="&DATE(2026,8,1),'Daily Issuance'!$B:$B,"<"&DATE(2026,9,1)),0) -> 0 | U14: =SUM(Q14:T14) -> 0 | V14: =IFERROR(SUMIFS('Daily Issuance'!$O$4:$O$991,'Daily Issuance'!$I$4:$I$991,$A14,'Daily Issuance'!$E$4:$E$991,"Inventory",'Daily Issuance'!$B$4:$B$991,">="&DATE(2026,9,1),'Daily Issuance'!$B$4:$B$991,"<"&DATE(2026,10,1)),0) -> 0 | W14: =IFERROR(SUMIFS('Daily Issuance'!$O$4:$O$991,'Daily Issuance'!$I$4:$I$991,$A14,'Daily Issuance'!$E$4:$E$991,"Non Inventory",'Daily Issuance'!$B$4:$B$991,">="&DATE(2026,9,1),'Daily Issuance'!$B$4:$B$991,"<"&DATE(2026,10,1)),0) -> 0 | X14: =IFERROR(SUMIFS('Daily Issuance'!$O$4:$O$991,'Daily Issuance'!$I$4:$I$991,$A14,'Daily Issuance'!$E$4:$E$991,"Services",'Daily Issuance'!$B$4:$B$991,">="&DATE(2026,9,1),'Daily Issuance'!$B$4:$B$991,"<"&DATE(2026,10,1)),0) -> 0 | Y14: =IFERROR(SUMIFS('Daily Issuance'!$O:$O,'Daily Issuance'!$I:$I,$A14,'Daily Issuance'!$E:$E,"Patty Cash",'Daily Issuance'!$B:$B,">="&DATE(2026,9,1),'Daily Issuance'!$B:$B,"<"&DATE(2026,10,1)),0) -> 0 | Z14: =SUM(V14:Y14) -> 0 | AA14: =IFERROR(SUMIFS('Daily Issuance'!$O$4:$O$991,'Daily Issuance'!$I$4:$I$991,$A14,'Daily Issuance'!$E$4:$E$991,"Inventory",'Daily Issuance'!$B$4:$B$991,">="&DATE(2026,10,1),'Daily Issuance'!$B$4:$B$991,"<"&DATE(2026,11,1)),0) -> 0 | AB14: =IFERROR(SUMIFS('Daily Issuance'!$O$4:$O$991,'Daily Issuance'!$I$4:$I$991,$A14,'Daily Issuance'!$E$4:$E$991,"Non Inventory",'Daily Issuance'!$B$4:$B$991,">="&DATE(2026,10,1),'Daily Issuance'!$B$4:$B$991,"<"&DATE(2026,11,1)),0) -> 0 | AC14: =IFERROR(SUMIFS('Daily Issuance'!$O$4:$O$991,'Daily Issuance'!$I$4:$I$991,$A14,'Daily Issuance'!$E$4:$E$991,"Services",'Daily Issuance'!$B$4:$B$991,">="&DATE(2026,10,1),'Daily Issuance'!$B$4:$B$991,"<"&DATE(2026,11,1)),0) -> 0 | AD14: =IFERROR(SUMIFS('Daily Issuance'!$O:$O,'Daily Issuance'!$I:$I,$A14,'Daily Issuance'!$E:$E,"Patty Cash",'Daily Issuance'!$B:$B,">="&DATE(2026,10,1),'Daily Issuance'!$B:$B,"<"&DATE(2026,11,1)),0) -> 0 | AE14: =SUM(AA14:AD14) -> 0 | AF14: =IFERROR(SUMIFS('Daily Issuance'!$O$4:$O$991,'Daily Issuance'!$I$4:$I$991,$A14,'Daily Issuance'!$E$4:$E$991,"Inventory",'Daily Issuance'!$B$4:$B$991,">="&DATE(2026,11,1),'Daily Issuance'!$B$4:$B$991,"<"&DATE(2026,12,1)),0) -> 0 | AG14: =IFERROR(SUMIFS('Daily Issuance'!$O$4:$O$991,'Daily Issuance'!$I$4:$I$991,$A14,'Daily Issuance'!$E$4:$E$991,"Non Inventory",'Daily Issuance'!$B$4:$B$991,">="&DATE(2026,11,1),'Daily Issuance'!$B$4:$B$991,"<"&DATE(2026,12,1)),0) -> 0 | AH14: =IFERROR(SUMIFS('Daily Issuance'!$O$4:$O$991,'Daily Issuance'!$I$4:$I$991,$A14,'Daily Issuance'!$E$4:$E$991,"Services",'Daily Issuance'!$B$4:$B$991,">="&DATE(2026,11,1),'Daily Issuance'!$B$4:$B$991,"<"&DATE(2026,12,1)),0) -> 0 | AI14: =IFERROR(SUMIFS('Daily Issuance'!$O:$O,'Daily Issuance'!$I:$I,$A14,'Daily Issuance'!$E:$E,"Patty Cash",'Daily Issuance'!$B:$B,">="&DATE(2026,11,1),'Daily Issuance'!$B:$B,"<"&DATE(2026,12,1)),0) -> 0 | AJ14: =SUM(AF14:AI14) -> 0 | AK14: =IFERROR(SUMIFS('Daily Issuance'!$O$4:$O$991,'Daily Issuance'!$I$4:$I$991,$A14,'Daily Issuance'!$E$4:$E$991,"Inventory",'Daily Issuance'!$B$4:$B$991,">="&DATE(2026,12,1),'Daily Issuance'!$B$4:$B$991,"<"&DATE(2027,1,1)),0) -> 0 | AL14: =IFERROR(SUMIFS('Daily Issuance'!$O$4:$O$991,'Daily Issuance'!$I$4:$I$991,$A14,'Daily Issuance'!$E$4:$E$991,"Non Inventory",'Daily Issuance'!$B$4:$B$991,">="&DATE(2026,12,1),'Daily Issuance'!$B$4:$B$991,"<"&DATE(2027,1,1)),0) -> 0 | AM14: =IFERROR(SUMIFS('Daily Issuance'!$O$4:$O$991,'Daily Issuance'!$I$4:$I$991,$A14,'Daily Issuance'!$E$4:$E$991,"Services",'Daily Issuance'!$B$4:$B$991,">="&DATE(2026,12,1),'Daily Issuance'!$B$4:$B$991,"<"&DATE(2027,1,1)),0) -> 0 | AN14: =IFERROR(SUMIFS('Daily Issuance'!$O:$O,'Daily Issuance'!$I:$I,$A14,'Daily Issuance'!$E:$E,"Patty Cash",'Daily Issuance'!$B:$B,">="&DATE(2026,12,1),'Daily Issuance'!$B:$B,"<"&DATE(2027,1,1)),0) -> 0 | AO14: =SUM(AK14:AN14) -> 0 | AP14: =SUM(F14,K14,P14,U14,Z14,AE14,AJ14,AO14) -> 34724
A15: Ishida No: 10 | B15: =IFERROR(SUMIFS('Daily Issuance'!$O:$O,'Daily Issuance'!$I:$I,$A15,'Daily Issuance'!$E:$E,"Inventory",'Daily Issuance'!$B:$B,">="&DATE(2026,5,1),'Daily Issuance'!$B:$B,"<"&DATE(2026,6,1)),0) -> 1500 | C15: =IFERROR(SUMIFS('Daily Issuance'!$O:$O,'Daily Issuance'!$I:$I,$A15,'Daily Issuance'!$E:$E,"Non Inventory",'Daily Issuance'!$B:$B,">="&DATE(2026,5,1),'Daily Issuance'!$B:$B,"<"&DATE(2026,6,1)),0) -> 2000 | D15: =IFERROR(SUMIFS('Daily Issuance'!$O:$O,'Daily Issuance'!$I:$I,$A15,'Daily Issuance'!$E:$E,"Services",'Daily Issuance'!$B:$B,">="&DATE(2026,5,1),'Daily Issuance'!$B:$B,"<"&DATE(2026,6,1)),0) -> 0 | E15: =IFERROR(SUMIFS('Daily Issuance'!$O:$O,'Daily Issuance'!$I:$I,$A15,'Daily Issuance'!$E:$E,"Patty Cash",'Daily Issuance'!$B:$B,">="&DATE(2026,5,1),'Daily Issuance'!$B:$B,"<"&DATE(2026,6,1)),0) -> 0 | F15: =SUM(B15:E15) -> 3500 | G15: =IFERROR(SUMIFS('Daily Issuance'!$O$4:$O$991,'Daily Issuance'!$I$4:$I$991,$A15,'Daily Issuance'!$E$4:$E$991,"Inventory",'Daily Issuance'!$B$4:$B$991,">="&DATE(2026,6,1),'Daily Issuance'!$B$4:$B$991,"<"&DATE(2026,7,1)),0) -> 0 | H15: =IFERROR(SUMIFS('Daily Issuance'!$O$4:$O$991,'Daily Issuance'!$I$4:$I$991,$A15,'Daily Issuance'!$E$4:$E$991,"Non Inventory",'Daily Issuance'!$B$4:$B$991,">="&DATE(2026,6,1),'Daily Issuance'!$B$4:$B$991,"<"&DATE(2026,7,1)),0) -> 0 | I15: =IFERROR(SUMIFS('Daily Issuance'!$O$4:$O$991,'Daily Issuance'!$I$4:$I$991,$A15,'Daily Issuance'!$E$4:$E$991,"Services",'Daily Issuance'!$B$4:$B$991,">="&DATE(2026,6,1),'Daily Issuance'!$B$4:$B$991,"<"&DATE(2026,7,1)),0) -> 0 | J15: =IFERROR(SUMIFS('Daily Issuance'!$O:$O,'Daily Issuance'!$I:$I,$A15,'Daily Issuance'!$E:$E,"Patty Cash",'Daily Issuance'!$B:$B,">="&DATE(2026,6,1),'Daily Issuance'!$B:$B,"<"&DATE(2026,7,1)),0) -> 0 | K15: =SUM(G15:J15) -> 0 | L15: =IFERROR(SUMIFS('Daily Issuance'!$O$4:$O$991,'Daily Issuance'!$I$4:$I$991,$A15,'Daily Issuance'!$E$4:$E$991,"Inventory",'Daily Issuance'!$B$4:$B$991,">="&DATE(2026,7,1),'Daily Issuance'!$B$4:$B$991,"<"&DATE(2026,8,1)),0) -> 0 | M15: =IFERROR(SUMIFS('Daily Issuance'!$O$4:$O$991,'Daily Issuance'!$I$4:$I$991,$A15,'Daily Issuance'!$E$4:$E$991,"Non Inventory",'Daily Issuance'!$B$4:$B$991,">="&DATE(2026,7,1),'Daily Issuance'!$B$4:$B$991,"<"&DATE(2026,8,1)),0) -> 0 | N15: =IFERROR(SUMIFS('Daily Issuance'!$O$4:$O$991,'Daily Issuance'!$I$4:$I$991,$A15,'Daily Issuance'!$E$4:$E$991,"Services",'Daily Issuance'!$B$4:$B$991,">="&DATE(2026,7,1),'Daily Issuance'!$B$4:$B$991,"<"&DATE(2026,8,1)),0) -> 0 | O15: =IFERROR(SUMIFS('Daily Issuance'!$O:$O,'Daily Issuance'!$I:$I,$A15,'Daily Issuance'!$E:$E,"Patty Cash",'Daily Issuance'!$B:$B,">="&DATE(2026,7,1),'Daily Issuance'!$B:$B,"<"&DATE(2026,8,1)),0) -> 0 | P15: =SUM(L15:O15) -> 0 | Q15: =IFERROR(SUMIFS('Daily Issuance'!$O$4:$O$991,'Daily Issuance'!$I$4:$I$991,$A15,'Daily Issuance'!$E$4:$E$991,"Inventory",'Daily Issuance'!$B$4:$B$991,">="&DATE(2026,8,1),'Daily Issuance'!$B$4:$B$991,"<"&DATE(2026,9,1)),0) -> 0 | R15: =IFERROR(SUMIFS('Daily Issuance'!$O$4:$O$991,'Daily Issuance'!$I$4:$I$991,$A15,'Daily Issuance'!$E$4:$E$991,"Non Inventory",'Daily Issuance'!$B$4:$B$991,">="&DATE(2026,8,1),'Daily Issuance'!$B$4:$B$991,"<"&DATE(2026,9,1)),0) -> 0 | S15: =IFERROR(SUMIFS('Daily Issuance'!$O$4:$O$991,'Daily Issuance'!$I$4:$I$991,$A15,'Daily Issuance'!$E$4:$E$991,"Services",'Daily Issuance'!$B$4:$B$991,">="&DATE(2026,8,1),'Daily Issuance'!$B$4:$B$991,"<"&DATE(2026,9,1)),0) -> 0 | T15: =IFERROR(SUMIFS('Daily Issuance'!$O:$O,'Daily Issuance'!$I:$I,$A15,'Daily Issuance'!$E:$E,"Patty Cash",'Daily Issuance'!$B:$B,">="&DATE(2026,8,1),'Daily Issuance'!$B:$B,"<"&DATE(2026,9,1)),0) -> 0 | U15: =SUM(Q15:T15) -> 0 | V15: =IFERROR(SUMIFS('Daily Issuance'!$O$4:$O$991,'Daily Issuance'!$I$4:$I$991,$A15,'Daily Issuance'!$E$4:$E$991,"Inventory",'Daily Issuance'!$B$4:$B$991,">="&DATE(2026,9,1),'Daily Issuance'!$B$4:$B$991,"<"&DATE(2026,10,1)),0) -> 0 | W15: =IFERROR(SUMIFS('Daily Issuance'!$O$4:$O$991,'Daily Issuance'!$I$4:$I$991,$A15,'Daily Issuance'!$E$4:$E$991,"Non Inventory",'Daily Issuance'!$B$4:$B$991,">="&DATE(2026,9,1),'Daily Issuance'!$B$4:$B$991,"<"&DATE(2026,10,1)),0) -> 0 | X15: =IFERROR(SUMIFS('Daily Issuance'!$O$4:$O$991,'Daily Issuance'!$I$4:$I$991,$A15,'Daily Issuance'!$E$4:$E$991,"Services",'Daily Issuance'!$B$4:$B$991,">="&DATE(2026,9,1),'Daily Issuance'!$B$4:$B$991,"<"&DATE(2026,10,1)),0) -> 0 | Y15: =IFERROR(SUMIFS('Daily Issuance'!$O:$O,'Daily Issuance'!$I:$I,$A15,'Daily Issuance'!$E:$E,"Patty Cash",'Daily Issuance'!$B:$B,">="&DATE(2026,9,1),'Daily Issuance'!$B:$B,"<"&DATE(2026,10,1)),0) -> 0 | Z15: =SUM(V15:Y15) -> 0 | AA15: =IFERROR(SUMIFS('Daily Issuance'!$O$4:$O$991,'Daily Issuance'!$I$4:$I$991,$A15,'Daily Issuance'!$E$4:$E$991,"Inventory",'Daily Issuance'!$B$4:$B$991,">="&DATE(2026,10,1),'Daily Issuance'!$B$4:$B$991,"<"&DATE(2026,11,1)),0) -> 0 | AB15: =IFERROR(SUMIFS('Daily Issuance'!$O$4:$O$991,'Daily Issuance'!$I$4:$I$991,$A15,'Daily Issuance'!$E$4:$E$991,"Non Inventory",'Daily Issuance'!$B$4:$B$991,">="&DATE(2026,10,1),'Daily Issuance'!$B$4:$B$991,"<"&DATE(2026,11,1)),0) -> 0 | AC15: =IFERROR(SUMIFS('Daily Issuance'!$O$4:$O$991,'Daily Issuance'!$I$4:$I$991,$A15,'Daily Issuance'!$E$4:$E$991,"Services",'Daily Issuance'!$B$4:$B$991,">="&DATE(2026,10,1),'Daily Issuance'!$B$4:$B$991,"<"&DATE(2026,11,1)),0) -> 0 | AD15: =IFERROR(SUMIFS('Daily Issuance'!$O:$O,'Daily Issuance'!$I:$I,$A15,'Daily Issuance'!$E:$E,"Patty Cash",'Daily Issuance'!$B:$B,">="&DATE(2026,10,1),'Daily Issuance'!$B:$B,"<"&DATE(2026,11,1)),0) -> 0 | AE15: =SUM(AA15:AD15) -> 0 | AF15: =IFERROR(SUMIFS('Daily Issuance'!$O$4:$O$991,'Daily Issuance'!$I$4:$I$991,$A15,'Daily Issuance'!$E$4:$E$991,"Inventory",'Daily Issuance'!$B$4:$B$991,">="&DATE(2026,11,1),'Daily Issuance'!$B$4:$B$991,"<"&DATE(2026,12,1)),0) -> 0 | AG15: =IFERROR(SUMIFS('Daily Issuance'!$O$4:$O$991,'Daily Issuance'!$I$4:$I$991,$A15,'Daily Issuance'!$E$4:$E$991,"Non Inventory",'Daily Issuance'!$B$4:$B$991,">="&DATE(2026,11,1),'Daily Issuance'!$B$4:$B$991,"<"&DATE(2026,12,1)),0) -> 0 | AH15: =IFERROR(SUMIFS('Daily Issuance'!$O$4:$O$991,'Daily Issuance'!$I$4:$I$991,$A15,'Daily Issuance'!$E$4:$E$991,"Services",'Daily Issuance'!$B$4:$B$991,">="&DATE(2026,11,1),'Daily Issuance'!$B$4:$B$991,"<"&DATE(2026,12,1)),0) -> 0 | AI15: =IFERROR(SUMIFS('Daily Issuance'!$O:$O,'Daily Issuance'!$I:$I,$A15,'Daily Issuance'!$E:$E,"Patty Cash",'Daily Issuance'!$B:$B,">="&DATE(2026,11,1),'Daily Issuance'!$B:$B,"<"&DATE(2026,12,1)),0) -> 0 | AJ15: =SUM(AF15:AI15) -> 0 | AK15: =IFERROR(SUMIFS('Daily Issuance'!$O$4:$O$991,'Daily Issuance'!$I$4:$I$991,$A15,'Daily Issuance'!$E$4:$E$991,"Inventory",'Daily Issuance'!$B$4:$B$991,">="&DATE(2026,12,1),'Daily Issuance'!$B$4:$B$991,"<"&DATE(2027,1,1)),0) -> 0 | AL15: =IFERROR(SUMIFS('Daily Issuance'!$O$4:$O$991,'Daily Issuance'!$I$4:$I$991,$A15,'Daily Issuance'!$E$4:$E$991,"Non Inventory",'Daily Issuance'!$B$4:$B$991,">="&DATE(2026,12,1),'Daily Issuance'!$B$4:$B$991,"<"&DATE(2027,1,1)),0) -> 0 | AM15: =IFERROR(SUMIFS('Daily Issuance'!$O$4:$O$991,'Daily Issuance'!$I$4:$I$991,$A15,'Daily Issuance'!$E$4:$E$991,"Services",'Daily Issuance'!$B$4:$B$991,">="&DATE(2026,12,1),'Daily Issuance'!$B$4:$B$991,"<"&DATE(2027,1,1)),0) -> 0 | AN15: =IFERROR(SUMIFS('Daily Issuance'!$O:$O,'Daily Issuance'!$I:$I,$A15,'Daily Issuance'!$E:$E,"Patty Cash",'Daily Issuance'!$B:$B,">="&DATE(2026,12,1),'Daily Issuance'!$B:$B,"<"&DATE(2027,1,1)),0) -> 0 | AO15: =SUM(AK15:AN15) -> 0 | AP15: =SUM(F15,K15,P15,U15,Z15,AE15,AJ15,AO15) -> 3500
A16: Ishida No: 11 | B16: =IFERROR(SUMIFS('Daily Issuance'!$O:$O,'Daily Issuance'!$I:$I,$A16,'Daily Issuance'!$E:$E,"Inventory",'Daily Issuance'!$B:$B,">="&DATE(2026,5,1),'Daily Issuance'!$B:$B,"<"&DATE(2026,6,1)),0) -> 625 | C16: =IFERROR(SUMIFS('Daily Issuance'!$O:$O,'Daily Issuance'!$I:$I,$A16,'Daily Issuance'!$E:$E,"Non Inventory",'Daily Issuance'!$B:$B,">="&DATE(2026,5,1),'Daily Issuance'!$B:$B,"<"&DATE(2026,6,1)),0) -> 0 | D16: =IFERROR(SUMIFS('Daily Issuance'!$O:$O,'Daily Issuance'!$I:$I,$A16,'Daily Issuance'!$E:$E,"Services",'Daily Issuance'!$B:$B,">="&DATE(2026,5,1),'Daily Issuance'!$B:$B,"<"&DATE(2026,6,1)),0) -> 0 | E16: =IFERROR(SUMIFS('Daily Issuance'!$O:$O,'Daily Issuance'!$I:$I,$A16,'Daily Issuance'!$E:$E,"Patty Cash",'Daily Issuance'!$B:$B,">="&DATE(2026,5,1),'Daily Issuance'!$B:$B,"<"&DATE(2026,6,1)),0) -> 0 | F16: =SUM(B16:E16) -> 625 | G16: =IFERROR(SUMIFS('Daily Issuance'!$O$4:$O$991,'Daily Issuance'!$I$4:$I$991,$A16,'Daily Issuance'!$E$4:$E$991,"Inventory",'Daily Issuance'!$B$4:$B$991,">="&DATE(2026,6,1),'Daily Issuance'!$B$4:$B$991,"<"&DATE(2026,7,1)),0) -> 5500 | H16: =IFERROR(SUMIFS('Daily Issuance'!$O$4:$O$991,'Daily Issuance'!$I$4:$I$991,$A16,'Daily Issuance'!$E$4:$E$991,"Non Inventory",'Daily Issuance'!$B$4:$B$991,">="&DATE(2026,6,1),'Daily Issuance'!$B$4:$B$991,"<"&DATE(2026,7,1)),0) -> 0 | I16: =IFERROR(SUMIFS('Daily Issuance'!$O$4:$O$991,'Daily Issuance'!$I$4:$I$991,$A16,'Daily Issuance'!$E$4:$E$991,"Services",'Daily Issuance'!$B$4:$B$991,">="&DATE(2026,6,1),'Daily Issuance'!$B$4:$B$991,"<"&DATE(2026,7,1)),0) -> 0 | J16: =IFERROR(SUMIFS('Daily Issuance'!$O:$O,'Daily Issuance'!$I:$I,$A16,'Daily Issuance'!$E:$E,"Patty Cash",'Daily Issuance'!$B:$B,">="&DATE(2026,6,1),'Daily Issuance'!$B:$B,"<"&DATE(2026,7,1)),0) -> 0 | K16: =SUM(G16:J16) -> 5500 | L16: =IFERROR(SUMIFS('Daily Issuance'!$O$4:$O$991,'Daily Issuance'!$I$4:$I$991,$A16,'Daily Issuance'!$E$4:$E$991,"Inventory",'Daily Issuance'!$B$4:$B$991,">="&DATE(2026,7,1),'Daily Issuance'!$B$4:$B$991,"<"&DATE(2026,8,1)),0) -> 0 | M16: =IFERROR(SUMIFS('Daily Issuance'!$O$4:$O$991,'Daily Issuance'!$I$4:$I$991,$A16,'Daily Issuance'!$E$4:$E$991,"Non Inventory",'Daily Issuance'!$B$4:$B$991,">="&DATE(2026,7,1),'Daily Issuance'!$B$4:$B$991,"<"&DATE(2026,8,1)),0) -> 0 | N16: =IFERROR(SUMIFS('Daily Issuance'!$O$4:$O$991,'Daily Issuance'!$I$4:$I$991,$A16,'Daily Issuance'!$E$4:$E$991,"Services",'Daily Issuance'!$B$4:$B$991,">="&DATE(2026,7,1),'Daily Issuance'!$B$4:$B$991,"<"&DATE(2026,8,1)),0) -> 0 | O16: =IFERROR(SUMIFS('Daily Issuance'!$O:$O,'Daily Issuance'!$I:$I,$A16,'Daily Issuance'!$E:$E,"Patty Cash",'Daily Issuance'!$B:$B,">="&DATE(2026,7,1),'Daily Issuance'!$B:$B,"<"&DATE(2026,8,1)),0) -> 0 | P16: =SUM(L16:O16) -> 0 | Q16: =IFERROR(SUMIFS('Daily Issuance'!$O$4:$O$991,'Daily Issuance'!$I$4:$I$991,$A16,'Daily Issuance'!$E$4:$E$991,"Inventory",'Daily Issuance'!$B$4:$B$991,">="&DATE(2026,8,1),'Daily Issuance'!$B$4:$B$991,"<"&DATE(2026,9,1)),0) -> 0 | R16: =IFERROR(SUMIFS('Daily Issuance'!$O$4:$O$991,'Daily Issuance'!$I$4:$I$991,$A16,'Daily Issuance'!$E$4:$E$991,"Non Inventory",'Daily Issuance'!$B$4:$B$991,">="&DATE(2026,8,1),'Daily Issuance'!$B$4:$B$991,"<"&DATE(2026,9,1)),0) -> 0 | S16: =IFERROR(SUMIFS('Daily Issuance'!$O$4:$O$991,'Daily Issuance'!$I$4:$I$991,$A16,'Daily Issuance'!$E$4:$E$991,"Services",'Daily Issuance'!$B$4:$B$991,">="&DATE(2026,8,1),'Daily Issuance'!$B$4:$B$991,"<"&DATE(2026,9,1)),0) -> 0 | T16: =IFERROR(SUMIFS('Daily Issuance'!$O:$O,'Daily Issuance'!$I:$I,$A16,'Daily Issuance'!$E:$E,"Patty Cash",'Daily Issuance'!$B:$B,">="&DATE(2026,8,1),'Daily Issuance'!$B:$B,"<"&DATE(2026,9,1)),0) -> 0 | U16: =SUM(Q16:T16) -> 0 | V16: =IFERROR(SUMIFS('Daily Issuance'!$O$4:$O$991,'Daily Issuance'!$I$4:$I$991,$A16,'Daily Issuance'!$E$4:$E$991,"Inventory",'Daily Issuance'!$B$4:$B$991,">="&DATE(2026,9,1),'Daily Issuance'!$B$4:$B$991,"<"&DATE(2026,10,1)),0) -> 0 | W16: =IFERROR(SUMIFS('Daily Issuance'!$O$4:$O$991,'Daily Issuance'!$I$4:$I$991,$A16,'Daily Issuance'!$E$4:$E$991,"Non Inventory",'Daily Issuance'!$B$4:$B$991,">="&DATE(2026,9,1),'Daily Issuance'!$B$4:$B$991,"<"&DATE(2026,10,1)),0) -> 0 | X16: =IFERROR(SUMIFS('Daily Issuance'!$O$4:$O$991,'Daily Issuance'!$I$4:$I$991,$A16,'Daily Issuance'!$E$4:$E$991,"Services",'Daily Issuance'!$B$4:$B$991,">="&DATE(2026,9,1),'Daily Issuance'!$B$4:$B$991,"<"&DATE(2026,10,1)),0) -> 0 | Y16: =IFERROR(SUMIFS('Daily Issuance'!$O:$O,'Daily Issuance'!$I:$I,$A16,'Daily Issuance'!$E:$E,"Patty Cash",'Daily Issuance'!$B:$B,">="&DATE(2026,9,1),'Daily Issuance'!$B:$B,"<"&DATE(2026,10,1)),0) -> 0 | Z16: =SUM(V16:Y16) -> 0 | AA16: =IFERROR(SUMIFS('Daily Issuance'!$O$4:$O$991,'Daily Issuance'!$I$4:$I$991,$A16,'Daily Issuance'!$E$4:$E$991,"Inventory",'Daily Issuance'!$B$4:$B$991,">="&DATE(2026,10,1),'Daily Issuance'!$B$4:$B$991,"<"&DATE(2026,11,1)),0) -> 0 | AB16: =IFERROR(SUMIFS('Daily Issuance'!$O$4:$O$991,'Daily Issuance'!$I$4:$I$991,$A16,'Daily Issuance'!$E$4:$E$991,"Non Inventory",'Daily Issuance'!$B$4:$B$991,">="&DATE(2026,10,1),'Daily Issuance'!$B$4:$B$991,"<"&DATE(2026,11,1)),0) -> 0 | AC16: =IFERROR(SUMIFS('Daily Issuance'!$O$4:$O$991,'Daily Issuance'!$I$4:$I$991,$A16,'Daily Issuance'!$E$4:$E$991,"Services",'Daily Issuance'!$B$4:$B$991,">="&DATE(2026,10,1),'Daily Issuance'!$B$4:$B$991,"<"&DATE(2026,11,1)),0) -> 0 | AD16: =IFERROR(SUMIFS('Daily Issuance'!$O:$O,'Daily Issuance'!$I:$I,$A16,'Daily Issuance'!$E:$E,"Patty Cash",'Daily Issuance'!$B:$B,">="&DATE(2026,10,1),'Daily Issuance'!$B:$B,"<"&DATE(2026,11,1)),0) -> 0 | AE16: =SUM(AA16:AD16) -> 0 | AF16: =IFERROR(SUMIFS('Daily Issuance'!$O$4:$O$991,'Daily Issuance'!$I$4:$I$991,$A16,'Daily Issuance'!$E$4:$E$991,"Inventory",'Daily Issuance'!$B$4:$B$991,">="&DATE(2026,11,1),'Daily Issuance'!$B$4:$B$991,"<"&DATE(2026,12,1)),0) -> 0 | AG16: =IFERROR(SUMIFS('Daily Issuance'!$O$4:$O$991,'Daily Issuance'!$I$4:$I$991,$A16,'Daily Issuance'!$E$4:$E$991,"Non Inventory",'Daily Issuance'!$B$4:$B$991,">="&DATE(2026,11,1),'Daily Issuance'!$B$4:$B$991,"<"&DATE(2026,12,1)),0) -> 0 | AH16: =IFERROR(SUMIFS('Daily Issuance'!$O$4:$O$991,'Daily Issuance'!$I$4:$I$991,$A16,'Daily Issuance'!$E$4:$E$991,"Services",'Daily Issuance'!$B$4:$B$991,">="&DATE(2026,11,1),'Daily Issuance'!$B$4:$B$991,"<"&DATE(2026,12,1)),0) -> 0 | AI16: =IFERROR(SUMIFS('Daily Issuance'!$O:$O,'Daily Issuance'!$I:$I,$A16,'Daily Issuance'!$E:$E,"Patty Cash",'Daily Issuance'!$B:$B,">="&DATE(2026,11,1),'Daily Issuance'!$B:$B,"<"&DATE(2026,12,1)),0) -> 0 | AJ16: =SUM(AF16:AI16) -> 0 | AK16: =IFERROR(SUMIFS('Daily Issuance'!$O$4:$O$991,'Daily Issuance'!$I$4:$I$991,$A16,'Daily Issuance'!$E$4:$E$991,"Inventory",'Daily Issuance'!$B$4:$B$991,">="&DATE(2026,12,1),'Daily Issuance'!$B$4:$B$991,"<"&DATE(2027,1,1)),0) -> 0 | AL16: =IFERROR(SUMIFS('Daily Issuance'!$O$4:$O$991,'Daily Issuance'!$I$4:$I$991,$A16,'Daily Issuance'!$E$4:$E$991,"Non Inventory",'Daily Issuance'!$B$4:$B$991,">="&DATE(2026,12,1),'Daily Issuance'!$B$4:$B$991,"<"&DATE(2027,1,1)),0) -> 0 | AM16: =IFERROR(SUMIFS('Daily Issuance'!$O$4:$O$991,'Daily Issuance'!$I$4:$I$991,$A16,'Daily Issuance'!$E$4:$E$991,"Services",'Daily Issuance'!$B$4:$B$991,">="&DATE(2026,12,1),'Daily Issuance'!$B$4:$B$991,"<"&DATE(2027,1,1)),0) -> 0 | AN16: =IFERROR(SUMIFS('Daily Issuance'!$O:$O,'Daily Issuance'!$I:$I,$A16,'Daily Issuance'!$E:$E,"Patty Cash",'Daily Issuance'!$B:$B,">="&DATE(2026,12,1),'Daily Issuance'!$B:$B,"<"&DATE(2027,1,1)),0) -> 0 | AO16: =SUM(AK16:AN16) -> 0 | AP16: =SUM(F16,K16,P16,U16,Z16,AE16,AJ16,AO16) -> 6125
A17: Ishida No: 12 | B17: =IFERROR(SUMIFS('Daily Issuance'!$O:$O,'Daily Issuance'!$I:$I,$A17,'Daily Issuance'!$E:$E,"Inventory",'Daily Issuance'!$B:$B,">="&DATE(2026,5,1),'Daily Issuance'!$B:$B,"<"&DATE(2026,6,1)),0) -> 22200 | C17: =IFERROR(SUMIFS('Daily Issuance'!$O:$O,'Daily Issuance'!$I:$I,$A17,'Daily Issuance'!$E:$E,"Non Inventory",'Daily Issuance'!$B:$B,">="&DATE(2026,5,1),'Daily Issuance'!$B:$B,"<"&DATE(2026,6,1)),0) -> 5256 | D17: =IFERROR(SUMIFS('Daily Issuance'!$O:$O,'Daily Issuance'!$I:$I,$A17,'Daily Issuance'!$E:$E,"Services",'Daily Issuance'!$B:$B,">="&DATE(2026,5,1),'Daily Issuance'!$B:$B,"<"&DATE(2026,6,1)),0) -> 0 | E17: =IFERROR(SUMIFS('Daily Issuance'!$O:$O,'Daily Issuance'!$I:$I,$A17,'Daily Issuance'!$E:$E,"Patty Cash",'Daily Issuance'!$B:$B,">="&DATE(2026,5,1),'Daily Issuance'!$B:$B,"<"&DATE(2026,6,1)),0) -> 0 | F17: =SUM(B17:E17) -> 27456 | G17: =IFERROR(SUMIFS('Daily Issuance'!$O$4:$O$991,'Daily Issuance'!$I$4:$I$991,$A17,'Daily Issuance'!$E$4:$E$991,"Inventory",'Daily Issuance'!$B$4:$B$991,">="&DATE(2026,6,1),'Daily Issuance'!$B$4:$B$991,"<"&DATE(2026,7,1)),0) -> 3750 | H17: =IFERROR(SUMIFS('Daily Issuance'!$O$4:$O$991,'Daily Issuance'!$I$4:$I$991,$A17,'Daily Issuance'!$E$4:$E$991,"Non Inventory",'Daily Issuance'!$B$4:$B$991,">="&DATE(2026,6,1),'Daily Issuance'!$B$4:$B$991,"<"&DATE(2026,7,1)),0) -> 512 | I17: =IFERROR(SUMIFS('Daily Issuance'!$O$4:$O$991,'Daily Issuance'!$I$4:$I$991,$A17,'Daily Issuance'!$E$4:$E$991,"Services",'Daily Issuance'!$B$4:$B$991,">="&DATE(2026,6,1),'Daily Issuance'!$B$4:$B$991,"<"&DATE(2026,7,1)),0) -> 0 | J17: =IFERROR(SUMIFS('Daily Issuance'!$O:$O,'Daily Issuance'!$I:$I,$A17,'Daily Issuance'!$E:$E,"Patty Cash",'Daily Issuance'!$B:$B,">="&DATE(2026,6,1),'Daily Issuance'!$B:$B,"<"&DATE(2026,7,1)),0) -> 0 | K17: =SUM(G17:J17) -> 4262 | L17: =IFERROR(SUMIFS('Daily Issuance'!$O$4:$O$991,'Daily Issuance'!$I$4:$I$991,$A17,'Daily Issuance'!$E$4:$E$991,"Inventory",'Daily Issuance'!$B$4:$B$991,">="&DATE(2026,7,1),'Daily Issuance'!$B$4:$B$991,"<"&DATE(2026,8,1)),0) -> 0 | M17: =IFERROR(SUMIFS('Daily Issuance'!$O$4:$O$991,'Daily Issuance'!$I$4:$I$991,$A17,'Daily Issuance'!$E$4:$E$991,"Non Inventory",'Daily Issuance'!$B$4:$B$991,">="&DATE(2026,7,1),'Daily Issuance'!$B$4:$B$991,"<"&DATE(2026,8,1)),0) -> 0 | N17: =IFERROR(SUMIFS('Daily Issuance'!$O$4:$O$991,'Daily Issuance'!$I$4:$I$991,$A17,'Daily Issuance'!$E$4:$E$991,"Services",'Daily Issuance'!$B$4:$B$991,">="&DATE(2026,7,1),'Daily Issuance'!$B$4:$B$991,"<"&DATE(2026,8,1)),0) -> 0 | O17: =IFERROR(SUMIFS('Daily Issuance'!$O:$O,'Daily Issuance'!$I:$I,$A17,'Daily Issuance'!$E:$E,"Patty Cash",'Daily Issuance'!$B:$B,">="&DATE(2026,7,1),'Daily Issuance'!$B:$B,"<"&DATE(2026,8,1)),0) -> 0 | P17: =SUM(L17:O17) -> 0 | Q17: =IFERROR(SUMIFS('Daily Issuance'!$O$4:$O$991,'Daily Issuance'!$I$4:$I$991,$A17,'Daily Issuance'!$E$4:$E$991,"Inventory",'Daily Issuance'!$B$4:$B$991,">="&DATE(2026,8,1),'Daily Issuance'!$B$4:$B$991,"<"&DATE(2026,9,1)),0) -> 0 | R17: =IFERROR(SUMIFS('Daily Issuance'!$O$4:$O$991,'Daily Issuance'!$I$4:$I$991,$A17,'Daily Issuance'!$E$4:$E$991,"Non Inventory",'Daily Issuance'!$B$4:$B$991,">="&DATE(2026,8,1),'Daily Issuance'!$B$4:$B$991,"<"&DATE(2026,9,1)),0) -> 0 | S17: =IFERROR(SUMIFS('Daily Issuance'!$O$4:$O$991,'Daily Issuance'!$I$4:$I$991,$A17,'Daily Issuance'!$E$4:$E$991,"Services",'Daily Issuance'!$B$4:$B$991,">="&DATE(2026,8,1),'Daily Issuance'!$B$4:$B$991,"<"&DATE(2026,9,1)),0) -> 0 | T17: =IFERROR(SUMIFS('Daily Issuance'!$O:$O,'Daily Issuance'!$I:$I,$A17,'Daily Issuance'!$E:$E,"Patty Cash",'Daily Issuance'!$B:$B,">="&DATE(2026,8,1),'Daily Issuance'!$B:$B,"<"&DATE(2026,9,1)),0) -> 0 | U17: =SUM(Q17:T17) -> 0 | V17: =IFERROR(SUMIFS('Daily Issuance'!$O$4:$O$991,'Daily Issuance'!$I$4:$I$991,$A17,'Daily Issuance'!$E$4:$E$991,"Inventory",'Daily Issuance'!$B$4:$B$991,">="&DATE(2026,9,1),'Daily Issuance'!$B$4:$B$991,"<"&DATE(2026,10,1)),0) -> 0 | W17: =IFERROR(SUMIFS('Daily Issuance'!$O$4:$O$991,'Daily Issuance'!$I$4:$I$991,$A17,'Daily Issuance'!$E$4:$E$991,"Non Inventory",'Daily Issuance'!$B$4:$B$991,">="&DATE(2026,9,1),'Daily Issuance'!$B$4:$B$991,"<"&DATE(2026,10,1)),0) -> 0 | X17: =IFERROR(SUMIFS('Daily Issuance'!$O$4:$O$991,'Daily Issuance'!$I$4:$I$991,$A17,'Daily Issuance'!$E$4:$E$991,"Services",'Daily Issuance'!$B$4:$B$991,">="&DATE(2026,9,1),'Daily Issuance'!$B$4:$B$991,"<"&DATE(2026,10,1)),0) -> 0 | Y17: =IFERROR(SUMIFS('Daily Issuance'!$O:$O,'Daily Issuance'!$I:$I,$A17,'Daily Issuance'!$E:$E,"Patty Cash",'Daily Issuance'!$B:$B,">="&DATE(2026,9,1),'Daily Issuance'!$B:$B,"<"&DATE(2026,10,1)),0) -> 0 | Z17: =SUM(V17:Y17) -> 0 | AA17: =IFERROR(SUMIFS('Daily Issuance'!$O$4:$O$991,'Daily Issuance'!$I$4:$I$991,$A17,'Daily Issuance'!$E$4:$E$991,"Inventory",'Daily Issuance'!$B$4:$B$991,">="&DATE(2026,10,1),'Daily Issuance'!$B$4:$B$991,"<"&DATE(2026,11,1)),0) -> 0 | AB17: =IFERROR(SUMIFS('Daily Issuance'!$O$4:$O$991,'Daily Issuance'!$I$4:$I$991,$A17,'Daily Issuance'!$E$4:$E$991,"Non Inventory",'Daily Issuance'!$B$4:$B$991,">="&DATE(2026,10,1),'Daily Issuance'!$B$4:$B$991,"<"&DATE(2026,11,1)),0) -> 0 | AC17: =IFERROR(SUMIFS('Daily Issuance'!$O$4:$O$991,'Daily Issuance'!$I$4:$I$991,$A17,'Daily Issuance'!$E$4:$E$991,"Services",'Daily Issuance'!$B$4:$B$991,">="&DATE(2026,10,1),'Daily Issuance'!$B$4:$B$991,"<"&DATE(2026,11,1)),0) -> 0 | AD17: =IFERROR(SUMIFS('Daily Issuance'!$O:$O,'Daily Issuance'!$I:$I,$A17,'Daily Issuance'!$E:$E,"Patty Cash",'Daily Issuance'!$B:$B,">="&DATE(2026,10,1),'Daily Issuance'!$B:$B,"<"&DATE(2026,11,1)),0) -> 0 | AE17: =SUM(AA17:AD17) -> 0 | AF17: =IFERROR(SUMIFS('Daily Issuance'!$O$4:$O$991,'Daily Issuance'!$I$4:$I$991,$A17,'Daily Issuance'!$E$4:$E$991,"Inventory",'Daily Issuance'!$B$4:$B$991,">="&DATE(2026,11,1),'Daily Issuance'!$B$4:$B$991,"<"&DATE(2026,12,1)),0) -> 0 | AG17: =IFERROR(SUMIFS('Daily Issuance'!$O$4:$O$991,'Daily Issuance'!$I$4:$I$991,$A17,'Daily Issuance'!$E$4:$E$991,"Non Inventory",'Daily Issuance'!$B$4:$B$991,">="&DATE(2026,11,1),'Daily Issuance'!$B$4:$B$991,"<"&DATE(2026,12,1)),0) -> 0 | AH17: =IFERROR(SUMIFS('Daily Issuance'!$O$4:$O$991,'Daily Issuance'!$I$4:$I$991,$A17,'Daily Issuance'!$E$4:$E$991,"Services",'Daily Issuance'!$B$4:$B$991,">="&DATE(2026,11,1),'Daily Issuance'!$B$4:$B$991,"<"&DATE(2026,12,1)),0) -> 0 | AI17: =IFERROR(SUMIFS('Daily Issuance'!$O:$O,'Daily Issuance'!$I:$I,$A17,'Daily Issuance'!$E:$E,"Patty Cash",'Daily Issuance'!$B:$B,">="&DATE(2026,11,1),'Daily Issuance'!$B:$B,"<"&DATE(2026,12,1)),0) -> 0 | AJ17: =SUM(AF17:AI17) -> 0 | AK17: =IFERROR(SUMIFS('Daily Issuance'!$O$4:$O$991,'Daily Issuance'!$I$4:$I$991,$A17,'Daily Issuance'!$E$4:$E$991,"Inventory",'Daily Issuance'!$B$4:$B$991,">="&DATE(2026,12,1),'Daily Issuance'!$B$4:$B$991,"<"&DATE(2027,1,1)),0) -> 0 | AL17: =IFERROR(SUMIFS('Daily Issuance'!$O$4:$O$991,'Daily Issuance'!$I$4:$I$991,$A17,'Daily Issuance'!$E$4:$E$991,"Non Inventory",'Daily Issuance'!$B$4:$B$991,">="&DATE(2026,12,1),'Daily Issuance'!$B$4:$B$991,"<"&DATE(2027,1,1)),0) -> 0 | AM17: =IFERROR(SUMIFS('Daily Issuance'!$O$4:$O$991,'Daily Issuance'!$I$4:$I$991,$A17,'Daily Issuance'!$E$4:$E$991,"Services",'Daily Issuance'!$B$4:$B$991,">="&DATE(2026,12,1),'Daily Issuance'!$B$4:$B$991,"<"&DATE(2027,1,1)),0) -> 0 | AN17: =IFERROR(SUMIFS('Daily Issuance'!$O:$O,'Daily Issuance'!$I:$I,$A17,'Daily Issuance'!$E:$E,"Patty Cash",'Daily Issuance'!$B:$B,">="&DATE(2026,12,1),'Daily Issuance'!$B:$B,"<"&DATE(2027,1,1)),0) -> 0 | AO17: =SUM(AK17:AN17) -> 0 | AP17: =SUM(F17,K17,P17,U17,Z17,AE17,AJ17,AO17) -> 31718
... A36: Water Cooled Chiller | B36: =IFERROR(SUMIFS('Daily Issuance'!$O:$O,'Daily Issuance'!$I:$I,$A36,'Daily Issuance'!$E:$E,"Inventory",'Daily Issuance'!$B:$B,">="&DATE(2026,5,1),'Daily Issuance'!$B:$B,"<"&DATE(2026,6,1)),0) -> 0 | C36: =IFERROR(SUMIFS('Daily Issuance'!$O:$O,'Daily Issuance'!$I:$I,$A36,'Daily Issuance'!$E:$E,"Non Inventory",'Daily Issuance'!$B:$B,">="&DATE(2026,5,1),'Daily Issuance'!$B:$B,"<"&DATE(2026,6,1)),0) -> 174 | D36: =IFERROR(SUMIFS('Daily Issuance'!$O:$O,'Daily Issuance'!$I:$I,$A36,'Daily Issuance'!$E:$E,"Services",'Daily Issuance'!$B:$B,">="&DATE(2026,5,1),'Daily Issuance'!$B:$B,"<"&DATE(2026,6,1)),0) -> 0 | E36: =IFERROR(SUMIFS('Daily Issuance'!$O:$O,'Daily Issuance'!$I:$I,$A36,'Daily Issuance'!$E:$E,"Patty Cash",'Daily Issuance'!$B:$B,">="&DATE(2026,5,1),'Daily Issuance'!$B:$B,"<"&DATE(2026,6,1)),0) -> 2455 | F36: =SUM(B36:E36) -> 2629 | G36: =IFERROR(SUMIFS('Daily Issuance'!$O$4:$O$991,'Daily Issuance'!$I$4:$I$991,$A36,'Daily Issuance'!$E$4:$E$991,"Inventory",'Daily Issuance'!$B$4:$B$991,">="&DATE(2026,6,1),'Daily Issuance'!$B$4:$B$991,"<"&DATE(2026,7,1)),0) -> 6656 | H36: =IFERROR(SUMIFS('Daily Issuance'!$O$4:$O$991,'Daily Issuance'!$I$4:$I$991,$A36,'Daily Issuance'!$E$4:$E$991,"Non Inventory",'Daily Issuance'!$B$4:$B$991,">="&DATE(2026,6,1),'Daily Issuance'!$B$4:$B$991,"<"&DATE(2026,7,1)),0) -> 61572 | I36: =IFERROR(SUMIFS('Daily Issuance'!$O$4:$O$991,'Daily Issuance'!$I$4:$I$991,$A36,'Daily Issuance'!$E$4:$E$991,"Services",'Daily Issuance'!$B$4:$B$991,">="&DATE(2026,6,1),'Daily Issuance'!$B$4:$B$991,"<"&DATE(2026,7,1)),0) -> 0 | J36: =IFERROR(SUMIFS('Daily Issuance'!$O:$O,'Daily Issuance'!$I:$I,$A36,'Daily Issuance'!$E:$E,"Patty Cash",'Daily Issuance'!$B:$B,">="&DATE(2026,6,1),'Daily Issuance'!$B:$B,"<"&DATE(2026,7,1)),0) -> 400 | K36: =SUM(G36:J36) -> 68628 | L36: =IFERROR(SUMIFS('Daily Issuance'!$O$4:$O$991,'Daily Issuance'!$I$4:$I$991,$A36,'Daily Issuance'!$E$4:$E$991,"Inventory",'Daily Issuance'!$B$4:$B$991,">="&DATE(2026,7,1),'Daily Issuance'!$B$4:$B$991,"<"&DATE(2026,8,1)),0) -> 0 | M36: =IFERROR(SUMIFS('Daily Issuance'!$O$4:$O$991,'Daily Issuance'!$I$4:$I$991,$A36,'Daily Issuance'!$E$4:$E$991,"Non Inventory",'Daily Issuance'!$B$4:$B$991,">="&DATE(2026,7,1),'Daily Issuance'!$B$4:$B$991,"<"&DATE(2026,8,1)),0) -> 0 | N36: =IFERROR(SUMIFS('Daily Issuance'!$O$4:$O$991,'Daily Issuance'!$I$4:$I$991,$A36,'Daily Issuance'!$E$4:$E$991,"Services",'Daily Issuance'!$B$4:$B$991,">="&DATE(2026,7,1),'Daily Issuance'!$B$4:$B$991,"<"&DATE(2026,8,1)),0) -> 0 | O36: =IFERROR(SUMIFS('Daily Issuance'!$O:$O,'Daily Issuance'!$I:$I,$A36,'Daily Issuance'!$E:$E,"Patty Cash",'Daily Issuance'!$B:$B,">="&DATE(2026,7,1),'Daily Issuance'!$B:$B,"<"&DATE(2026,8,1)),0) -> 0 | P36: =SUM(L36:O36) -> 0 | Q36: =IFERROR(SUMIFS('Daily Issuance'!$O$4:$O$991,'Daily Issuance'!$I$4:$I$991,$A36,'Daily Issuance'!$E$4:$E$991,"Inventory",'Daily Issuance'!$B$4:$B$991,">="&DATE(2026,8,1),'Daily Issuance'!$B$4:$B$991,"<"&DATE(2026,9,1)),0) -> 0 | R36: =IFERROR(SUMIFS('Daily Issuance'!$O$4:$O$991,'Daily Issuance'!$I$4:$I$991,$A36,'Daily Issuance'!$E$4:$E$991,"Non Inventory",'Daily Issuance'!$B$4:$B$991,">="&DATE(2026,8,1),'Daily Issuance'!$B$4:$B$991,"<"&DATE(2026,9,1)),0) -> 0 | S36: =IFERROR(SUMIFS('Daily Issuance'!$O$4:$O$991,'Daily Issuance'!$I$4:$I$991,$A36,'Daily Issuance'!$E$4:$E$991,"Services",'Daily Issuance'!$B$4:$B$991,">="&DATE(2026,8,1),'Daily Issuance'!$B$4:$B$991,"<"&DATE(2026,9,1)),0) -> 0 | T36: =IFERROR(SUMIFS('Daily Issuance'!$O:$O,'Daily Issuance'!$I:$I,$A36,'Daily Issuance'!$E:$E,"Patty Cash",'Daily Issuance'!$B:$B,">="&DATE(2026,8,1),'Daily Issuance'!$B:$B,"<"&DATE(2026,9,1)),0) -> 0 | U36: =SUM(Q36:T36) -> 0 | V36: =IFERROR(SUMIFS('Daily Issuance'!$O$4:$O$991,'Daily Issuance'!$I$4:$I$991,$A36,'Daily Issuance'!$E$4:$E$991,"Inventory",'Daily Issuance'!$B$4:$B$991,">="&DATE(2026,9,1),'Daily Issuance'!$B$4:$B$991,"<"&DATE(2026,10,1)),0) -> 0 | W36: =IFERROR(SUMIFS('Daily Issuance'!$O$4:$O$991,'Daily Issuance'!$I$4:$I$991,$A36,'Daily Issuance'!$E$4:$E$991,"Non Inventory",'Daily Issuance'!$B$4:$B$991,">="&DATE(2026,9,1),'Daily Issuance'!$B$4:$B$991,"<"&DATE(2026,10,1)),0) -> 0 | X36: =IFERROR(SUMIFS('Daily Issuance'!$O$4:$O$991,'Daily Issuance'!$I$4:$I$991,$A36,'Daily Issuance'!$E$4:$E$991,"Services",'Daily Issuance'!$B$4:$B$991,">="&DATE(2026,9,1),'Daily Issuance'!$B$4:$B$991,"<"&DATE(2026,10,1)),0) -> 0 | Y36: =IFERROR(SUMIFS('Daily Issuance'!$O:$O,'Daily Issuance'!$I:$I,$A36,'Daily Issuance'!$E:$E,"Patty Cash",'Daily Issuance'!$B:$B,">="&DATE(2026,9,1),'Daily Issuance'!$B:$B,"<"&DATE(2026,10,1)),0) -> 0 | Z36: =SUM(V36:Y36) -> 0 | AA36: =IFERROR(SUMIFS('Daily Issuance'!$O$4:$O$991,'Daily Issuance'!$I$4:$I$991,$A36,'Daily Issuance'!$E$4:$E$991,"Inventory",'Daily Issuance'!$B$4:$B$991,">="&DATE(2026,10,1),'Daily Issuance'!$B$4:$B$991,"<"&DATE(2026,11,1)),0) -> 0 | AB36: =IFERROR(SUMIFS('Daily Issuance'!$O$4:$O$991,'Daily Issuance'!$I$4:$I$991,$A36,'Daily Issuance'!$E$4:$E$991,"Non Inventory",'Daily Issuance'!$B$4:$B$991,">="&DATE(2026,10,1),'Daily Issuance'!$B$4:$B$991,"<"&DATE(2026,11,1)),0) -> 0 | AC36: =IFERROR(SUMIFS('Daily Issuance'!$O$4:$O$991,'Daily Issuance'!$I$4:$I$991,$A36,'Daily Issuance'!$E$4:$E$991,"Services",'Daily Issuance'!$B$4:$B$991,">="&DATE(2026,10,1),'Daily Issuance'!$B$4:$B$991,"<"&DATE(2026,11,1)),0) -> 0 | AD36: =IFERROR(SUMIFS('Daily Issuance'!$O:$O,'Daily Issuance'!$I:$I,$A36,'Daily Issuance'!$E:$E,"Patty Cash",'Daily Issuance'!$B:$B,">="&DATE(2026,10,1),'Daily Issuance'!$B:$B,"<"&DATE(2026,11,1)),0) -> 0 | AE36: =SUM(AA36:AD36) -> 0 | AF36: =IFERROR(SUMIFS('Daily Issuance'!$O$4:$O$991,'Daily Issuance'!$I$4:$I$991,$A36,'Daily Issuance'!$E$4:$E$991,"Inventory",'Daily Issuance'!$B$4:$B$991,">="&DATE(2026,11,1),'Daily Issuance'!$B$4:$B$991,"<"&DATE(2026,12,1)),0) -> 0 | AG36: =IFERROR(SUMIFS('Daily Issuance'!$O$4:$O$991,'Daily Issuance'!$I$4:$I$991,$A36,'Daily Issuance'!$E$4:$E$991,"Non Inventory",'Daily Issuance'!$B$4:$B$991,">="&DATE(2026,11,1),'Daily Issuance'!$B$4:$B$991,"<"&DATE(2026,12,1)),0) -> 0 | AH36: =IFERROR(SUMIFS('Daily Issuance'!$O$4:$O$991,'Daily Issuance'!$I$4:$I$991,$A36,'Daily Issuance'!$E$4:$E$991,"Services",'Daily Issuance'!$B$4:$B$991,">="&DATE(2026,11,1),'Daily Issuance'!$B$4:$B$991,"<"&DATE(2026,12,1)),0) -> 0 | AI36: =IFERROR(SUMIFS('Daily Issuance'!$O:$O,'Daily Issuance'!$I:$I,$A36,'Daily Issuance'!$E:$E,"Patty Cash",'Daily Issuance'!$B:$B,">="&DATE(2026,11,1),'Daily Issuance'!$B:$B,"<"&DATE(2026,12,1)),0) -> 0 | AJ36: =SUM(AF36:AI36) -> 0 | AK36: =IFERROR(SUMIFS('Daily Issuance'!$O$4:$O$991,'Daily Issuance'!$I$4:$I$991,$A36,'Daily Issuance'!$E$4:$E$991,"Inventory",'Daily Issuance'!$B$4:$B$991,">="&DATE(2026,12,1),'Daily Issuance'!$B$4:$B$991,"<"&DATE(2027,1,1)),0) -> 0 | AL36: =IFERROR(SUMIFS('Daily Issuance'!$O$4:$O$991,'Daily Issuance'!$I$4:$I$991,$A36,'Daily Issuance'!$E$4:$E$991,"Non Inventory",'Daily Issuance'!$B$4:$B$991,">="&DATE(2026,12,1),'Daily Issuance'!$B$4:$B$991,"<"&DATE(2027,1,1)),0) -> 0 | AM36: =IFERROR(SUMIFS('Daily Issuance'!$O$4:$O$991,'Daily Issuance'!$I$4:$I$991,$A36,'Daily Issuance'!$E$4:$E$991,"Services",'Daily Issuance'!$B$4:$B$991,">="&DATE(2026,12,1),'Daily Issuance'!$B$4:$B$991,"<"&DATE(2027,1,1)),0) -> 0 | AN36: =IFERROR(SUMIFS('Daily Issuance'!$O:$O,'Daily Issuance'!$I:$I,$A36,'Daily Issuance'!$E:$E,"Patty Cash",'Daily Issuance'!$B:$B,">="&DATE(2026,12,1),'Daily Issuance'!$B:$B,"<"&DATE(2027,1,1)),0) -> 0 | AO36: =SUM(AK36:AN36) -> 0 | AP36: =SUM(F36,K36,P36,U36,Z36,AE36,AJ36,AO36) -> 71257
A37: RO Plant | B37: =IFERROR(SUMIFS('Daily Issuance'!$O:$O,'Daily Issuance'!$I:$I,$A37,'Daily Issuance'!$E:$E,"Inventory",'Daily Issuance'!$B:$B,">="&DATE(2026,5,1),'Daily Issuance'!$B:$B,"<"&DATE(2026,6,1)),0) -> 0 | C37: =IFERROR(SUMIFS('Daily Issuance'!$O:$O,'Daily Issuance'!$I:$I,$A37,'Daily Issuance'!$E:$E,"Non Inventory",'Daily Issuance'!$B:$B,">="&DATE(2026,5,1),'Daily Issuance'!$B:$B,"<"&DATE(2026,6,1)),0) -> 2085 | D37: =IFERROR(SUMIFS('Daily Issuance'!$O:$O,'Daily Issuance'!$I:$I,$A37,'Daily Issuance'!$E:$E,"Services",'Daily Issuance'!$B:$B,">="&DATE(2026,5,1),'Daily Issuance'!$B:$B,"<"&DATE(2026,6,1)),0) -> 0 | E37: =IFERROR(SUMIFS('Daily Issuance'!$O:$O,'Daily Issuance'!$I:$I,$A37,'Daily Issuance'!$E:$E,"Patty Cash",'Daily Issuance'!$B:$B,">="&DATE(2026,5,1),'Daily Issuance'!$B:$B,"<"&DATE(2026,6,1)),0) -> 0 | F37: =SUM(B37:E37) -> 2085 | G37: =IFERROR(SUMIFS('Daily Issuance'!$O$4:$O$991,'Daily Issuance'!$I$4:$I$991,$A37,'Daily Issuance'!$E$4:$E$991,"Inventory",'Daily Issuance'!$B$4:$B$991,">="&DATE(2026,6,1),'Daily Issuance'!$B$4:$B$991,"<"&DATE(2026,7,1)),0) -> 3100 | H37: =IFERROR(SUMIFS('Daily Issuance'!$O$4:$O$991,'Daily Issuance'!$I$4:$I$991,$A37,'Daily Issuance'!$E$4:$E$991,"Non Inventory",'Daily Issuance'!$B$4:$B$991,">="&DATE(2026,6,1),'Daily Issuance'!$B$4:$B$991,"<"&DATE(2026,7,1)),0) -> 150237 | I37: =IFERROR(SUMIFS('Daily Issuance'!$O$4:$O$991,'Daily Issuance'!$I$4:$I$991,$A37,'Daily Issuance'!$E$4:$E$991,"Services",'Daily Issuance'!$B$4:$B$991,">="&DATE(2026,6,1),'Daily Issuance'!$B$4:$B$991,"<"&DATE(2026,7,1)),0) -> 0 | J37: =IFERROR(SUMIFS('Daily Issuance'!$O:$O,'Daily Issuance'!$I:$I,$A37,'Daily Issuance'!$E:$E,"Patty Cash",'Daily Issuance'!$B:$B,">="&DATE(2026,6,1),'Daily Issuance'!$B:$B,"<"&DATE(2026,7,1)),0) -> 0 | K37: =SUM(G37:J37) -> 153337 | P37: =SUM(L37:O37) -> 0 | U37: =SUM(Q37:T37) -> 0 | Z37: =SUM(V37:Y37) -> 0 | AE37: =SUM(AA37:AD37) -> 0 | AJ37: =SUM(AF37:AI37) -> 0 | AO37: =SUM(AK37:AN37) -> 0 | AP37: =SUM(F37,K37,P37,U37,Z37,AE37,AJ37,AO37) -> 155422
A38: LPG Plant | B38: =IFERROR(SUMIFS('Daily Issuance'!$O:$O,'Daily Issuance'!$I:$I,$A38,'Daily Issuance'!$E:$E,"Inventory",'Daily Issuance'!$B:$B,">="&DATE(2026,5,1),'Daily Issuance'!$B:$B,"<"&DATE(2026,6,1)),0) -> 0 | C38: =IFERROR(SUMIFS('Daily Issuance'!$O:$O,'Daily Issuance'!$I:$I,$A38,'Daily Issuance'!$E:$E,"Non Inventory",'Daily Issuance'!$B:$B,">="&DATE(2026,5,1),'Daily Issuance'!$B:$B,"<"&DATE(2026,6,1)),0) -> 0 | D38: =IFERROR(SUMIFS('Daily Issuance'!$O:$O,'Daily Issuance'!$I:$I,$A38,'Daily Issuance'!$E:$E,"Services",'Daily Issuance'!$B:$B,">="&DATE(2026,5,1),'Daily Issuance'!$B:$B,"<"&DATE(2026,6,1)),0) -> 220000 | E38: =IFERROR(SUMIFS('Daily Issuance'!$O:$O,'Daily Issuance'!$I:$I,$A38,'Daily Issuance'!$E:$E,"Patty Cash",'Daily Issuance'!$B:$B,">="&DATE(2026,5,1),'Daily Issuance'!$B:$B,"<"&DATE(2026,6,1)),0) -> 0 | F38: =SUM(B38:E38) -> 220000 | G38: =IFERROR(SUMIFS('Daily Issuance'!$O$4:$O$991,'Daily Issuance'!$I$4:$I$991,$A38,'Daily Issuance'!$E$4:$E$991,"Inventory",'Daily Issuance'!$B$4:$B$991,">="&DATE(2026,6,1),'Daily Issuance'!$B$4:$B$991,"<"&DATE(2026,7,1)),0) -> 0 | H38: =IFERROR(SUMIFS('Daily Issuance'!$O$4:$O$991,'Daily Issuance'!$I$4:$I$991,$A38,'Daily Issuance'!$E$4:$E$991,"Non Inventory",'Daily Issuance'!$B$4:$B$991,">="&DATE(2026,6,1),'Daily Issuance'!$B$4:$B$991,"<"&DATE(2026,7,1)),0) -> 0 | I38: =IFERROR(SUMIFS('Daily Issuance'!$O$4:$O$991,'Daily Issuance'!$I$4:$I$991,$A38,'Daily Issuance'!$E$4:$E$991,"Services",'Daily Issuance'!$B$4:$B$991,">="&DATE(2026,6,1),'Daily Issuance'!$B$4:$B$991,"<"&DATE(2026,7,1)),0) -> 220000 | J38: =IFERROR(SUMIFS('Daily Issuance'!$O:$O,'Daily Issuance'!$I:$I,$A38,'Daily Issuance'!$E:$E,"Patty Cash",'Daily Issuance'!$B:$B,">="&DATE(2026,6,1),'Daily Issuance'!$B:$B,"<"&DATE(2026,7,1)),0) -> 0 | K38: =SUM(G38:J38) -> 220000 | N38: =IFERROR(SUMIFS('Daily Issuance'!$O$4:$O$991,'Daily Issuance'!$I$4:$I$991,$A38,'Daily Issuance'!$E$4:$E$991,"Services",'Daily Issuance'!$B$4:$B$991,">="&DATE(2026,7,1),'Daily Issuance'!$B$4:$B$991,"<"&DATE(2026,8,1)),0) -> 0 | O38: =IFERROR(SUMIFS('Daily Issuance'!$O:$O,'Daily Issuance'!$I:$I,$A38,'Daily Issuance'!$E:$E,"Patty Cash",'Daily Issuance'!$B:$B,">="&DATE(2026,7,1),'Daily Issuance'!$B:$B,"<"&DATE(2026,8,1)),0) -> 0 | P38: =SUM(L38:O38) -> 0 | S38: =IFERROR(SUMIFS('Daily Issuance'!$O$4:$O$991,'Daily Issuance'!$I$4:$I$991,$A38,'Daily Issuance'!$E$4:$E$991,"Services",'Daily Issuance'!$B$4:$B$991,">="&DATE(2026,8,1),'Daily Issuance'!$B$4:$B$991,"<"&DATE(2026,9,1)),0) -> 0 | T38: =IFERROR(SUMIFS('Daily Issuance'!$O:$O,'Daily Issuance'!$I:$I,$A38,'Daily Issuance'!$E:$E,"Patty Cash",'Daily Issuance'!$B:$B,">="&DATE(2026,8,1),'Daily Issuance'!$B:$B,"<"&DATE(2026,9,1)),0) -> 0 | U38: =SUM(Q38:T38) -> 0 | X38: =IFERROR(SUMIFS('Daily Issuance'!$O$4:$O$991,'Daily Issuance'!$I$4:$I$991,$A38,'Daily Issuance'!$E$4:$E$991,"Services",'Daily Issuance'!$B$4:$B$991,">="&DATE(2026,9,1),'Daily Issuance'!$B$4:$B$991,"<"&DATE(2026,10,1)),0) -> 0 | Y38: =IFERROR(SUMIFS('Daily Issuance'!$O:$O,'Daily Issuance'!$I:$I,$A38,'Daily Issuance'!$E:$E,"Patty Cash",'Daily Issuance'!$B:$B,">="&DATE(2026,9,1),'Daily Issuance'!$B:$B,"<"&DATE(2026,10,1)),0) -> 0 | Z38: =SUM(V38:Y38) -> 0 | AC38: =IFERROR(SUMIFS('Daily Issuance'!$O$4:$O$991,'Daily Issuance'!$I$4:$I$991,$A38,'Daily Issuance'!$E$4:$E$991,"Services",'Daily Issuance'!$B$4:$B$991,">="&DATE(2026,10,1),'Daily Issuance'!$B$4:$B$991,"<"&DATE(2026,11,1)),0) -> 0 | AD38: =IFERROR(SUMIFS('Daily Issuance'!$O:$O,'Daily Issuance'!$I:$I,$A38,'Daily Issuance'!$E:$E,"Patty Cash",'Daily Issuance'!$B:$B,">="&DATE(2026,10,1),'Daily Issuance'!$B:$B,"<"&DATE(2026,11,1)),0) -> 0 | AE38: =SUM(AA38:AD38) -> 0 | AH38: =IFERROR(SUMIFS('Daily Issuance'!$O$4:$O$991,'Daily Issuance'!$I$4:$I$991,$A38,'Daily Issuance'!$E$4:$E$991,"Services",'Daily Issuance'!$B$4:$B$991,">="&DATE(2026,11,1),'Daily Issuance'!$B$4:$B$991,"<"&DATE(2026,12,1)),0) -> 0 | AI38: =IFERROR(SUMIFS('Daily Issuance'!$O:$O,'Daily Issuance'!$I:$I,$A38,'Daily Issuance'!$E:$E,"Patty Cash",'Daily Issuance'!$B:$B,">="&DATE(2026,11,1),'Daily Issuance'!$B:$B,"<"&DATE(2026,12,1)),0) -> 0 | AJ38: =SUM(AF38:AI38) -> 0 | AM38: =IFERROR(SUMIFS('Daily Issuance'!$O$4:$O$991,'Daily Issuance'!$I$4:$I$991,$A38,'Daily Issuance'!$E$4:$E$991,"Services",'Daily Issuance'!$B$4:$B$991,">="&DATE(2026,12,1),'Daily Issuance'!$B$4:$B$991,"<"&DATE(2027,1,1)),0) -> 0 | AN38: =IFERROR(SUMIFS('Daily Issuance'!$O:$O,'Daily Issuance'!$I:$I,$A38,'Daily Issuance'!$E:$E,"Patty Cash",'Daily Issuance'!$B:$B,">="&DATE(2026,12,1),'Daily Issuance'!$B:$B,"<"&DATE(2027,1,1)),0) -> 0 | AO38: =SUM(AK38:AN38) -> 0 | AP38: =SUM(F38,K38,P38,U38,Z38,AE38,AJ38,AO38) -> 440000
A39: WWTP | B39: =IFERROR(SUMIFS('Daily Issuance'!$O:$O,'Daily Issuance'!$I:$I,$A39,'Daily Issuance'!$E:$E,"Inventory",'Daily Issuance'!$B:$B,">="&DATE(2026,5,1),'Daily Issuance'!$B:$B,"<"&DATE(2026,6,1)),0) -> 0 | C39: =IFERROR(SUMIFS('Daily Issuance'!$O:$O,'Daily Issuance'!$I:$I,$A39,'Daily Issuance'!$E:$E,"Non Inventory",'Daily Issuance'!$B:$B,">="&DATE(2026,5,1),'Daily Issuance'!$B:$B,"<"&DATE(2026,6,1)),0) -> 0 | D39: =IFERROR(SUMIFS('Daily Issuance'!$O:$O,'Daily Issuance'!$I:$I,$A39,'Daily Issuance'!$E:$E,"Services",'Daily Issuance'!$B:$B,">="&DATE(2026,5,1),'Daily Issuance'!$B:$B,"<"&DATE(2026,6,1)),0) -> 160000 | E39: =IFERROR(SUMIFS('Daily Issuance'!$O:$O,'Daily Issuance'!$I:$I,$A39,'Daily Issuance'!$E:$E,"Patty Cash",'Daily Issuance'!$B:$B,">="&DATE(2026,5,1),'Daily Issuance'!$B:$B,"<"&DATE(2026,6,1)),0) -> 510 | F39: =SUM(B39:E39) -> 160510 | G39: =IFERROR(SUMIFS('Daily Issuance'!$O$4:$O$991,'Daily Issuance'!$I$4:$I$991,$A39,'Daily Issuance'!$E$4:$E$991,"Inventory",'Daily Issuance'!$B$4:$B$991,">="&DATE(2026,6,1),'Daily Issuance'!$B$4:$B$991,"<"&DATE(2026,7,1)),0) -> 0 | H39: =IFERROR(SUMIFS('Daily Issuance'!$O$4:$O$991,'Daily Issuance'!$I$4:$I$991,$A39,'Daily Issuance'!$E$4:$E$991,"Non Inventory",'Daily Issuance'!$B$4:$B$991,">="&DATE(2026,6,1),'Daily Issuance'!$B$4:$B$991,"<"&DATE(2026,7,1)),0) -> 0 | I39: =IFERROR(SUMIFS('Daily Issuance'!$O$4:$O$991,'Daily Issuance'!$I$4:$I$991,$A39,'Daily Issuance'!$E$4:$E$991,"Services",'Daily Issuance'!$B$4:$B$991,">="&DATE(2026,6,1),'Daily Issuance'!$B$4:$B$991,"<"&DATE(2026,7,1)),0) -> 160000 | J39: =IFERROR(SUMIFS('Daily Issuance'!$O:$O,'Daily Issuance'!$I:$I,$A39,'Daily Issuance'!$E:$E,"Patty Cash",'Daily Issuance'!$B:$B,">="&DATE(2026,6,1),'Daily Issuance'!$B:$B,"<"&DATE(2026,7,1)),0) -> 0 | K39: =SUM(G39:J39) -> 160000 | L39: =IFERROR(SUMIFS('Daily Issuance'!$O$4:$O$991,'Daily Issuance'!$I$4:$I$991,$A39,'Daily Issuance'!$E$4:$E$991,"Inventory",'Daily Issuance'!$B$4:$B$991,">="&DATE(2026,7,1),'Daily Issuance'!$B$4:$B$991,"<"&DATE(2026,8,1)),0) -> 0 | M39: =IFERROR(SUMIFS('Daily Issuance'!$O$4:$O$991,'Daily Issuance'!$I$4:$I$991,$A39,'Daily Issuance'!$E$4:$E$991,"Non Inventory",'Daily Issuance'!$B$4:$B$991,">="&DATE(2026,7,1),'Daily Issuance'!$B$4:$B$991,"<"&DATE(2026,8,1)),0) -> 0 | N39: =IFERROR(SUMIFS('Daily Issuance'!$O$4:$O$991,'Daily Issuance'!$I$4:$I$991,$A39,'Daily Issuance'!$E$4:$E$991,"Services",'Daily Issuance'!$B$4:$B$991,">="&DATE(2026,7,1),'Daily Issuance'!$B$4:$B$991,"<"&DATE(2026,8,1)),0) -> 0 | O39: =IFERROR(SUMIFS('Daily Issuance'!$O:$O,'Daily Issuance'!$I:$I,$A39,'Daily Issuance'!$E:$E,"Patty Cash",'Daily Issuance'!$B:$B,">="&DATE(2026,7,1),'Daily Issuance'!$B:$B,"<"&DATE(2026,8,1)),0) -> 0 | P39: =SUM(L39:O39) -> 0 | Q39: =IFERROR(SUMIFS('Daily Issuance'!$O$4:$O$991,'Daily Issuance'!$I$4:$I$991,$A39,'Daily Issuance'!$E$4:$E$991,"Inventory",'Daily Issuance'!$B$4:$B$991,">="&DATE(2026,8,1),'Daily Issuance'!$B$4:$B$991,"<"&DATE(2026,9,1)),0) -> 0 | R39: =IFERROR(SUMIFS('Daily Issuance'!$O$4:$O$991,'Daily Issuance'!$I$4:$I$991,$A39,'Daily Issuance'!$E$4:$E$991,"Non Inventory",'Daily Issuance'!$B$4:$B$991,">="&DATE(2026,8,1),'Daily Issuance'!$B$4:$B$991,"<"&DATE(2026,9,1)),0) -> 0 | S39: =IFERROR(SUMIFS('Daily Issuance'!$O$4:$O$991,'Daily Issuance'!$I$4:$I$991,$A39,'Daily Issuance'!$E$4:$E$991,"Services",'Daily Issuance'!$B$4:$B$991,">="&DATE(2026,8,1),'Daily Issuance'!$B$4:$B$991,"<"&DATE(2026,9,1)),0) -> 0 | T39: =IFERROR(SUMIFS('Daily Issuance'!$O:$O,'Daily Issuance'!$I:$I,$A39,'Daily Issuance'!$E:$E,"Patty Cash",'Daily Issuance'!$B:$B,">="&DATE(2026,8,1),'Daily Issuance'!$B:$B,"<"&DATE(2026,9,1)),0) -> 0 | U39: =SUM(Q39:T39) -> 0 | V39: =IFERROR(SUMIFS('Daily Issuance'!$O$4:$O$991,'Daily Issuance'!$I$4:$I$991,$A39,'Daily Issuance'!$E$4:$E$991,"Inventory",'Daily Issuance'!$B$4:$B$991,">="&DATE(2026,9,1),'Daily Issuance'!$B$4:$B$991,"<"&DATE(2026,10,1)),0) -> 0 | W39: =IFERROR(SUMIFS('Daily Issuance'!$O$4:$O$991,'Daily Issuance'!$I$4:$I$991,$A39,'Daily Issuance'!$E$4:$E$991,"Non Inventory",'Daily Issuance'!$B$4:$B$991,">="&DATE(2026,9,1),'Daily Issuance'!$B$4:$B$991,"<"&DATE(2026,10,1)),0) -> 0 | X39: =IFERROR(SUMIFS('Daily Issuance'!$O$4:$O$991,'Daily Issuance'!$I$4:$I$991,$A39,'Daily Issuance'!$E$4:$E$991,"Services",'Daily Issuance'!$B$4:$B$991,">="&DATE(2026,9,1),'Daily Issuance'!$B$4:$B$991,"<"&DATE(2026,10,1)),0) -> 0 | Y39: =IFERROR(SUMIFS('Daily Issuance'!$O:$O,'Daily Issuance'!$I:$I,$A39,'Daily Issuance'!$E:$E,"Patty Cash",'Daily Issuance'!$B:$B,">="&DATE(2026,9,1),'Daily Issuance'!$B:$B,"<"&DATE(2026,10,1)),0) -> 0 | Z39: =SUM(V39:Y39) -> 0 | AA39: =IFERROR(SUMIFS('Daily Issuance'!$O$4:$O$991,'Daily Issuance'!$I$4:$I$991,$A39,'Daily Issuance'!$E$4:$E$991,"Inventory",'Daily Issuance'!$B$4:$B$991,">="&DATE(2026,10,1),'Daily Issuance'!$B$4:$B$991,"<"&DATE(2026,11,1)),0) -> 0 | AB39: =IFERROR(SUMIFS('Daily Issuance'!$O$4:$O$991,'Daily Issuance'!$I$4:$I$991,$A39,'Daily Issuance'!$E$4:$E$991,"Non Inventory",'Daily Issuance'!$B$4:$B$991,">="&DATE(2026,10,1),'Daily Issuance'!$B$4:$B$991,"<"&DATE(2026,11,1)),0) -> 0 | AC39: =IFERROR(SUMIFS('Daily Issuance'!$O$4:$O$991,'Daily Issuance'!$I$4:$I$991,$A39,'Daily Issuance'!$E$4:$E$991,"Services",'Daily Issuance'!$B$4:$B$991,">="&DATE(2026,10,1),'Daily Issuance'!$B$4:$B$991,"<"&DATE(2026,11,1)),0) -> 0 | AD39: =IFERROR(SUMIFS('Daily Issuance'!$O:$O,'Daily Issuance'!$I:$I,$A39,'Daily Issuance'!$E:$E,"Patty Cash",'Daily Issuance'!$B:$B,">="&DATE(2026,10,1),'Daily Issuance'!$B:$B,"<"&DATE(2026,11,1)),0) -> 0 | AE39: =SUM(AA39:AD39) -> 0 | AF39: =IFERROR(SUMIFS('Daily Issuance'!$O$4:$O$991,'Daily Issuance'!$I$4:$I$991,$A39,'Daily Issuance'!$E$4:$E$991,"Inventory",'Daily Issuance'!$B$4:$B$991,">="&DATE(2026,11,1),'Daily Issuance'!$B$4:$B$991,"<"&DATE(2026,12,1)),0) -> 0 | AG39: =IFERROR(SUMIFS('Daily Issuance'!$O$4:$O$991,'Daily Issuance'!$I$4:$I$991,$A39,'Daily Issuance'!$E$4:$E$991,"Non Inventory",'Daily Issuance'!$B$4:$B$991,">="&DATE(2026,11,1),'Daily Issuance'!$B$4:$B$991,"<"&DATE(2026,12,1)),0) -> 0 | AH39: =IFERROR(SUMIFS('Daily Issuance'!$O$4:$O$991,'Daily Issuance'!$I$4:$I$991,$A39,'Daily Issuance'!$E$4:$E$991,"Services",'Daily Issuance'!$B$4:$B$991,">="&DATE(2026,11,1),'Daily Issuance'!$B$4:$B$991,"<"&DATE(2026,12,1)),0) -> 0 | AI39: =IFERROR(SUMIFS('Daily Issuance'!$O:$O,'Daily Issuance'!$I:$I,$A39,'Daily Issuance'!$E:$E,"Patty Cash",'Daily Issuance'!$B:$B,">="&DATE(2026,11,1),'Daily Issuance'!$B:$B,"<"&DATE(2026,12,1)),0) -> 0 | AJ39: =SUM(AF39:AI39) -> 0 | AK39: =IFERROR(SUMIFS('Daily Issuance'!$O$4:$O$991,'Daily Issuance'!$I$4:$I$991,$A39,'Daily Issuance'!$E$4:$E$991,"Inventory",'Daily Issuance'!$B$4:$B$991,">="&DATE(2026,12,1),'Daily Issuance'!$B$4:$B$991,"<"&DATE(2027,1,1)),0) -> 0 | AL39: =IFERROR(SUMIFS('Daily Issuance'!$O$4:$O$991,'Daily Issuance'!$I$4:$I$991,$A39,'Daily Issuance'!$E$4:$E$991,"Non Inventory",'Daily Issuance'!$B$4:$B$991,">="&DATE(2026,12,1),'Daily Issuance'!$B$4:$B$991,"<"&DATE(2027,1,1)),0) -> 0 | AM39: =IFERROR(SUMIFS('Daily Issuance'!$O$4:$O$991,'Daily Issuance'!$I$4:$I$991,$A39,'Daily Issuance'!$E$4:$E$991,"Services",'Daily Issuance'!$B$4:$B$991,">="&DATE(2026,12,1),'Daily Issuance'!$B$4:$B$991,"<"&DATE(2027,1,1)),0) -> 0 | AN39: =IFERROR(SUMIFS('Daily Issuance'!$O:$O,'Daily Issuance'!$I:$I,$A39,'Daily Issuance'!$E:$E,"Patty Cash",'Daily Issuance'!$B:$B,">="&DATE(2026,12,1),'Daily Issuance'!$B:$B,"<"&DATE(2027,1,1)),0) -> 0 | AO39: =SUM(AK39:AN39) -> 0 | AP39: =SUM(F39,K39,P39,U39,Z39,AE39,AJ39,AO39) -> 320510
A40: General | B40: =IFERROR(SUMIFS('Daily Issuance'!$O:$O,'Daily Issuance'!$I:$I,$A40,'Daily Issuance'!$E:$E,"Inventory",'Daily Issuance'!$B:$B,">="&DATE(2026,5,1),'Daily Issuance'!$B:$B,"<"&DATE(2026,6,1)),0) -> 2741 | C40: =IFERROR(SUMIFS('Daily Issuance'!$O:$O,'Daily Issuance'!$I:$I,$A40,'Daily Issuance'!$E:$E,"Non Inventory",'Daily Issuance'!$B:$B,">="&DATE(2026,5,1),'Daily Issuance'!$B:$B,"<"&DATE(2026,6,1)),0) -> 109114 | D40: =IFERROR(SUMIFS('Daily Issuance'!$O:$O,'Daily Issuance'!$I:$I,$A40,'Daily Issuance'!$E:$E,"Services",'Daily Issuance'!$B:$B,">="&DATE(2026,5,1),'Daily Issuance'!$B:$B,"<"&DATE(2026,6,1)),0) -> 0 | E40: =IFERROR(SUMIFS('Daily Issuance'!$O:$O,'Daily Issuance'!$I:$I,$A40,'Daily Issuance'!$E:$E,"Patty Cash",'Daily Issuance'!$B:$B,">="&DATE(2026,5,1),'Daily Issuance'!$B:$B,"<"&DATE(2026,6,1)),0) -> 2465 | F40: =SUM(B40:E40) -> 114320 | G40: =IFERROR(SUMIFS('Daily Issuance'!$O$4:$O$991,'Daily Issuance'!$I$4:$I$991,$A40,'Daily Issuance'!$E$4:$E$991,"Inventory",'Daily Issuance'!$B$4:$B$991,">="&DATE(2026,6,1),'Daily Issuance'!$B$4:$B$991,"<"&DATE(2026,7,1)),0) -> 4564 | H40: =IFERROR(SUMIFS('Daily Issuance'!$O$4:$O$991,'Daily Issuance'!$I$4:$I$991,$A40,'Daily Issuance'!$E$4:$E$991,"Non Inventory",'Daily Issuance'!$B$4:$B$991,">="&DATE(2026,6,1),'Daily Issuance'!$B$4:$B$991,"<"&DATE(2026,7,1)),0) -> 13211 | I40: =IFERROR(SUMIFS('Daily Issuance'!$O$4:$O$991,'Daily Issuance'!$I$4:$I$991,$A40,'Daily Issuance'!$E$4:$E$991,"Services",'Daily Issuance'!$B$4:$B$991,">="&DATE(2026,6,1),'Daily Issuance'!$B$4:$B$991,"<"&DATE(2026,7,1)),0) -> 0 | J40: =IFERROR(SUMIFS('Daily Issuance'!$O:$O,'Daily Issuance'!$I:$I,$A40,'Daily Issuance'!$E:$E,"Patty Cash",'Daily Issuance'!$B:$B,">="&DATE(2026,6,1),'Daily Issuance'!$B:$B,"<"&DATE(2026,7,1)),0) -> 2138 | K40: =SUM(G40:J40) -> 19913 | L40: =IFERROR(SUMIFS('Daily Issuance'!$O$4:$O$991,'Daily Issuance'!$I$4:$I$991,$A40,'Daily Issuance'!$E$4:$E$991,"Inventory",'Daily Issuance'!$B$4:$B$991,">="&DATE(2026,7,1),'Daily Issuance'!$B$4:$B$991,"<"&DATE(2026,8,1)),0) -> 0 | M40: =IFERROR(SUMIFS('Daily Issuance'!$O$4:$O$991,'Daily Issuance'!$I$4:$I$991,$A40,'Daily Issuance'!$E$4:$E$991,"Non Inventory",'Daily Issuance'!$B$4:$B$991,">="&DATE(2026,7,1),'Daily Issuance'!$B$4:$B$991,"<"&DATE(2026,8,1)),0) -> 0 | N40: =IFERROR(SUMIFS('Daily Issuance'!$O$4:$O$991,'Daily Issuance'!$I$4:$I$991,$A40,'Daily Issuance'!$E$4:$E$991,"Services",'Daily Issuance'!$B$4:$B$991,">="&DATE(2026,7,1),'Daily Issuance'!$B$4:$B$991,"<"&DATE(2026,8,1)),0) -> 0 | O40: =IFERROR(SUMIFS('Daily Issuance'!$O:$O,'Daily Issuance'!$I:$I,$A40,'Daily Issuance'!$E:$E,"Patty Cash",'Daily Issuance'!$B:$B,">="&DATE(2026,7,1),'Daily Issuance'!$B:$B,"<"&DATE(2026,8,1)),0) -> 0 | P40: =SUM(L40:O40) -> 0 | Q40: =IFERROR(SUMIFS('Daily Issuance'!$O$4:$O$991,'Daily Issuance'!$I$4:$I$991,$A40,'Daily Issuance'!$E$4:$E$991,"Inventory",'Daily Issuance'!$B$4:$B$991,">="&DATE(2026,8,1),'Daily Issuance'!$B$4:$B$991,"<"&DATE(2026,9,1)),0) -> 0 | R40: =IFERROR(SUMIFS('Daily Issuance'!$O$4:$O$991,'Daily Issuance'!$I$4:$I$991,$A40,'Daily Issuance'!$E$4:$E$991,"Non Inventory",'Daily Issuance'!$B$4:$B$991,">="&DATE(2026,8,1),'Daily Issuance'!$B$4:$B$991,"<"&DATE(2026,9,1)),0) -> 0 | S40: =IFERROR(SUMIFS('Daily Issuance'!$O$4:$O$991,'Daily Issuance'!$I$4:$I$991,$A40,'Daily Issuance'!$E$4:$E$991,"Services",'Daily Issuance'!$B$4:$B$991,">="&DATE(2026,8,1),'Daily Issuance'!$B$4:$B$991,"<"&DATE(2026,9,1)),0) -> 0 | T40: =IFERROR(SUMIFS('Daily Issuance'!$O:$O,'Daily Issuance'!$I:$I,$A40,'Daily Issuance'!$E:$E,"Patty Cash",'Daily Issuance'!$B:$B,">="&DATE(2026,8,1),'Daily Issuance'!$B:$B,"<"&DATE(2026,9,1)),0) -> 0 | U40: =SUM(Q40:T40) -> 0 | V40: =IFERROR(SUMIFS('Daily Issuance'!$O$4:$O$991,'Daily Issuance'!$I$4:$I$991,$A40,'Daily Issuance'!$E$4:$E$991,"Inventory",'Daily Issuance'!$B$4:$B$991,">="&DATE(2026,9,1),'Daily Issuance'!$B$4:$B$991,"<"&DATE(2026,10,1)),0) -> 0 | W40: =IFERROR(SUMIFS('Daily Issuance'!$O$4:$O$991,'Daily Issuance'!$I$4:$I$991,$A40,'Daily Issuance'!$E$4:$E$991,"Non Inventory",'Daily Issuance'!$B$4:$B$991,">="&DATE(2026,9,1),'Daily Issuance'!$B$4:$B$991,"<"&DATE(2026,10,1)),0) -> 0 | X40: =IFERROR(SUMIFS('Daily Issuance'!$O$4:$O$991,'Daily Issuance'!$I$4:$I$991,$A40,'Daily Issuance'!$E$4:$E$991,"Services",'Daily Issuance'!$B$4:$B$991,">="&DATE(2026,9,1),'Daily Issuance'!$B$4:$B$991,"<"&DATE(2026,10,1)),0) -> 0 | Y40: =IFERROR(SUMIFS('Daily Issuance'!$O:$O,'Daily Issuance'!$I:$I,$A40,'Daily Issuance'!$E:$E,"Patty Cash",'Daily Issuance'!$B:$B,">="&DATE(2026,9,1),'Daily Issuance'!$B:$B,"<"&DATE(2026,10,1)),0) -> 0 | Z40: =SUM(V40:Y40) -> 0 | AA40: =IFERROR(SUMIFS('Daily Issuance'!$O$4:$O$991,'Daily Issuance'!$I$4:$I$991,$A40,'Daily Issuance'!$E$4:$E$991,"Inventory",'Daily Issuance'!$B$4:$B$991,">="&DATE(2026,10,1),'Daily Issuance'!$B$4:$B$991,"<"&DATE(2026,11,1)),0) -> 0 | AB40: =IFERROR(SUMIFS('Daily Issuance'!$O$4:$O$991,'Daily Issuance'!$I$4:$I$991,$A40,'Daily Issuance'!$E$4:$E$991,"Non Inventory",'Daily Issuance'!$B$4:$B$991,">="&DATE(2026,10,1),'Daily Issuance'!$B$4:$B$991,"<"&DATE(2026,11,1)),0) -> 0 | AC40: =IFERROR(SUMIFS('Daily Issuance'!$O$4:$O$991,'Daily Issuance'!$I$4:$I$991,$A40,'Daily Issuance'!$E$4:$E$991,"Services",'Daily Issuance'!$B$4:$B$991,">="&DATE(2026,10,1),'Daily Issuance'!$B$4:$B$991,"<"&DATE(2026,11,1)),0) -> 0 | AD40: =IFERROR(SUMIFS('Daily Issuance'!$O:$O,'Daily Issuance'!$I:$I,$A40,'Daily Issuance'!$E:$E,"Patty Cash",'Daily Issuance'!$B:$B,">="&DATE(2026,10,1),'Daily Issuance'!$B:$B,"<"&DATE(2026,11,1)),0) -> 0 | AE40: =SUM(AA40:AD40) -> 0 | AF40: =IFERROR(SUMIFS('Daily Issuance'!$O$4:$O$991,'Daily Issuance'!$I$4:$I$991,$A40,'Daily Issuance'!$E$4:$E$991,"Inventory",'Daily Issuance'!$B$4:$B$991,">="&DATE(2026,11,1),'Daily Issuance'!$B$4:$B$991,"<"&DATE(2026,12,1)),0) -> 0 | AG40: =IFERROR(SUMIFS('Daily Issuance'!$O$4:$O$991,'Daily Issuance'!$I$4:$I$991,$A40,'Daily Issuance'!$E$4:$E$991,"Non Inventory",'Daily Issuance'!$B$4:$B$991,">="&DATE(2026,11,1),'Daily Issuance'!$B$4:$B$991,"<"&DATE(2026,12,1)),0) -> 0 | AH40: =IFERROR(SUMIFS('Daily Issuance'!$O$4:$O$991,'Daily Issuance'!$I$4:$I$991,$A40,'Daily Issuance'!$E$4:$E$991,"Services",'Daily Issuance'!$B$4:$B$991,">="&DATE(2026,11,1),'Daily Issuance'!$B$4:$B$991,"<"&DATE(2026,12,1)),0) -> 0 | AI40: =IFERROR(SUMIFS('Daily Issuance'!$O:$O,'Daily Issuance'!$I:$I,$A40,'Daily Issuance'!$E:$E,"Patty Cash",'Daily Issuance'!$B:$B,">="&DATE(2026,11,1),'Daily Issuance'!$B:$B,"<"&DATE(2026,12,1)),0) -> 0 | AJ40: =SUM(AF40:AI40) -> 0 | AK40: =IFERROR(SUMIFS('Daily Issuance'!$O$4:$O$991,'Daily Issuance'!$I$4:$I$991,$A40,'Daily Issuance'!$E$4:$E$991,"Inventory",'Daily Issuance'!$B$4:$B$991,">="&DATE(2026,12,1),'Daily Issuance'!$B$4:$B$991,"<"&DATE(2027,1,1)),0) -> 0 | AL40: =IFERROR(SUMIFS('Daily Issuance'!$O$4:$O$991,'Daily Issuance'!$I$4:$I$991,$A40,'Daily Issuance'!$E$4:$E$991,"Non Inventory",'Daily Issuance'!$B$4:$B$991,">="&DATE(2026,12,1),'Daily Issuance'!$B$4:$B$991,"<"&DATE(2027,1,1)),0) -> 0 | AM40: =IFERROR(SUMIFS('Daily Issuance'!$O$4:$O$991,'Daily Issuance'!$I$4:$I$991,$A40,'Daily Issuance'!$E$4:$E$991,"Services",'Daily Issuance'!$B$4:$B$991,">="&DATE(2026,12,1),'Daily Issuance'!$B$4:$B$991,"<"&DATE(2027,1,1)),0) -> 0 | AN40: =IFERROR(SUMIFS('Daily Issuance'!$O:$O,'Daily Issuance'!$I:$I,$A40,'Daily Issuance'!$E:$E,"Patty Cash",'Daily Issuance'!$B:$B,">="&DATE(2026,12,1),'Daily Issuance'!$B:$B,"<"&DATE(2027,1,1)),0) -> 0 | AO40: =SUM(AK40:AN40) -> 0 | AP40: =SUM(F40,K40,P40,U40,Z40,AE40,AJ40,AO40) -> 134233
A41: Workshop | B41: =IFERROR(SUMIFS('Daily Issuance'!$O:$O,'Daily Issuance'!$I:$I,$A41,'Daily Issuance'!$E:$E,"Inventory",'Daily Issuance'!$B:$B,">="&DATE(2026,5,1),'Daily Issuance'!$B:$B,"<"&DATE(2026,6,1)),0) -> 0 | C41: =IFERROR(SUMIFS('Daily Issuance'!$O:$O,'Daily Issuance'!$I:$I,$A41,'Daily Issuance'!$E:$E,"Non Inventory",'Daily Issuance'!$B:$B,">="&DATE(2026,5,1),'Daily Issuance'!$B:$B,"<"&DATE(2026,6,1)),0) -> 1010 | D41: =IFERROR(SUMIFS('Daily Issuance'!$O:$O,'Daily Issuance'!$I:$I,$A41,'Daily Issuance'!$E:$E,"Services",'Daily Issuance'!$B:$B,">="&DATE(2026,5,1),'Daily Issuance'!$B:$B,"<"&DATE(2026,6,1)),0) -> 0 | E41: =IFERROR(SUMIFS('Daily Issuance'!$O:$O,'Daily Issuance'!$I:$I,$A41,'Daily Issuance'!$E:$E,"Patty Cash",'Daily Issuance'!$B:$B,">="&DATE(2026,5,1),'Daily Issuance'!$B:$B,"<"&DATE(2026,6,1)),0) -> 0 | F41: =SUM(B41:E41) -> 1010 | G41: =IFERROR(SUMIFS('Daily Issuance'!$O$4:$O$991,'Daily Issuance'!$I$4:$I$991,$A41,'Daily Issuance'!$E$4:$E$991,"Inventory",'Daily Issuance'!$B$4:$B$991,">="&DATE(2026,6,1),'Daily Issuance'!$B$4:$B$991,"<"&DATE(2026,7,1)),0) -> 0 | H41: =IFERROR(SUMIFS('Daily Issuance'!$O$4:$O$991,'Daily Issuance'!$I$4:$I$991,$A41,'Daily Issuance'!$E$4:$E$991,"Non Inventory",'Daily Issuance'!$B$4:$B$991,">="&DATE(2026,6,1),'Daily Issuance'!$B$4:$B$991,"<"&DATE(2026,7,1)),0) -> 0 | I41: =IFERROR(SUMIFS('Daily Issuance'!$O$4:$O$991,'Daily Issuance'!$I$4:$I$991,$A41,'Daily Issuance'!$E$4:$E$991,"Services",'Daily Issuance'!$B$4:$B$991,">="&DATE(2026,6,1),'Daily Issuance'!$B$4:$B$991,"<"&DATE(2026,7,1)),0) -> 0 | J41: =IFERROR(SUMIFS('Daily Issuance'!$O:$O,'Daily Issuance'!$I:$I,$A41,'Daily Issuance'!$E:$E,"Patty Cash",'Daily Issuance'!$B:$B,">="&DATE(2026,6,1),'Daily Issuance'!$B:$B,"<"&DATE(2026,7,1)),0) -> 0 | K41: =SUM(G41:J41) -> 0 | L41: =IFERROR(SUMIFS('Daily Issuance'!$O$4:$O$991,'Daily Issuance'!$I$4:$I$991,$A41,'Daily Issuance'!$E$4:$E$991,"Inventory",'Daily Issuance'!$B$4:$B$991,">="&DATE(2026,7,1),'Daily Issuance'!$B$4:$B$991,"<"&DATE(2026,8,1)),0) -> 0 | M41: =IFERROR(SUMIFS('Daily Issuance'!$O$4:$O$991,'Daily Issuance'!$I$4:$I$991,$A41,'Daily Issuance'!$E$4:$E$991,"Non Inventory",'Daily Issuance'!$B$4:$B$991,">="&DATE(2026,7,1),'Daily Issuance'!$B$4:$B$991,"<"&DATE(2026,8,1)),0) -> 0 | N41: =IFERROR(SUMIFS('Daily Issuance'!$O$4:$O$991,'Daily Issuance'!$I$4:$I$991,$A41,'Daily Issuance'!$E$4:$E$991,"Services",'Daily Issuance'!$B$4:$B$991,">="&DATE(2026,7,1),'Daily Issuance'!$B$4:$B$991,"<"&DATE(2026,8,1)),0) -> 0 | O41: =IFERROR(SUMIFS('Daily Issuance'!$O:$O,'Daily Issuance'!$I:$I,$A41,'Daily Issuance'!$E:$E,"Patty Cash",'Daily Issuance'!$B:$B,">="&DATE(2026,7,1),'Daily Issuance'!$B:$B,"<"&DATE(2026,8,1)),0) -> 0 | P41: =SUM(L41:O41) -> 0 | Q41: =IFERROR(SUMIFS('Daily Issuance'!$O$4:$O$991,'Daily Issuance'!$I$4:$I$991,$A41,'Daily Issuance'!$E$4:$E$991,"Inventory",'Daily Issuance'!$B$4:$B$991,">="&DATE(2026,8,1),'Daily Issuance'!$B$4:$B$991,"<"&DATE(2026,9,1)),0) -> 0 | R41: =IFERROR(SUMIFS('Daily Issuance'!$O$4:$O$991,'Daily Issuance'!$I$4:$I$991,$A41,'Daily Issuance'!$E$4:$E$991,"Non Inventory",'Daily Issuance'!$B$4:$B$991,">="&DATE(2026,8,1),'Daily Issuance'!$B$4:$B$991,"<"&DATE(2026,9,1)),0) -> 0 | S41: =IFERROR(SUMIFS('Daily Issuance'!$O$4:$O$991,'Daily Issuance'!$I$4:$I$991,$A41,'Daily Issuance'!$E$4:$E$991,"Services",'Daily Issuance'!$B$4:$B$991,">="&DATE(2026,8,1),'Daily Issuance'!$B$4:$B$991,"<"&DATE(2026,9,1)),0) -> 0 | T41: =IFERROR(SUMIFS('Daily Issuance'!$O:$O,'Daily Issuance'!$I:$I,$A41,'Daily Issuance'!$E:$E,"Patty Cash",'Daily Issuance'!$B:$B,">="&DATE(2026,8,1),'Daily Issuance'!$B:$B,"<"&DATE(2026,9,1)),0) -> 0 | U41: =SUM(Q41:T41) -> 0 | V41: =IFERROR(SUMIFS('Daily Issuance'!$O$4:$O$991,'Daily Issuance'!$I$4:$I$991,$A41,'Daily Issuance'!$E$4:$E$991,"Inventory",'Daily Issuance'!$B$4:$B$991,">="&DATE(2026,9,1),'Daily Issuance'!$B$4:$B$991,"<"&DATE(2026,10,1)),0) -> 0 | W41: =IFERROR(SUMIFS('Daily Issuance'!$O$4:$O$991,'Daily Issuance'!$I$4:$I$991,$A41,'Daily Issuance'!$E$4:$E$991,"Non Inventory",'Daily Issuance'!$B$4:$B$991,">="&DATE(2026,9,1),'Daily Issuance'!$B$4:$B$991,"<"&DATE(2026,10,1)),0) -> 0 | X41: =IFERROR(SUMIFS('Daily Issuance'!$O$4:$O$991,'Daily Issuance'!$I$4:$I$991,$A41,'Daily Issuance'!$E$4:$E$991,"Services",'Daily Issuance'!$B$4:$B$991,">="&DATE(2026,9,1),'Daily Issuance'!$B$4:$B$991,"<"&DATE(2026,10,1)),0) -> 0 | Y41: =IFERROR(SUMIFS('Daily Issuance'!$O:$O,'Daily Issuance'!$I:$I,$A41,'Daily Issuance'!$E:$E,"Patty Cash",'Daily Issuance'!$B:$B,">="&DATE(2026,9,1),'Daily Issuance'!$B:$B,"<"&DATE(2026,10,1)),0) -> 0 | Z41: =SUM(V41:Y41) -> 0 | AA41: =IFERROR(SUMIFS('Daily Issuance'!$O$4:$O$991,'Daily Issuance'!$I$4:$I$991,$A41,'Daily Issuance'!$E$4:$E$991,"Inventory",'Daily Issuance'!$B$4:$B$991,">="&DATE(2026,10,1),'Daily Issuance'!$B$4:$B$991,"<"&DATE(2026,11,1)),0) -> 0 | AB41: =IFERROR(SUMIFS('Daily Issuance'!$O$4:$O$991,'Daily Issuance'!$I$4:$I$991,$A41,'Daily Issuance'!$E$4:$E$991,"Non Inventory",'Daily Issuance'!$B$4:$B$991,">="&DATE(2026,10,1),'Daily Issuance'!$B$4:$B$991,"<"&DATE(2026,11,1)),0) -> 0 | AC41: =IFERROR(SUMIFS('Daily Issuance'!$O$4:$O$991,'Daily Issuance'!$I$4:$I$991,$A41,'Daily Issuance'!$E$4:$E$991,"Services",'Daily Issuance'!$B$4:$B$991,">="&DATE(2026,10,1),'Daily Issuance'!$B$4:$B$991,"<"&DATE(2026,11,1)),0) -> 0 | AD41: =IFERROR(SUMIFS('Daily Issuance'!$O:$O,'Daily Issuance'!$I:$I,$A41,'Daily Issuance'!$E:$E,"Patty Cash",'Daily Issuance'!$B:$B,">="&DATE(2026,10,1),'Daily Issuance'!$B:$B,"<"&DATE(2026,11,1)),0) -> 0 | AE41: =SUM(AA41:AD41) -> 0 | AF41: =IFERROR(SUMIFS('Daily Issuance'!$O$4:$O$991,'Daily Issuance'!$I$4:$I$991,$A41,'Daily Issuance'!$E$4:$E$991,"Inventory",'Daily Issuance'!$B$4:$B$991,">="&DATE(2026,11,1),'Daily Issuance'!$B$4:$B$991,"<"&DATE(2026,12,1)),0) -> 0 | AG41: =IFERROR(SUMIFS('Daily Issuance'!$O$4:$O$991,'Daily Issuance'!$I$4:$I$991,$A41,'Daily Issuance'!$E$4:$E$991,"Non Inventory",'Daily Issuance'!$B$4:$B$991,">="&DATE(2026,11,1),'Daily Issuance'!$B$4:$B$991,"<"&DATE(2026,12,1)),0) -> 0 | AH41: =IFERROR(SUMIFS('Daily Issuance'!$O$4:$O$991,'Daily Issuance'!$I$4:$I$991,$A41,'Daily Issuance'!$E$4:$E$991,"Services",'Daily Issuance'!$B$4:$B$991,">="&DATE(2026,11,1),'Daily Issuance'!$B$4:$B$991,"<"&DATE(2026,12,1)),0) -> 0 | AI41: =IFERROR(SUMIFS('Daily Issuance'!$O:$O,'Daily Issuance'!$I:$I,$A41,'Daily Issuance'!$E:$E,"Patty Cash",'Daily Issuance'!$B:$B,">="&DATE(2026,11,1),'Daily Issuance'!$B:$B,"<"&DATE(2026,12,1)),0) -> 0 | AJ41: =SUM(AF41:AI41) -> 0 | AK41: =IFERROR(SUMIFS('Daily Issuance'!$O$4:$O$991,'Daily Issuance'!$I$4:$I$991,$A41,'Daily Issuance'!$E$4:$E$991,"Inventory",'Daily Issuance'!$B$4:$B$991,">="&DATE(2026,12,1),'Daily Issuance'!$B$4:$B$991,"<"&DATE(2027,1,1)),0) -> 0 | AL41: =IFERROR(SUMIFS('Daily Issuance'!$O$4:$O$991,'Daily Issuance'!$I$4:$I$991,$A41,'Daily Issuance'!$E$4:$E$991,"Non Inventory",'Daily Issuance'!$B$4:$B$991,">="&DATE(2026,12,1),'Daily Issuance'!$B$4:$B$991,"<"&DATE(2027,1,1)),0) -> 0 | AM41: =IFERROR(SUMIFS('Daily Issuance'!$O$4:$O$991,'Daily Issuance'!$I$4:$I$991,$A41,'Daily Issuance'!$E$4:$E$991,"Services",'Daily Issuance'!$B$4:$B$991,">="&DATE(2026,12,1),'Daily Issuance'!$B$4:$B$991,"<"&DATE(2027,1,1)),0) -> 0 | AN41: =IFERROR(SUMIFS('Daily Issuance'!$O:$O,'Daily Issuance'!$I:$I,$A41,'Daily Issuance'!$E:$E,"Patty Cash",'Daily Issuance'!$B:$B,">="&DATE(2026,12,1),'Daily Issuance'!$B:$B,"<"&DATE(2027,1,1)),0) -> 0 | AO41: =SUM(AK41:AN41) -> 0 | AP41: =SUM(F41,K41,P41,U41,Z41,AE41,AJ41,AO41) -> 1010
A42: Laesse Plant | B42: =IFERROR(SUMIFS('Daily Issuance'!$O:$O,'Daily Issuance'!$I:$I,$A42,'Daily Issuance'!$E:$E,"Inventory",'Daily Issuance'!$B:$B,">="&DATE(2026,5,1),'Daily Issuance'!$B:$B,"<"&DATE(2026,6,1)),0) -> 750 | C42: =IFERROR(SUMIFS('Daily Issuance'!$O:$O,'Daily Issuance'!$I:$I,$A42,'Daily Issuance'!$E:$E,"Non Inventory",'Daily Issuance'!$B:$B,">="&DATE(2026,5,1),'Daily Issuance'!$B:$B,"<"&DATE(2026,6,1)),0) -> 141636 | D42: =IFERROR(SUMIFS('Daily Issuance'!$O:$O,'Daily Issuance'!$I:$I,$A42,'Daily Issuance'!$E:$E,"Services",'Daily Issuance'!$B:$B,">="&DATE(2026,5,1),'Daily Issuance'!$B:$B,"<"&DATE(2026,6,1)),0) -> 0 | E42: =IFERROR(SUMIFS('Daily Issuance'!$O:$O,'Daily Issuance'!$I:$I,$A42,'Daily Issuance'!$E:$E,"Patty Cash",'Daily Issuance'!$B:$B,">="&DATE(2026,5,1),'Daily Issuance'!$B:$B,"<"&DATE(2026,6,1)),0) -> 0 | F42: =SUM(B42:E42) -> 142386 | G42: =IFERROR(SUMIFS('Daily Issuance'!$O$4:$O$991,'Daily Issuance'!$I$4:$I$991,$A42,'Daily Issuance'!$E$4:$E$991,"Inventory",'Daily Issuance'!$B$4:$B$991,">="&DATE(2026,6,1),'Daily Issuance'!$B$4:$B$991,"<"&DATE(2026,7,1)),0) -> 0 | H42: =IFERROR(SUMIFS('Daily Issuance'!$O$4:$O$991,'Daily Issuance'!$I$4:$I$991,$A42,'Daily Issuance'!$E$4:$E$991,"Non Inventory",'Daily Issuance'!$B$4:$B$991,">="&DATE(2026,6,1),'Daily Issuance'!$B$4:$B$991,"<"&DATE(2026,7,1)),0) -> 0 | I42: =IFERROR(SUMIFS('Daily Issuance'!$O$4:$O$991,'Daily Issuance'!$I$4:$I$991,$A42,'Daily Issuance'!$E$4:$E$991,"Services",'Daily Issuance'!$B$4:$B$991,">="&DATE(2026,6,1),'Daily Issuance'!$B$4:$B$991,"<"&DATE(2026,7,1)),0) -> 0 | J42: =IFERROR(SUMIFS('Daily Issuance'!$O:$O,'Daily Issuance'!$I:$I,$A42,'Daily Issuance'!$E:$E,"Patty Cash",'Daily Issuance'!$B:$B,">="&DATE(2026,6,1),'Daily Issuance'!$B:$B,"<"&DATE(2026,7,1)),0) -> 0 | K42: =SUM(G42:J42) -> 0 | L42: =IFERROR(SUMIFS('Daily Issuance'!$O$4:$O$991,'Daily Issuance'!$I$4:$I$991,$A42,'Daily Issuance'!$E$4:$E$991,"Inventory",'Daily Issuance'!$B$4:$B$991,">="&DATE(2026,7,1),'Daily Issuance'!$B$4:$B$991,"<"&DATE(2026,8,1)),0) -> 0 | M42: =IFERROR(SUMIFS('Daily Issuance'!$O$4:$O$991,'Daily Issuance'!$I$4:$I$991,$A42,'Daily Issuance'!$E$4:$E$991,"Non Inventory",'Daily Issuance'!$B$4:$B$991,">="&DATE(2026,7,1),'Daily Issuance'!$B$4:$B$991,"<"&DATE(2026,8,1)),0) -> 0 | N42: =IFERROR(SUMIFS('Daily Issuance'!$O$4:$O$991,'Daily Issuance'!$I$4:$I$991,$A42,'Daily Issuance'!$E$4:$E$991,"Services",'Daily Issuance'!$B$4:$B$991,">="&DATE(2026,7,1),'Daily Issuance'!$B$4:$B$991,"<"&DATE(2026,8,1)),0) -> 0 | O42: =IFERROR(SUMIFS('Daily Issuance'!$O:$O,'Daily Issuance'!$I:$I,$A42,'Daily Issuance'!$E:$E,"Patty Cash",'Daily Issuance'!$B:$B,">="&DATE(2026,7,1),'Daily Issuance'!$B:$B,"<"&DATE(2026,8,1)),0) -> 0 | P42: =SUM(L42:O42) -> 0 | Q42: =IFERROR(SUMIFS('Daily Issuance'!$O$4:$O$991,'Daily Issuance'!$I$4:$I$991,$A42,'Daily Issuance'!$E$4:$E$991,"Inventory",'Daily Issuance'!$B$4:$B$991,">="&DATE(2026,8,1),'Daily Issuance'!$B$4:$B$991,"<"&DATE(2026,9,1)),0) -> 0 | R42: =IFERROR(SUMIFS('Daily Issuance'!$O$4:$O$991,'Daily Issuance'!$I$4:$I$991,$A42,'Daily Issuance'!$E$4:$E$991,"Non Inventory",'Daily Issuance'!$B$4:$B$991,">="&DATE(2026,8,1),'Daily Issuance'!$B$4:$B$991,"<"&DATE(2026,9,1)),0) -> 0 | S42: =IFERROR(SUMIFS('Daily Issuance'!$O$4:$O$991,'Daily Issuance'!$I$4:$I$991,$A42,'Daily Issuance'!$E$4:$E$991,"Services",'Daily Issuance'!$B$4:$B$991,">="&DATE(2026,8,1),'Daily Issuance'!$B$4:$B$991,"<"&DATE(2026,9,1)),0) -> 0 | T42: =IFERROR(SUMIFS('Daily Issuance'!$O:$O,'Daily Issuance'!$I:$I,$A42,'Daily Issuance'!$E:$E,"Patty Cash",'Daily Issuance'!$B:$B,">="&DATE(2026,8,1),'Daily Issuance'!$B:$B,"<"&DATE(2026,9,1)),0) -> 0 | U42: =SUM(Q42:T42) -> 0 | V42: =IFERROR(SUMIFS('Daily Issuance'!$O$4:$O$991,'Daily Issuance'!$I$4:$I$991,$A42,'Daily Issuance'!$E$4:$E$991,"Inventory",'Daily Issuance'!$B$4:$B$991,">="&DATE(2026,9,1),'Daily Issuance'!$B$4:$B$991,"<"&DATE(2026,10,1)),0) -> 0 | W42: =IFERROR(SUMIFS('Daily Issuance'!$O$4:$O$991,'Daily Issuance'!$I$4:$I$991,$A42,'Daily Issuance'!$E$4:$E$991,"Non Inventory",'Daily Issuance'!$B$4:$B$991,">="&DATE(2026,9,1),'Daily Issuance'!$B$4:$B$991,"<"&DATE(2026,10,1)),0) -> 0 | X42: =IFERROR(SUMIFS('Daily Issuance'!$O$4:$O$991,'Daily Issuance'!$I$4:$I$991,$A42,'Daily Issuance'!$E$4:$E$991,"Services",'Daily Issuance'!$B$4:$B$991,">="&DATE(2026,9,1),'Daily Issuance'!$B$4:$B$991,"<"&DATE(2026,10,1)),0) -> 0 | Y42: =IFERROR(SUMIFS('Daily Issuance'!$O:$O,'Daily Issuance'!$I:$I,$A42,'Daily Issuance'!$E:$E,"Patty Cash",'Daily Issuance'!$B:$B,">="&DATE(2026,9,1),'Daily Issuance'!$B:$B,"<"&DATE(2026,10,1)),0) -> 0 | Z42: =SUM(V42:Y42) -> 0 | AA42: =IFERROR(SUMIFS('Daily Issuance'!$O$4:$O$991,'Daily Issuance'!$I$4:$I$991,$A42,'Daily Issuance'!$E$4:$E$991,"Inventory",'Daily Issuance'!$B$4:$B$991,">="&DATE(2026,10,1),'Daily Issuance'!$B$4:$B$991,"<"&DATE(2026,11,1)),0) -> 0 | AB42: =IFERROR(SUMIFS('Daily Issuance'!$O$4:$O$991,'Daily Issuance'!$I$4:$I$991,$A42,'Daily Issuance'!$E$4:$E$991,"Non Inventory",'Daily Issuance'!$B$4:$B$991,">="&DATE(2026,10,1),'Daily Issuance'!$B$4:$B$991,"<"&DATE(2026,11,1)),0) -> 0 | AC42: =IFERROR(SUMIFS('Daily Issuance'!$O$4:$O$991,'Daily Issuance'!$I$4:$I$991,$A42,'Daily Issuance'!$E$4:$E$991,"Services",'Daily Issuance'!$B$4:$B$991,">="&DATE(2026,10,1),'Daily Issuance'!$B$4:$B$991,"<"&DATE(2026,11,1)),0) -> 0 | AD42: =IFERROR(SUMIFS('Daily Issuance'!$O:$O,'Daily Issuance'!$I:$I,$A42,'Daily Issuance'!$E:$E,"Patty Cash",'Daily Issuance'!$B:$B,">="&DATE(2026,10,1),'Daily Issuance'!$B:$B,"<"&DATE(2026,11,1)),0) -> 0 | AE42: =SUM(AA42:AD42) -> 0 | AF42: =IFERROR(SUMIFS('Daily Issuance'!$O$4:$O$991,'Daily Issuance'!$I$4:$I$991,$A42,'Daily Issuance'!$E$4:$E$991,"Inventory",'Daily Issuance'!$B$4:$B$991,">="&DATE(2026,11,1),'Daily Issuance'!$B$4:$B$991,"<"&DATE(2026,12,1)),0) -> 0 | AG42: =IFERROR(SUMIFS('Daily Issuance'!$O$4:$O$991,'Daily Issuance'!$I$4:$I$991,$A42,'Daily Issuance'!$E$4:$E$991,"Non Inventory",'Daily Issuance'!$B$4:$B$991,">="&DATE(2026,11,1),'Daily Issuance'!$B$4:$B$991,"<"&DATE(2026,12,1)),0) -> 0 | AH42: =IFERROR(SUMIFS('Daily Issuance'!$O$4:$O$991,'Daily Issuance'!$I$4:$I$991,$A42,'Daily Issuance'!$E$4:$E$991,"Services",'Daily Issuance'!$B$4:$B$991,">="&DATE(2026,11,1),'Daily Issuance'!$B$4:$B$991,"<"&DATE(2026,12,1)),0) -> 0 | AI42: =IFERROR(SUMIFS('Daily Issuance'!$O:$O,'Daily Issuance'!$I:$I,$A42,'Daily Issuance'!$E:$E,"Patty Cash",'Daily Issuance'!$B:$B,">="&DATE(2026,11,1),'Daily Issuance'!$B:$B,"<"&DATE(2026,12,1)),0) -> 0 | AJ42: =SUM(AF42:AI42) -> 0 | AK42: =IFERROR(SUMIFS('Daily Issuance'!$O$4:$O$991,'Daily Issuance'!$I$4:$I$991,$A42,'Daily Issuance'!$E$4:$E$991,"Inventory",'Daily Issuance'!$B$4:$B$991,">="&DATE(2026,12,1),'Daily Issuance'!$B$4:$B$991,"<"&DATE(2027,1,1)),0) -> 0 | AL42: =IFERROR(SUMIFS('Daily Issuance'!$O$4:$O$991,'Daily Issuance'!$I$4:$I$991,$A42,'Daily Issuance'!$E$4:$E$991,"Non Inventory",'Daily Issuance'!$B$4:$B$991,">="&DATE(2026,12,1),'Daily Issuance'!$B$4:$B$991,"<"&DATE(2027,1,1)),0) -> 0 | AM42: =IFERROR(SUMIFS('Daily Issuance'!$O$4:$O$991,'Daily Issuance'!$I$4:$I$991,$A42,'Daily Issuance'!$E$4:$E$991,"Services",'Daily Issuance'!$B$4:$B$991,">="&DATE(2026,12,1),'Daily Issuance'!$B$4:$B$991,"<"&DATE(2027,1,1)),0) -> 0 | AN42: =IFERROR(SUMIFS('Daily Issuance'!$O:$O,'Daily Issuance'!$I:$I,$A42,'Daily Issuance'!$E:$E,"Patty Cash",'Daily Issuance'!$B:$B,">="&DATE(2026,12,1),'Daily Issuance'!$B:$B,"<"&DATE(2027,1,1)),0) -> 0 | AO42: =SUM(AK42:AN42) -> 0 | AP42: =SUM(F42,K42,P42,U42,Z42,AE42,AJ42,AO42) -> 142386
A43: Seasioning Pin Mall | B43: =IFERROR(SUMIFS('Daily Issuance'!$O:$O,'Daily Issuance'!$I:$I,$A43,'Daily Issuance'!$E:$E,"Inventory",'Daily Issuance'!$B:$B,">="&DATE(2026,5,1),'Daily Issuance'!$B:$B,"<"&DATE(2026,6,1)),0) -> 0 | C43: =IFERROR(SUMIFS('Daily Issuance'!$O:$O,'Daily Issuance'!$I:$I,$A43,'Daily Issuance'!$E:$E,"Non Inventory",'Daily Issuance'!$B:$B,">="&DATE(2026,5,1),'Daily Issuance'!$B:$B,"<"&DATE(2026,6,1)),0) -> 1100 | D43: =IFERROR(SUMIFS('Daily Issuance'!$O:$O,'Daily Issuance'!$I:$I,$A43,'Daily Issuance'!$E:$E,"Services",'Daily Issuance'!$B:$B,">="&DATE(2026,5,1),'Daily Issuance'!$B:$B,"<"&DATE(2026,6,1)),0) -> 0 | E43: =IFERROR(SUMIFS('Daily Issuance'!$O:$O,'Daily Issuance'!$I:$I,$A43,'Daily Issuance'!$E:$E,"Patty Cash",'Daily Issuance'!$B:$B,">="&DATE(2026,5,1),'Daily Issuance'!$B:$B,"<"&DATE(2026,6,1)),0) -> 1020 | F43: =SUM(B43:E43) -> 2120 | G43: =IFERROR(SUMIFS('Daily Issuance'!$O$4:$O$991,'Daily Issuance'!$I$4:$I$991,$A43,'Daily Issuance'!$E$4:$E$991,"Inventory",'Daily Issuance'!$B$4:$B$991,">="&DATE(2026,6,1),'Daily Issuance'!$B$4:$B$991,"<"&DATE(2026,7,1)),0) -> 0 | H43: =IFERROR(SUMIFS('Daily Issuance'!$O$4:$O$991,'Daily Issuance'!$I$4:$I$991,$A43,'Daily Issuance'!$E$4:$E$991,"Non Inventory",'Daily Issuance'!$B$4:$B$991,">="&DATE(2026,6,1),'Daily Issuance'!$B$4:$B$991,"<"&DATE(2026,7,1)),0) -> 12500 | I43: =IFERROR(SUMIFS('Daily Issuance'!$O$4:$O$991,'Daily Issuance'!$I$4:$I$991,$A43,'Daily Issuance'!$E$4:$E$991,"Services",'Daily Issuance'!$B$4:$B$991,">="&DATE(2026,6,1),'Daily Issuance'!$B$4:$B$991,"<"&DATE(2026,7,1)),0) -> 0 | J43: =IFERROR(SUMIFS('Daily Issuance'!$O:$O,'Daily Issuance'!$I:$I,$A43,'Daily Issuance'!$E:$E,"Patty Cash",'Daily Issuance'!$B:$B,">="&DATE(2026,6,1),'Daily Issuance'!$B:$B,"<"&DATE(2026,7,1)),0) -> 0 | K43: =SUM(G43:J43) -> 12500 | L43: =IFERROR(SUMIFS('Daily Issuance'!$O$4:$O$991,'Daily Issuance'!$I$4:$I$991,$A43,'Daily Issuance'!$E$4:$E$991,"Inventory",'Daily Issuance'!$B$4:$B$991,">="&DATE(2026,7,1),'Daily Issuance'!$B$4:$B$991,"<"&DATE(2026,8,1)),0) -> 0 | M43: =IFERROR(SUMIFS('Daily Issuance'!$O$4:$O$991,'Daily Issuance'!$I$4:$I$991,$A43,'Daily Issuance'!$E$4:$E$991,"Non Inventory",'Daily Issuance'!$B$4:$B$991,">="&DATE(2026,7,1),'Daily Issuance'!$B$4:$B$991,"<"&DATE(2026,8,1)),0) -> 0 | N43: =IFERROR(SUMIFS('Daily Issuance'!$O$4:$O$991,'Daily Issuance'!$I$4:$I$991,$A43,'Daily Issuance'!$E$4:$E$991,"Services",'Daily Issuance'!$B$4:$B$991,">="&DATE(2026,7,1),'Daily Issuance'!$B$4:$B$991,"<"&DATE(2026,8,1)),0) -> 0 | O43: =IFERROR(SUMIFS('Daily Issuance'!$O:$O,'Daily Issuance'!$I:$I,$A43,'Daily Issuance'!$E:$E,"Patty Cash",'Daily Issuance'!$B:$B,">="&DATE(2026,7,1),'Daily Issuance'!$B:$B,"<"&DATE(2026,8,1)),0) -> 0 | P43: =SUM(L43:O43) -> 0 | Q43: =IFERROR(SUMIFS('Daily Issuance'!$O$4:$O$991,'Daily Issuance'!$I$4:$I$991,$A43,'Daily Issuance'!$E$4:$E$991,"Inventory",'Daily Issuance'!$B$4:$B$991,">="&DATE(2026,8,1),'Daily Issuance'!$B$4:$B$991,"<"&DATE(2026,9,1)),0) -> 0 | R43: =IFERROR(SUMIFS('Daily Issuance'!$O$4:$O$991,'Daily Issuance'!$I$4:$I$991,$A43,'Daily Issuance'!$E$4:$E$991,"Non Inventory",'Daily Issuance'!$B$4:$B$991,">="&DATE(2026,8,1),'Daily Issuance'!$B$4:$B$991,"<"&DATE(2026,9,1)),0) -> 0 | S43: =IFERROR(SUMIFS('Daily Issuance'!$O$4:$O$991,'Daily Issuance'!$I$4:$I$991,$A43,'Daily Issuance'!$E$4:$E$991,"Services",'Daily Issuance'!$B$4:$B$991,">="&DATE(2026,8,1),'Daily Issuance'!$B$4:$B$991,"<"&DATE(2026,9,1)),0) -> 0 | T43: =IFERROR(SUMIFS('Daily Issuance'!$O:$O,'Daily Issuance'!$I:$I,$A43,'Daily Issuance'!$E:$E,"Patty Cash",'Daily Issuance'!$B:$B,">="&DATE(2026,8,1),'Daily Issuance'!$B:$B,"<"&DATE(2026,9,1)),0) -> 0 | U43: =SUM(Q43:T43) -> 0 | V43: =IFERROR(SUMIFS('Daily Issuance'!$O$4:$O$991,'Daily Issuance'!$I$4:$I$991,$A43,'Daily Issuance'!$E$4:$E$991,"Inventory",'Daily Issuance'!$B$4:$B$991,">="&DATE(2026,9,1),'Daily Issuance'!$B$4:$B$991,"<"&DATE(2026,10,1)),0) -> 0 | W43: =IFERROR(SUMIFS('Daily Issuance'!$O$4:$O$991,'Daily Issuance'!$I$4:$I$991,$A43,'Daily Issuance'!$E$4:$E$991,"Non Inventory",'Daily Issuance'!$B$4:$B$991,">="&DATE(2026,9,1),'Daily Issuance'!$B$4:$B$991,"<"&DATE(2026,10,1)),0) -> 0 | X43: =IFERROR(SUMIFS('Daily Issuance'!$O$4:$O$991,'Daily Issuance'!$I$4:$I$991,$A43,'Daily Issuance'!$E$4:$E$991,"Services",'Daily Issuance'!$B$4:$B$991,">="&DATE(2026,9,1),'Daily Issuance'!$B$4:$B$991,"<"&DATE(2026,10,1)),0) -> 0 | Y43: =IFERROR(SUMIFS('Daily Issuance'!$O:$O,'Daily Issuance'!$I:$I,$A43,'Daily Issuance'!$E:$E,"Patty Cash",'Daily Issuance'!$B:$B,">="&DATE(2026,9,1),'Daily Issuance'!$B:$B,"<"&DATE(2026,10,1)),0) -> 0 | Z43: =SUM(V43:Y43) -> 0 | AA43: =IFERROR(SUMIFS('Daily Issuance'!$O$4:$O$991,'Daily Issuance'!$I$4:$I$991,$A43,'Daily Issuance'!$E$4:$E$991,"Inventory",'Daily Issuance'!$B$4:$B$991,">="&DATE(2026,10,1),'Daily Issuance'!$B$4:$B$991,"<"&DATE(2026,11,1)),0) -> 0 | AB43: =IFERROR(SUMIFS('Daily Issuance'!$O$4:$O$991,'Daily Issuance'!$I$4:$I$991,$A43,'Daily Issuance'!$E$4:$E$991,"Non Inventory",'Daily Issuance'!$B$4:$B$991,">="&DATE(2026,10,1),'Daily Issuance'!$B$4:$B$991,"<"&DATE(2026,11,1)),0) -> 0 | AC43: =IFERROR(SUMIFS('Daily Issuance'!$O$4:$O$991,'Daily Issuance'!$I$4:$I$991,$A43,'Daily Issuance'!$E$4:$E$991,"Services",'Daily Issuance'!$B$4:$B$991,">="&DATE(2026,10,1),'Daily Issuance'!$B$4:$B$991,"<"&DATE(2026,11,1)),0) -> 0 | AD43: =IFERROR(SUMIFS('Daily Issuance'!$O:$O,'Daily Issuance'!$I:$I,$A43,'Daily Issuance'!$E:$E,"Patty Cash",'Daily Issuance'!$B:$B,">="&DATE(2026,10,1),'Daily Issuance'!$B:$B,"<"&DATE(2026,11,1)),0) -> 0 | AE43: =SUM(AA43:AD43) -> 0 | AF43: =IFERROR(SUMIFS('Daily Issuance'!$O$4:$O$991,'Daily Issuance'!$I$4:$I$991,$A43,'Daily Issuance'!$E$4:$E$991,"Inventory",'Daily Issuance'!$B$4:$B$991,">="&DATE(2026,11,1),'Daily Issuance'!$B$4:$B$991,"<"&DATE(2026,12,1)),0) -> 0 | AG43: =IFERROR(SUMIFS('Daily Issuance'!$O$4:$O$991,'Daily Issuance'!$I$4:$I$991,$A43,'Daily Issuance'!$E$4:$E$991,"Non Inventory",'Daily Issuance'!$B$4:$B$991,">="&DATE(2026,11,1),'Daily Issuance'!$B$4:$B$991,"<"&DATE(2026,12,1)),0) -> 0 | AH43: =IFERROR(SUMIFS('Daily Issuance'!$O$4:$O$991,'Daily Issuance'!$I$4:$I$991,$A43,'Daily Issuance'!$E$4:$E$991,"Services",'Daily Issuance'!$B$4:$B$991,">="&DATE(2026,11,1),'Daily Issuance'!$B$4:$B$991,"<"&DATE(2026,12,1)),0) -> 0 | AI43: =IFERROR(SUMIFS('Daily Issuance'!$O:$O,'Daily Issuance'!$I:$I,$A43,'Daily Issuance'!$E:$E,"Patty Cash",'Daily Issuance'!$B:$B,">="&DATE(2026,11,1),'Daily Issuance'!$B:$B,"<"&DATE(2026,12,1)),0) -> 0 | AJ43: =SUM(AF43:AI43) -> 0 | AK43: =IFERROR(SUMIFS('Daily Issuance'!$O$4:$O$991,'Daily Issuance'!$I$4:$I$991,$A43,'Daily Issuance'!$E$4:$E$991,"Inventory",'Daily Issuance'!$B$4:$B$991,">="&DATE(2026,12,1),'Daily Issuance'!$B$4:$B$991,"<"&DATE(2027,1,1)),0) -> 0 | AL43: =IFERROR(SUMIFS('Daily Issuance'!$O$4:$O$991,'Daily Issuance'!$I$4:$I$991,$A43,'Daily Issuance'!$E$4:$E$991,"Non Inventory",'Daily Issuance'!$B$4:$B$991,">="&DATE(2026,12,1),'Daily Issuance'!$B$4:$B$991,"<"&DATE(2027,1,1)),0) -> 0 | AM43: =IFERROR(SUMIFS('Daily Issuance'!$O$4:$O$991,'Daily Issuance'!$I$4:$I$991,$A43,'Daily Issuance'!$E$4:$E$991,"Services",'Daily Issuance'!$B$4:$B$991,">="&DATE(2026,12,1),'Daily Issuance'!$B$4:$B$991,"<"&DATE(2027,1,1)),0) -> 0 | AN43: =IFERROR(SUMIFS('Daily Issuance'!$O:$O,'Daily Issuance'!$I:$I,$A43,'Daily Issuance'!$E:$E,"Patty Cash",'Daily Issuance'!$B:$B,">="&DATE(2026,12,1),'Daily Issuance'!$B:$B,"<"&DATE(2027,1,1)),0) -> 0 | AO43: =SUM(AK43:AN43) -> 0 | AP43: =SUM(F43,K43,P43,U43,Z43,AE43,AJ43,AO43) -> 14620
A44: Sama No: 01 | B44: =IFERROR(SUMIFS('Daily Issuance'!$O:$O,'Daily Issuance'!$I:$I,$A44,'Daily Issuance'!$E:$E,"Inventory",'Daily Issuance'!$B:$B,">="&DATE(2026,5,1),'Daily Issuance'!$B:$B,"<"&DATE(2026,6,1)),0) -> 0 | C44: =IFERROR(SUMIFS('Daily Issuance'!$O:$O,'Daily Issuance'!$I:$I,$A44,'Daily Issuance'!$E:$E,"Non Inventory",'Daily Issuance'!$B:$B,">="&DATE(2026,5,1),'Daily Issuance'!$B:$B,"<"&DATE(2026,6,1)),0) -> 0 | D44: =IFERROR(SUMIFS('Daily Issuance'!$O:$O,'Daily Issuance'!$I:$I,$A44,'Daily Issuance'!$E:$E,"Services",'Daily Issuance'!$B:$B,">="&DATE(2026,5,1),'Daily Issuance'!$B:$B,"<"&DATE(2026,6,1)),0) -> 0 | E44: =IFERROR(SUMIFS('Daily Issuance'!$O:$O,'Daily Issuance'!$I:$I,$A44,'Daily Issuance'!$E:$E,"Patty Cash",'Daily Issuance'!$B:$B,">="&DATE(2026,5,1),'Daily Issuance'!$B:$B,"<"&DATE(2026,6,1)),0) -> 0 | F44: =SUM(B44:E44) -> 0 | G44: =IFERROR(SUMIFS('Daily Issuance'!$O$4:$O$991,'Daily Issuance'!$I$4:$I$991,$A44,'Daily Issuance'!$E$4:$E$991,"Inventory",'Daily Issuance'!$B$4:$B$991,">="&DATE(2026,6,1),'Daily Issuance'!$B$4:$B$991,"<"&DATE(2026,7,1)),0) -> 0 | H44: =IFERROR(SUMIFS('Daily Issuance'!$O$4:$O$991,'Daily Issuance'!$I$4:$I$991,$A44,'Daily Issuance'!$E$4:$E$991,"Non Inventory",'Daily Issuance'!$B$4:$B$991,">="&DATE(2026,6,1),'Daily Issuance'!$B$4:$B$991,"<"&DATE(2026,7,1)),0) -> 0 | I44: =IFERROR(SUMIFS('Daily Issuance'!$O$4:$O$991,'Daily Issuance'!$I$4:$I$991,$A44,'Daily Issuance'!$E$4:$E$991,"Services",'Daily Issuance'!$B$4:$B$991,">="&DATE(2026,6,1),'Daily Issuance'!$B$4:$B$991,"<"&DATE(2026,7,1)),0) -> 0 | J44: =IFERROR(SUMIFS('Daily Issuance'!$O:$O,'Daily Issuance'!$I:$I,$A44,'Daily Issuance'!$E:$E,"Patty Cash",'Daily Issuance'!$B:$B,">="&DATE(2026,6,1),'Daily Issuance'!$B:$B,"<"&DATE(2026,7,1)),0) -> 0 | K44: =SUM(G44:J44) -> 0 | L44: =IFERROR(SUMIFS('Daily Issuance'!$O$4:$O$991,'Daily Issuance'!$I$4:$I$991,$A44,'Daily Issuance'!$E$4:$E$991,"Inventory",'Daily Issuance'!$B$4:$B$991,">="&DATE(2026,7,1),'Daily Issuance'!$B$4:$B$991,"<"&DATE(2026,8,1)),0) -> 0 | M44: =IFERROR(SUMIFS('Daily Issuance'!$O$4:$O$991,'Daily Issuance'!$I$4:$I$991,$A44,'Daily Issuance'!$E$4:$E$991,"Non Inventory",'Daily Issuance'!$B$4:$B$991,">="&DATE(2026,7,1),'Daily Issuance'!$B$4:$B$991,"<"&DATE(2026,8,1)),0) -> 0 | N44: =IFERROR(SUMIFS('Daily Issuance'!$O$4:$O$991,'Daily Issuance'!$I$4:$I$991,$A44,'Daily Issuance'!$E$4:$E$991,"Services",'Daily Issuance'!$B$4:$B$991,">="&DATE(2026,7,1),'Daily Issuance'!$B$4:$B$991,"<"&DATE(2026,8,1)),0) -> 0 | O44: =IFERROR(SUMIFS('Daily Issuance'!$O:$O,'Daily Issuance'!$I:$I,$A44,'Daily Issuance'!$E:$E,"Patty Cash",'Daily Issuance'!$B:$B,">="&DATE(2026,7,1),'Daily Issuance'!$B:$B,"<"&DATE(2026,8,1)),0) -> 0 | P44: =SUM(L44:O44) -> 0 | Q44: =IFERROR(SUMIFS('Daily Issuance'!$O$4:$O$991,'Daily Issuance'!$I$4:$I$991,$A44,'Daily Issuance'!$E$4:$E$991,"Inventory",'Daily Issuance'!$B$4:$B$991,">="&DATE(2026,8,1),'Daily Issuance'!$B$4:$B$991,"<"&DATE(2026,9,1)),0) -> 0 | R44: =IFERROR(SUMIFS('Daily Issuance'!$O$4:$O$991,'Daily Issuance'!$I$4:$I$991,$A44,'Daily Issuance'!$E$4:$E$991,"Non Inventory",'Daily Issuance'!$B$4:$B$991,">="&DATE(2026,8,1),'Daily Issuance'!$B$4:$B$991,"<"&DATE(2026,9,1)),0) -> 0 | S44: =IFERROR(SUMIFS('Daily Issuance'!$O$4:$O$991,'Daily Issuance'!$I$4:$I$991,$A44,'Daily Issuance'!$E$4:$E$991,"Services",'Daily Issuance'!$B$4:$B$991,">="&DATE(2026,8,1),'Daily Issuance'!$B$4:$B$991,"<"&DATE(2026,9,1)),0) -> 0 | T44: =IFERROR(SUMIFS('Daily Issuance'!$O:$O,'Daily Issuance'!$I:$I,$A44,'Daily Issuance'!$E:$E,"Patty Cash",'Daily Issuance'!$B:$B,">="&DATE(2026,8,1),'Daily Issuance'!$B:$B,"<"&DATE(2026,9,1)),0) -> 0 | U44: =SUM(Q44:T44) -> 0 | V44: =IFERROR(SUMIFS('Daily Issuance'!$O$4:$O$991,'Daily Issuance'!$I$4:$I$991,$A44,'Daily Issuance'!$E$4:$E$991,"Inventory",'Daily Issuance'!$B$4:$B$991,">="&DATE(2026,9,1),'Daily Issuance'!$B$4:$B$991,"<"&DATE(2026,10,1)),0) -> 0 | W44: =IFERROR(SUMIFS('Daily Issuance'!$O$4:$O$991,'Daily Issuance'!$I$4:$I$991,$A44,'Daily Issuance'!$E$4:$E$991,"Non Inventory",'Daily Issuance'!$B$4:$B$991,">="&DATE(2026,9,1),'Daily Issuance'!$B$4:$B$991,"<"&DATE(2026,10,1)),0) -> 0 | X44: =IFERROR(SUMIFS('Daily Issuance'!$O$4:$O$991,'Daily Issuance'!$I$4:$I$991,$A44,'Daily Issuance'!$E$4:$E$991,"Services",'Daily Issuance'!$B$4:$B$991,">="&DATE(2026,9,1),'Daily Issuance'!$B$4:$B$991,"<"&DATE(2026,10,1)),0) -> 0 | Y44: =IFERROR(SUMIFS('Daily Issuance'!$O:$O,'Daily Issuance'!$I:$I,$A44,'Daily Issuance'!$E:$E,"Patty Cash",'Daily Issuance'!$B:$B,">="&DATE(2026,9,1),'Daily Issuance'!$B:$B,"<"&DATE(2026,10,1)),0) -> 0 | Z44: =SUM(V44:Y44) -> 0 | AA44: =IFERROR(SUMIFS('Daily Issuance'!$O$4:$O$991,'Daily Issuance'!$I$4:$I$991,$A44,'Daily Issuance'!$E$4:$E$991,"Inventory",'Daily Issuance'!$B$4:$B$991,">="&DATE(2026,10,1),'Daily Issuance'!$B$4:$B$991,"<"&DATE(2026,11,1)),0) -> 0 | AB44: =IFERROR(SUMIFS('Daily Issuance'!$O$4:$O$991,'Daily Issuance'!$I$4:$I$991,$A44,'Daily Issuance'!$E$4:$E$991,"Non Inventory",'Daily Issuance'!$B$4:$B$991,">="&DATE(2026,10,1),'Daily Issuance'!$B$4:$B$991,"<"&DATE(2026,11,1)),0) -> 0 | AC44: =IFERROR(SUMIFS('Daily Issuance'!$O$4:$O$991,'Daily Issuance'!$I$4:$I$991,$A44,'Daily Issuance'!$E$4:$E$991,"Services",'Daily Issuance'!$B$4:$B$991,">="&DATE(2026,10,1),'Daily Issuance'!$B$4:$B$991,"<"&DATE(2026,11,1)),0) -> 0 | AD44: =IFERROR(SUMIFS('Daily Issuance'!$O:$O,'Daily Issuance'!$I:$I,$A44,'Daily Issuance'!$E:$E,"Patty Cash",'Daily Issuance'!$B:$B,">="&DATE(2026,10,1),'Daily Issuance'!$B:$B,"<"&DATE(2026,11,1)),0) -> 0 | AE44: =SUM(AA44:AD44) -> 0 | AF44: =IFERROR(SUMIFS('Daily Issuance'!$O$4:$O$991,'Daily Issuance'!$I$4:$I$991,$A44,'Daily Issuance'!$E$4:$E$991,"Inventory",'Daily Issuance'!$B$4:$B$991,">="&DATE(2026,11,1),'Daily Issuance'!$B$4:$B$991,"<"&DATE(2026,12,1)),0) -> 0 | AG44: =IFERROR(SUMIFS('Daily Issuance'!$O$4:$O$991,'Daily Issuance'!$I$4:$I$991,$A44,'Daily Issuance'!$E$4:$E$991,"Non Inventory",'Daily Issuance'!$B$4:$B$991,">="&DATE(2026,11,1),'Daily Issuance'!$B$4:$B$991,"<"&DATE(2026,12,1)),0) -> 0 | AH44: =IFERROR(SUMIFS('Daily Issuance'!$O$4:$O$991,'Daily Issuance'!$I$4:$I$991,$A44,'Daily Issuance'!$E$4:$E$991,"Services",'Daily Issuance'!$B$4:$B$991,">="&DATE(2026,11,1),'Daily Issuance'!$B$4:$B$991,"<"&DATE(2026,12,1)),0) -> 0 | AI44: =IFERROR(SUMIFS('Daily Issuance'!$O:$O,'Daily Issuance'!$I:$I,$A44,'Daily Issuance'!$E:$E,"Patty Cash",'Daily Issuance'!$B:$B,">="&DATE(2026,11,1),'Daily Issuance'!$B:$B,"<"&DATE(2026,12,1)),0) -> 0 | AJ44: =SUM(AF44:AI44) -> 0 | AK44: =IFERROR(SUMIFS('Daily Issuance'!$O$4:$O$991,'Daily Issuance'!$I$4:$I$991,$A44,'Daily Issuance'!$E$4:$E$991,"Inventory",'Daily Issuance'!$B$4:$B$991,">="&DATE(2026,12,1),'Daily Issuance'!$B$4:$B$991,"<"&DATE(2027,1,1)),0) -> 0 | AL44: =IFERROR(SUMIFS('Daily Issuance'!$O$4:$O$991,'Daily Issuance'!$I$4:$I$991,$A44,'Daily Issuance'!$E$4:$E$991,"Non Inventory",'Daily Issuance'!$B$4:$B$991,">="&DATE(2026,12,1),'Daily Issuance'!$B$4:$B$991,"<"&DATE(2027,1,1)),0) -> 0 | AM44: =IFERROR(SUMIFS('Daily Issuance'!$O$4:$O$991,'Daily Issuance'!$I$4:$I$991,$A44,'Daily Issuance'!$E$4:$E$991,"Services",'Daily Issuance'!$B$4:$B$991,">="&DATE(2026,12,1),'Daily Issuance'!$B$4:$B$991,"<"&DATE(2027,1,1)),0) -> 0 | AN44: =IFERROR(SUMIFS('Daily Issuance'!$O:$O,'Daily Issuance'!$I:$I,$A44,'Daily Issuance'!$E:$E,"Patty Cash",'Daily Issuance'!$B:$B,">="&DATE(2026,12,1),'Daily Issuance'!$B:$B,"<"&DATE(2027,1,1)),0) -> 0 | AO44: =SUM(AK44:AN44) -> 0 | AP44: =SUM(F44,K44,P44,U44,Z44,AE44,AJ44,AO44) -> 0
